Workbook
Name acc.accountNo: #REF!
Name acc.aliasName: #REF!
Name acc.availableBalance: #REF!
Name acc.currency: #REF!
Name acc.interestRate: #REF!
Name acc.openDate: #REF!
Name acc.statusname: #REF!
Name Fx: #REF!
Name Fx: '>>Chart'!$C$1
Name Fx_rate: #REF!
Name Fx_rate: #REF!
Name Fx_rate: Summary!$B$3
Name KeywordsTable: #REF!
Name NGÂN_HÀNG_TMCP_CÔNG_THƯƠNG_VIỆT_NAM: #REF!
Name ROW___ROW_A10: #REF!
Name ROW___ROW_A25: #REF!

Sheet for email
B4: BW Industrial Development JSC
B5: Floor 17, Becamex Tower, 230 Binh Duong Boulevard,
B6: Phu Hoa Ward, Thu Dau Mot City, Binh Duong Province, Vietnam
B7: SUMMARY | F7: =F89-F106 -> 0
C8: From 22-Feb-2021 to 28-Feb-2021 | G8: From 08-Feb-2021 to 21-Feb-2021 | K8: Var | N8: From 08-Feb-2021
C9: BWID JSC | D9: VIETCO3 | E9: Subsidiaries | G9: BWID JSC | H9: VietCo3 | I9: Subsidiaries | K9: BWID JSC | L9: VietCo3 | M9: Subsidiaries
C10: Equivalent to VND bn | D10: Equivalent to VND bn | E10: Equivalent to VND bn | G10: Equivalent to VND bn | H10: Equivalent to VND bn | I10: Equivalent to VND bn | K10: Equivalent to VND bn | L10: Equivalent to VND bn | M10: Equivalent to VND bn
B11: ACTUAL
B12: Opening balance | C12: #REF! | D12: #REF! | E12: #REF! | G12: 795.97527 | H12: 0.41238947 | I12: 495.65174 | K12: =C12-G12 -> #REF! | L12: =D12-H12 -> #REF! | M12: =E12-I12 -> #REF!
B13: Cash in | C13: =SUM(C14:C15) -> 22.066935 | D13: =SUM(D14:D15) -> 2.2534909 | E13: =SUM(E14:E15) -> 114.0661 | G13: 1.1986464 | H13: 110.503 | I13: 524.29885 | K13: =C13-G13 -> 20.868288 | L13: =D13-H13 -> -108.24951 | M13: =E13-I13 -> -410.23276
B14: Rental income and bank interest | C14: 22.066935 | D14: 2.2534909 | E14: 40.771099 | G14: 1.1986464 | H14: 0 | I14: 3.5326552
B15: Shareholder loan transfer | C15: 0 | D15: 0 | E15: 73.295 | G15: 0 | H15: 110.503 | I15: 520.7662
B16: Loan drawdown
B18: Cash out | C18: =SUM(C19:C23) -> 38.055948 | D18: =SUM(D19:D23) -> 60.957728 | E18: =SUM(E19:E23) -> 132.88481 | G18: 111.56871 | H18: 110.4042 | I18: 518.58906 | K18: =C18-G18 -> -73.51276 | L18: =D18-H18 -> -49.446471 | M18: =E18-I18 -> -385.70425
B19: Land lease price payment | C19: 0 | D19: 0 | E19: 0.44709496 | G19: 0 | H19: 0 | I19: 105.38667
B20: Deal payment | C20: 0 | D20: 0 | E20: 0 | G20: 0 | H20: 0 | I20: 0
B21: Construction expense | C21: 0 | D21: 0 | E21: 36.599596 | G21: 0 | H21: 0 | I21: 2.6932629
B22: Others (G&A expenses, bank charge…) | C22: 38.055948 | D22: 21.210228 | E22: 62.290621 | G22: 1.065708 | H22: 0.0041998 | I22: 0.14293196
B23: Shareholder loan transfer | C23: 0 | D23: 39.7475 | E23: 33.5475 | G23: 110.503 | H23: 110.4 | I23: 410.3662
B25: Closing balance | C25: #REF! | D25: #REF! | E25: #REF! | G25: 795.97527 | H25: 0.41238947 | I25: 495.65174 | K25: =C25-G25 -> #REF! | L25: =D25-H25 -> #REF! | M25: =E25-I25 -> #REF!
B27: PLANNING FOR NEXT WEEK
B28: Opening balance | C28: =C25 -> #REF! | D28: =D25 -> #REF! | E28: =E25 -> #REF! | G28: 685.6052 | H28: 0.51118967 | I28: 502.62213 | K28: =C28-G28 -> #REF! | L28: =D28-H28 -> #REF! | M28: =E28-I28 -> #REF!
B29: Cash in | C29: =SUM(C30:C31) -> #REF! | D29: =SUM(D30:D31) -> #REF! | E29: =SUM(E30:E31) -> #REF! | G29: 31.608491 | H29: 0 | I29: 1.1273873 | K29: =C29-G29 -> #REF! | L29: =D29-H29 -> #REF! | M29: =E29-I29 -> #REF!
B30: - From tenants | C30: #REF! | D30: #REF! | E30: #REF! | G30: 24.470491 | H30: 0 | I30: 1.1273873 | K30: =C30-G30 -> #REF! | L30: =D30-H30 -> #REF! | M30: =E30-I30 -> #REF!
B31: - Refinancing | C31: #REF! | D31: 0 | E31: 0 | G31: 7.138 | H31: 0 | I31: 0 | K31: =C31-G31 -> #REF! | L31: =D31-H31 -> 0 | M31: =E31-I31 -> 0
B32: - Loan drawdown | K32: =C32-G32 -> 0 | L32: =D32-H32 -> 0 | M32: =E32-I32 -> 0
B33: Significant cash out | C33: =C35 -> #REF! | D33: =D35 -> 0 | E33: =E35 -> #REF! | G33: 125.52862 | H33: 0 | I33: 175.64445 | K33: =C33-G33 -> #REF! | L33: =D33-H33 -> 0 | M33: =E33-I33 -> #REF!
B34: - For investment deals | K34: =C34-G34 -> 0 | L34: =D34-H34 -> 0 | M34: =E34-I34 -> 0
B35: - For construction | C35: #REF! | D35: 0 | E35: #REF! | G35: 125.52862 | H35: 0 | I35: 175.64445 | K35: =C35-G35 -> #REF! | L35: =D35-H35 -> 0 | M35: =E35-I35 -> #REF!
B36: Surplus (+)/ Shortage (-) | C36: =C28+C29-C33 -> #REF! | D36: =D28+D29-D33 -> #REF! | E36: =E28+E29-E33 -> #REF! | G36: 591.68507 | H36: 0.51118967 | I36: 328.10507 | K36: =C36-G36 -> #REF! | L36: =D36-H36 -> #REF! | M36: =E36-I36 -> #REF!
C39: From 1-May-2024 to 18-May-2024 | G39: From 16-Apr-2024 to 30-Apr-2024 | K39: Variance
C40: BWID JSC | D40: VIETCO3 | E40: Subsidiaries | F40: Total | G40: BWID JSC | H40: VIETCO3 | I40: Subsidiaries | J40: Total | K40: BWID JSC | L40: VIETCO3 | M40: Subsidiaries | N40: Total
C41: Equivalent to USD mn | D41: Equivalent to USD mn | E41: Equivalent to USD mn | F41: Equivalent to USD mn | G41: Equivalent to USD mn | H41: Equivalent to USD mn | I41: Equivalent to USD mn | J41: Equivalent to USD mn | K41: Equivalent to USD mn | L41: Equivalent to USD mn | M41: Equivalent to USD mn | N41: Equivalent to USD mn
B42: ACTUAL
B43: Opening balance | C43: =G77-C110 -> 6.9899194 | D43: =H77-D110 -> 9.7598303 | E43: =I77-E110 -> 68.245747 | F43: =SUM(C43:E43) -> 84.995497 | G43: 6.9991763 | H43: 8.3059755 | I43: 76.97239 | J43: 92.277542 | O43: =F43+F75-Summary!E77 -> -49.525552
B45: Cash in | C45: =SUM(C47:C59) -> 2.3013678 | D45: =SUM(D47:D59) -> 52.043071 | E45: =SUM(E47:E59) -> 18.406773 | F45: =SUM(F47:F59) -> 72.751212 | G45: 2.6427603 | H45: 7.6943171 | I45: 46.043402 | J45: 56.380479 | K45: =C45-G45 -> -0.34139243 | L45: =D45-H45 -> 44.348754 | M45: =E45-I45 -> -27.636629 | N45: =F45-J45 -> 16.370733
B46: Actual Cash IN | C46: =C45-C49-C53-C54 -> 0.0091042269 | D46: =D45-D49-D53-D54 -> 0.2487225 | E46: =E45-E49-E53-E54 -> 12.413848 | F46: =F45-F49-F53-F54 -> 12.671675 | G46: 0.33506796 | H46: 0.010776304 | I46: 10.591504 | J46: 10.937348 | K46: =C46-G46 -> -0.32596373 | L46: =D46-H46 -> 0.2379462 | M46: =E46-I46 -> 1.8223441 | N46: =F46-J46 -> 1.7343265
B47: Receipt from tenants | C47: =IFERROR(VLOOKUP($B47,Summary!$A$80:$D$94,2,0),0) -> 0 | D47: =IFERROR(VLOOKUP($B47,Summary!$A$80:$D$94,3,0),0) -> 0.23338632 | E47: =IFERROR(VLOOKUP($B47,Summary!$A$80:$D$94,4,0),0) -> 12.252736 | F47: =SUM(C47:E47) -> 12.486122 | G47: 0.32124667 | H47: 0 | I47: 10.446865 | J47: 10.768112 | K47: =C47-G47 -> -0.32124667 | L47: =D47-H47 -> 0.23338632 | M47: =E47-I47 -> 1.8058709 | N47: =F47-J47 -> 1.7180105
B48: Refund land/deal deposit payment | C48: =IFERROR(VLOOKUP($B48,Summary!$A$80:$D$94,2,0),0) -> 0 | D48: =IFERROR(VLOOKUP($B48,Summary!$A$80:$D$94,3,0),0) -> 0 | E48: =IFERROR(VLOOKUP($B48,Summary!$A$80:$D$94,4,0),0) -> 0 | F48: =SUM(C48:E48) -> 0 | G48: 0 | H48: 0 | I48: 0 | J48: 0 | K48: =C48-G48 -> 0 | L48: =D48-H48 -> 0 | M48: =E48-I48 -> 0 | N48: =F48-J48 -> 0
B49: Internal transfer in | C49: =IFERROR(VLOOKUP($B49,Summary!$A$80:$D$94,2,0),0) -> 2.2922636 | D49: =IFERROR(VLOOKUP($B49,Summary!$A$80:$D$94,3,0),0) -> 51.794349 | E49: =IFERROR(VLOOKUP($B49,Summary!$A$80:$D$94,4,0),0) -> 5.9929246 | F49: =SUM(C49:E49) -> 60.079537 | G49: 2.3076923 | H49: 7.6835408 | I49: 35.451898 | J49: 45.443131 | K49: =C49-G49 -> -0.015428697 | L49: =D49-H49 -> 44.110808 | M49: =E49-I49 -> -29.458973 | N49: =F49-J49 -> 14.636406
B50: Refinancing | C50: =IFERROR(VLOOKUP($B50,Summary!$A$80:$D$94,2,0),0) -> 0 | D50: =IFERROR(VLOOKUP($B50,Summary!$A$80:$D$94,3,0),0) -> 0 | E50: =IFERROR(VLOOKUP($B50,Summary!$A$80:$D$94,4,0),0) -> 0 | F50: =SUM(C50:E50) -> 0 | G50: 0 | H50: 0 | I50: 0 | J50: 0 | K50: =C50-G50 -> 0 | L50: =D50-H50 -> 0 | M50: =E50-I50 -> 0 | N50: =F50-J50 -> 0
B51: VAT refund | C51: =IFERROR(VLOOKUP($B51,Summary!$A$80:$D$94,2,0),0) -> 0 | D51: =IFERROR(VLOOKUP($B51,Summary!$A$80:$D$94,3,0),0) -> 0 | E51: =IFERROR(VLOOKUP($B51,Summary!$A$80:$D$94,4,0),0) -> 0 | F51: =SUM(C51:E51) -> 0 | G51: 0 | H51: 0 | I51: 0 | J51: 0 | K51: =C51-G51 -> 0 | L51: =D51-H51 -> 0 | M51: =E51-I51 -> 0 | N51: =F51-J51 -> 0
B52: Other receipts | C52: =IFERROR(VLOOKUP($B52,Summary!$A$80:$D$94,2,0),0) -> 0.0091042269 | D52: =IFERROR(VLOOKUP($B52,Summary!$A$80:$D$94,3,0),0) -> 0.015336186 | E52: =IFERROR(VLOOKUP($B52,Summary!$A$80:$D$94,4,0),0) -> 0.16111207 | F52: =SUM(C52:E52) -> 0.18555249 | G52: 0.013821284 | H52: 0.010776304 | I52: 0.14463886 | J52: 0.16923645 | K52: =C52-G52 -> -0.0047170567 | L52: =D52-H52 -> 0.0045598818 | M52: =E52-I52 -> 0.01647321 | N52: =F52-J52 -> 0.016316035
B53: Internal contribution in | C53: =IFERROR(VLOOKUP($B53,Summary!$A$80:$D$94,2,0),0) -> 0 | D53: =IFERROR(VLOOKUP($B53,Summary!$A$80:$D$94,3,0),0) -> 0 | E53: =IFERROR(VLOOKUP($B53,Summary!$A$80:$D$94,4,0),0) -> 0 | F53: =SUM(C53:E53) -> 0 | G53: 0 | H53: 0 | I53: 0 | J53: 0 | K53: =C53-G53 -> 0 | L53: =D53-H53 -> 0 | M53: =E53-I53 -> 0 | N53: =F53-J53 -> 0
B54: Dividend receipt (inside group) | C54: =IFERROR(VLOOKUP($B54,Summary!$A$80:$D$94,2,0),0) -> 0 | D54: =IFERROR(VLOOKUP($B54,Summary!$A$80:$D$94,3,0),0) -> 0 | E54: =IFERROR(VLOOKUP($B54,Summary!$A$80:$D$94,4,0),0) -> 0 | F54: =SUM(C54:E54) -> 0 | G54: 0 | H54: 0 | I54: 0 | J54: 0 | K54: =C54-G54 -> 0 | L54: =D54-H54 -> 0 | M54: =E54-I54 -> 0 | N54: =F54-J54 -> 0
B55: Contribution | C55: =IFERROR(VLOOKUP($B55,Summary!$A$80:$D$94,2,0),0) -> 0 | D55: =IFERROR(VLOOKUP($B55,Summary!$A$80:$D$94,3,0),0) -> 0 | E55: =IFERROR(VLOOKUP($B55,Summary!$A$80:$D$94,4,0),0) -> 0 | F55: =SUM(C55:E55) -> 0 | G55: 0 | H55: 0 | I55: 0 | J55: 0 | K55: =C55-G55 -> 0 | L55: =D55-H55 -> 0 | M55: =E55-I55 -> 0 | N55: =F55-J55 -> 0
B56: Cash received from acquisition | C56: =IFERROR(VLOOKUP($B56,Summary!$A$80:$D$94,2,0),0) -> 0 | D56: =IFERROR(VLOOKUP($B56,Summary!$A$80:$D$94,3,0),0) -> 0 | E56: =IFERROR(VLOOKUP($B56,Summary!$A$80:$D$94,4,0),0) -> 0 | F56: =SUM(C56:E56) -> 0 | G56: 0 | H56: 0 | I56: 0 | J56: 0 | K56: =C56-G56 -> 0 | L56: =D56-H56 -> 0 | M56: =E56-I56 -> 0 | N56: =F56-J56 -> 0
B57: Loan receipts | C57: =IFERROR(VLOOKUP($B57,Summary!$A$80:$D$94,2,0),0) -> 0 | D57: =IFERROR(VLOOKUP($B57,Summary!$A$80:$D$94,3,0),0) -> 0 | E57: =IFERROR(VLOOKUP($B57,Summary!$A$80:$D$94,4,0),0) -> 0 | F57: =SUM(C57:E57) -> 0 | G57: 0 | H57: 0 | I57: 0 | J57: 0 | K57: =C57-G57 -> 0 | L57: =D57-H57 -> 0 | M57: =E57-I57 -> 0 | N57: =F57-J57 -> 0
B58: Loan drawdown | C58: =IFERROR(VLOOKUP($B58,Summary!$A$80:$D$94,2,0),0) -> 0 | D58: =IFERROR(VLOOKUP($B58,Summary!$A$80:$D$94,3,0),0) -> 0 | E58: =IFERROR(VLOOKUP($B58,Summary!$A$80:$D$94,4,0),0) -> 0 | F58: =SUM(C58:E58) -> 0 | G58: 0 | H58: 0 | I58: 0 | J58: 0 | K58: =C58-G58 -> 0 | L58: =D58-H58 -> 0 | M58: =E58-I58 -> 0 | N58: =F58-J58 -> 0
B59: Corporate Loan drawdown | C59: =IFERROR(VLOOKUP($B59,Summary!$A$80:$D$94,2,0),0) -> 0 | D59: =IFERROR(VLOOKUP($B59,Summary!$A$80:$D$94,3,0),0) -> 0 | E59: =IFERROR(VLOOKUP($B59,Summary!$A$80:$D$94,4,0),0) -> 0 | F59: =SUM(C59:E59) -> 0 | G59: 0 | H59: 0 | I59: 0 | J59: 0 | K59: =C59-G59 -> 0 | L59: =D59-H59 -> 0 | M59: =E59-I59 -> 0 | N59: =F59-J59 -> 0
K60: =C60-G60 -> 0 | L60: =D60-H60 -> 0 | M60: =E60-I60 -> 0
B61: Cash out | C61: =SUM(C63:C73) -> 2.3351174 | D61: =SUM(D63:D73) -> 33.506281 | E61: =SUM(E63:E73) -> 9.2846846 | F61: =SUM(F63:F73) -> 45.126083 | G61: 2.6520172 | H61: 6.2404623 | I61: 54.770045 | J61: 63.662524 | K61: =C61-G61 -> -0.31689976 | L61: =D61-H61 -> 27.265818 | M61: =E61-I61 -> -45.48536 | N61: =F61-J61 -> -18.536441
B62: Actual Cash OUT | C62: =C61-C69-C73-C70 -> 0.042853812 | D62: =D61-D69-D73-D70 -> 0.14358122 | E62: =E61-E69-E73-E70 -> 7.7827467 | F62: =F61-F69-F73-F70 -> 7.9691818 | G62: 0.34432487 | H62: 0.84315459 | I62: 17.031914 | J62: 18.219393 | K62: =C62-G62 -> -0.30147106 | L62: =D62-H62 -> -0.69957337 | M62: =E62-I62 -> -9.2491669 | N62: =F62-J62 -> -10.250211
B63: Land acquisition | C63: =-IFERROR(VLOOKUP($B63,Summary!$A$95:$D$104,2,0),0) -> 0 | D63: =-IFERROR(VLOOKUP($B63,Summary!$A$95:$D$104,3,0),0) -> 0 | E63: =-IFERROR(VLOOKUP($B63,Summary!$A$95:$D$104,4,0),0) -> 0 | F63: =SUM(C63:E63) -> 0 | G63: 0 | H63: 0 | I63: 0.57191903 | J63: 0.57191903 | K63: =C63-G63 -> 0 | L63: =D63-H63 -> 0 | M63: =E63-I63 -> -0.57191903 | N63: =F63-J63 -> -0.57191903
B64: Deal payment | C64: =-IFERROR(VLOOKUP($B64,Summary!$A$95:$D$104,2,0),0) -> 0 | D64: =-IFERROR(VLOOKUP($B64,Summary!$A$95:$D$104,3,0),0) -> 0 | E64: =-IFERROR(VLOOKUP($B64,Summary!$A$95:$D$104,4,0),0) -> 0 | F64: =SUM(C64:E64) -> 0 | G64: 0 | H64: 0 | I64: 0 | J64: 0 | K64: =C64-G64 -> 0 | L64: =D64-H64 -> 0 | M64: =E64-I64 -> 0 | N64: =F64-J64 -> 0
B65: Construction expense | C65: =-IFERROR(VLOOKUP($B65,Summary!$A$95:$D$104,2,0),0) -> 0 | D65: =-IFERROR(VLOOKUP($B65,Summary!$A$95:$D$104,3,0),0) -> 0 | E65: =-IFERROR(VLOOKUP($B65,Summary!$A$95:$D$104,4,0),0) -> 4.8135884 | F65: =SUM(C65:E65) -> 4.8135884 | G65: 0 | H65: 0 | I65: 0.27192801 | J65: 0.27192801 | K65: =C65-G65 -> 0 | L65: =D65-H65 -> 0 | M65: =E65-I65 -> 4.5416604 | N65: =F65-J65 -> 4.5416604
B66: Operating expense | C66: =-IFERROR(VLOOKUP($B66,Summary!$A$95:$D$104,2,0),0) -> 0.042853812 | D66: =-IFERROR(VLOOKUP($B66,Summary!$A$95:$D$104,3,0),0) -> 0.14358122 | E66: =-IFERROR(VLOOKUP($B66,Summary!$A$95:$D$104,4,0),0) -> 2.896553 | F66: =SUM(C66:E66) -> 3.082988 | G66: 0.060281802 | H66: 0.84315459 | I66: 2.6554316 | J66: 3.558868 | K66: =C66-G66 -> -0.017427989 | L66: =D66-H66 -> -0.69957337 | M66: =E66-I66 -> 0.24112137 | N66: =F66-J66 -> -0.47587999
B67: Loan repayment | C67: =-IFERROR(VLOOKUP($B67,Summary!$A$95:$D$104,2,0),0) -> 0 | D67: =-IFERROR(VLOOKUP($B67,Summary!$A$95:$D$104,3,0),0) -> 0 | E67: =-IFERROR(VLOOKUP($B67,Summary!$A$95:$D$104,4,0),0) -> 0.072605406 | F67: =SUM(C67:E67) -> 0.072605406 | G67: 0 | H67: 0 | I67: 0.36661538 | J67: 0.36661538 | K67: =C67-G67 -> 0 | L67: =D67-H67 -> 0 | M67: =E67-I67 -> -0.29400998 | N67: =F67-J67 -> -0.29400998
B68: Loan interest | C68: =-IFERROR(VLOOKUP($B68,Summary!$A$95:$D$104,2,0),0) -> 0 | D68: =-IFERROR(VLOOKUP($B68,Summary!$A$95:$D$104,3,0),0) -> 0 | E68: =-IFERROR(VLOOKUP($B68,Summary!$A$95:$D$104,4,0),0) -> 0 | F68: =SUM(C68:E68) -> 0 | G68: 0.28404307 | H68: 0 | I68: 13.16602 | J68: 13.450063 | K68: =C68-G68 -> -0.28404307 | L68: =D68-H68 -> 0 | M68: =E68-I68 -> -13.16602 | N68: =F68-J68 -> -13.450063
B69: Internal contribution out | C69: =-IFERROR(VLOOKUP($B69,Summary!$A$95:$D$104,2,0),0) -> 0 | D69: =-IFERROR(VLOOKUP($B69,Summary!$A$95:$D$104,3,0),0) -> 0 | E69: =-IFERROR(VLOOKUP($B69,Summary!$A$95:$D$104,4,0),0) -> 0 | F69: =SUM(C69:E69) -> 0 | G69: 0 | H69: 0 | I69: 0 | J69: 0 | K69: =C69-G69 -> 0 | L69: =D69-H69 -> 0 | M69: =E69-I69 -> 0 | N69: =F69-J69 -> 0
B70: Dividend paid (inside group) | C70: =-IFERROR(VLOOKUP($B70,Summary!$A$95:$D$104,2,0),0) -> 0 | D70: =-IFERROR(VLOOKUP($B70,Summary!$A$95:$D$104,3,0),0) -> 0 | E70: =-IFERROR(VLOOKUP($B70,Summary!$A$95:$D$104,4,0),0) -> 0 | F70: =SUM(C70:E70) -> 0 | G70: 0 | H70: 0 | I70: 0 | J70: 0 | K70: =C70-G70 -> 0 | L70: =D70-H70 -> 0 | M70: =E70-I70 -> 0 | N70: =F70-J70 -> 0
B71: Contribution | C71: =-IFERROR(VLOOKUP($B71,Summary!$A$95:$D$104,2,0),0) -> 0 | D71: =-IFERROR(VLOOKUP($B71,Summary!$A$95:$D$104,3,0),0) -> 0 | E71: =-IFERROR(VLOOKUP($B71,Summary!$A$95:$D$104,4,0),0) -> 0 | F71: =SUM(C71:E71) -> 0 | G71: 0 | H71: 0 | I71: 0 | J71: 0 | K71: =C71-G71 -> 0 | L71: =D71-H71 -> 0 | M71: =E71-I71 -> 0 | N71: =F71-J71 -> 0
B72: Payment for acquisition | C72: =-IFERROR(VLOOKUP($B72,Summary!$A$95:$D$106,2,0),0) -> 0 | D72: =-IFERROR(VLOOKUP($B72,Summary!$A$95:$D$106,3,0),0) -> 0 | E72: =-IFERROR(VLOOKUP($B72,Summary!$A$95:$D$106,4,0),0) -> 0 | F72: =SUM(C72:E72) -> 0 | G72: 0 | H72: 0 | I72: 0 | J72: 0 | K72: =C72-G72 -> 0 | L72: =D72-H72 -> 0 | M72: =E72-I72 -> 0 | N72: =F72-J72 -> 0
B73: Internal transfer out | C73: =-IFERROR(VLOOKUP($B73,Summary!$A$95:$D$104,2,0),0) -> 2.2922636 | D73: =-IFERROR(VLOOKUP($B73,Summary!$A$95:$D$104,3,0),0) -> 33.362699 | E73: =-IFERROR(VLOOKUP($B73,Summary!$A$95:$D$104,4,0),0) -> 1.5019379 | F73: =SUM(C73:E73) -> 37.156901 | G73: 2.3076923 | H73: 5.3973077 | I73: 37.738131 | J73: 45.443131 | K73: =C73-G73 -> -0.015428697 | L73: =D73-H73 -> 27.965392 | M73: =E73-I73 -> -36.236193 | N73: =F73-J73 -> -8.28623
B75: Change FX rate of report | K75: =C75-G75 -> 0 | L75: =D75-H75 -> 0 | M75: =E75-I75 -> 0 | N75: =F75-J75 -> 0
K76: =C76-G76 -> 0 | L76: =D76-H76 -> 0 | M76: =E76-I76 -> 0
B77: Closing balance | C77: =C43+C45-C61+C75 -> 6.9561698 | D77: =D43+D45-D61+D75 -> 28.296621 | E77: =E43+E45-E61+E75 -> 77.367835 | F77: =F43+F45-F61+F75 -> 112.62063 | G77: 6.9899194 | H77: 9.7598303 | I77: 68.245747 | J77: 84.995497 | K77: =C77-G77 -> -0.033749585 | L77: =D77-H77 -> 18.536791 | M77: =E77-I77 -> 9.122088 | N77: =F77-J77 -> 27.625129 | O77: =F77-Summary!E107 -> -49.525552
B79: Blocked Amount
B80: Available cash | C80: =C77-C79 -> 6.9561698 | D80: =D77-D79 -> 28.296621 | E80: =E77-E79 -> 77.367835 | F80: =F77-F79 -> 112.62063 | G80: 6.9991763 | H80: 8.3059755 | I80: 76.97239 | J80: 92.277542
B83: PLANNING FOR UPCOMING 1 MONTH
B84: Opening balance | C84: =C80 -> 6.9561698 | D84: =D80 -> 28.296621 | E84: =E80 -> 77.367835 | F84: =SUM(C84:E84) -> 112.62063
B86: Cash in | C86: =SUM(C87:C96)-C89 -> 0.95602924 | D86: =SUM(D87:D96)-D89 -> 39.131805 | E86: =SUM(E87:E96)-E89 -> 13.422003 | F86: =SUM(F87:F96)-F89 -> 53.509837 | O86: =Summary!E210=F86 -> TRUE | P86: =Summary!E209-F86 -> 0 | Q86: =P86-'Cash Planning'!AQ13/10^6 -> 0
B87: Receipt from tenants | C87: =IFERROR(VLOOKUP($B87,Summary!$A$211:$D$235,2,0),0) -> 0.95602924 | D87: =IFERROR(VLOOKUP($B87,Summary!$A$211:$D$235,3,0),0) -> 0 | E87: =IFERROR(VLOOKUP($B87,Summary!$A$211:$D$235,4,0),0) -> 13.013216 | F87: =SUM(C87:E87) -> 13.969245
B88: Refund land/deal deposit payment | C88: =IFERROR(VLOOKUP($B88,Summary!$A$211:$D$235,2,0),0) -> 0 | D88: =IFERROR(VLOOKUP($B88,Summary!$A$211:$D$235,3,0),0) -> 0 | E88: =IFERROR(VLOOKUP($B88,Summary!$A$211:$D$235,4,0),0) -> 0 | F88: =SUM(C88:E88) -> 0
B89: Internal transfer | C89: =IFERROR(VLOOKUP($B89,Summary!$A$211:$D$235,2,0),0) -> 0 | D89: =IFERROR(VLOOKUP($B89,Summary!$A$211:$D$235,3,0),0) -> 0 | E89: =IFERROR(VLOOKUP($B89,Summary!$A$211:$D$235,4,0),0) -> 0 | F89: =SUM(C89:E89) -> 0
B90: Refinancing | C90: =IFERROR(VLOOKUP($B90,Summary!$A$211:$D$235,2,0),0) -> 0 | D90: =IFERROR(VLOOKUP($B90,Summary!$A$211:$D$235,3,0),0) -> 39.131805 | E90: =IFERROR(VLOOKUP($B90,Summary!$A$211:$D$235,4,0),0) -> 0 | F90: =SUM(C90:E90) -> 39.131805
B91: Corporate Loan drawdown | C91: =IFERROR(VLOOKUP($B91,Summary!$A$211:$D$235,2,0),0) -> 0 | D91: =IFERROR(VLOOKUP($B91,Summary!$A$211:$D$235,3,0),0) -> 0 | E91: =IFERROR(VLOOKUP($B91,Summary!$A$211:$D$235,4,0),0) -> 0 | F91: =SUM(C91:E91) -> 0
B92: Loan drawdown | C92: =IFERROR(VLOOKUP($B92,Summary!$A$211:$D$235,2,0),0) -> 0 | D92: =IFERROR(VLOOKUP($B92,Summary!$A$211:$D$235,3,0),0) -> 0 | E92: =IFERROR(VLOOKUP($B92,Summary!$A$211:$D$235,4,0),0) -> 0 | F92: =SUM(C92:E92) -> 0
B93: VAT refund | C93: =IFERROR(VLOOKUP($B93,Summary!$A$211:$D$235,2,0),0) -> 0 | D93: =IFERROR(VLOOKUP($B93,Summary!$A$211:$D$235,3,0),0) -> 0 | E93: =IFERROR(VLOOKUP($B93,Summary!$A$211:$D$235,4,0),0) -> 0.40878701 | F93: =SUM(C93:E93) -> 0.40878701
B94: Receipt from share acquisition | C94: =IFERROR(VLOOKUP($B94,Summary!$A$211:$D$235,2,0),0) -> 0 | D94: =IFERROR(VLOOKUP($B94,Summary!$A$211:$D$235,3,0),0) -> 0 | E94: =IFERROR(VLOOKUP($B94,Summary!$A$211:$D$235,4,0),0) -> 0 | F94: =SUM(C94:E94) -> 0
B95: Management fee from subsidiaries | C95: =IFERROR(VLOOKUP($B95,Summary!$A$211:$D$235,2,0),0) -> 0 | D95: =IFERROR(VLOOKUP($B95,Summary!$A$211:$D$235,3,0),0) -> 0 | E95: =IFERROR(VLOOKUP($B95,Summary!$A$211:$D$235,4,0),0) -> 0 | F95: =SUM(C95:E95) -> 0
B96: Contribution | C96: =IFERROR(VLOOKUP($B96,Summary!$A$211:$D$235,2,0),0) -> 0 | D96: =IFERROR(VLOOKUP($B96,Summary!$A$211:$D$235,3,0),0) -> 0 | E96: =IFERROR(VLOOKUP($B96,Summary!$A$211:$D$235,4,0),0) -> 0 | F96: =SUM(C96:E96) -> 0
B98: Cash out | C98: =SUM(C99:C106)-C105-C106 -> 0.55684545 | D98: =SUM(D99:D106)-D105-D106 -> 13.481939 | E98: =SUM(E99:E106)-E105-E106 -> 3.426514 | F98: =SUM(F99:F106)-F105-F106 -> 17.465298 | O98: =-Summary!E225=F98 -> TRUE | P98: =-Summary!E224-F98 -> 0 | Q98: =P98-'Cash Planning'!AQ13/10^6 -> 0
B99: Land acquisition | C99: =-IFERROR(VLOOKUP($B99,Summary!$A$211:$D$235,2,0),0) -> 0 | D99: =-IFERROR(VLOOKUP($B99,Summary!$A$211:$D$235,3,0),0) -> 2.6147178 | E99: =-IFERROR(VLOOKUP($B99,Summary!$A$211:$D$235,4,0),0) -> 0 | F99: =SUM(C99:E99) -> 2.6147178
B100: Deal payment | C100: =-IFERROR(VLOOKUP($B100,Summary!$A$211:$D$235,2,0),0) -> 0 | D100: =-IFERROR(VLOOKUP($B100,Summary!$A$211:$D$235,3,0),0) -> 3.9312248 | E100: =-IFERROR(VLOOKUP($B100,Summary!$A$211:$D$235,4,0),0) -> 0.98191595 | F100: =SUM(C100:E100) -> 4.9131408
B101: Construction expense | C101: =-IFERROR(VLOOKUP($B101,Summary!$A$211:$D$235,2,0),0) -> 0 | D101: =-IFERROR(VLOOKUP($B101,Summary!$A$211:$D$235,3,0),0) -> 2.0063472 | E101: =-IFERROR(VLOOKUP($B101,Summary!$A$211:$D$235,4,0),0) -> 0.21638955 | F101: =SUM(C101:E101) -> 2.2227368
B102: Operating expense | C102: =-IFERROR(VLOOKUP($B102,Summary!$A$211:$D$235,2,0),0) -> 0 | D102: =-IFERROR(VLOOKUP($B102,Summary!$A$211:$D$235,3,0),0) -> 3.0353603 | E102: =-IFERROR(VLOOKUP($B102,Summary!$A$211:$D$235,4,0),0) -> 0.32652383 | F102: =SUM(C102:E102) -> 3.3618842
B103: Loan repayment | C103: =-IFERROR(VLOOKUP($B103,Summary!$A$211:$D$235,2,0),0) -> 0 | D103: =-IFERROR(VLOOKUP($B103,Summary!$A$211:$D$235,3,0),0) -> 0.5730659 | E103: =-IFERROR(VLOOKUP($B103,Summary!$A$211:$D$235,4,0),0) -> 0.85866335 | F103: =SUM(C103:E103) -> 1.4317292
B104: Loan interest | C104: =-IFERROR(VLOOKUP($B104,Summary!$A$211:$D$235,2,0),0) -> 0.55684545 | D104: =-IFERROR(VLOOKUP($B104,Summary!$A$211:$D$235,3,0),0) -> 1.3212228 | E104: =-IFERROR(VLOOKUP($B104,Summary!$A$211:$D$235,4,0),0) -> 1.0430213 | F104: =SUM(C104:E104) -> 2.9210895
B105: Contribution | C105: =-IFERROR(VLOOKUP($B105,Summary!$A$211:$D$235,2,0),0) -> 0 | D105: =-IFERROR(VLOOKUP($B105,Summary!$A$211:$D$235,3,0),0) -> 0 | E105: =-IFERROR(VLOOKUP($B105,Summary!$A$211:$D$235,4,0),0) -> 0 | F105: =SUM(C105:E105) -> 0
B106: Internal transfer | C106: =-Summary!B234 -> 0 | D106: =-Summary!C234 -> 0 | E106: =-Summary!D234 -> 0 | F106: =SUM(C106:E106) -> 0
B108: Surplus (+)/ Shortage (-) | C108: =C84+C86-C98 -> 7.3553536 | D108: =D84+D86-D98 -> 53.946487 | E108: =E84+E86-E98 -> 87.363324 | F108: =F84+F86-F98 -> 148.66516

Sheet >>Chart
C1: =Fx_rate -> 26175 | D1: BWID JSC | E1: BWID JSC | F1: BWID JSC | G1: VC3 | H1: VC3 | I1: VC3 | J1: VC3 | K1: Subsidiaries | L1: Subsidiaries | M1: Subsidiaries | N1: TOTAL
C2: Bank | D2: BW_VND_bn | E2: BW_USD_mn | F2: BW_Total_USD_mn | G2: VC3_VND_bn | H2: VC3_USD_mn | I2: VC3_Total_USD_mn | J2: VC3_Total_VND (bn) | K2: SUB_VND_bn | L2: SUB_USD_mn | M2: SUB_TOTAL_USD_mn | N2: VND | O2: USD | P2: Total | Q2: CREDIT FACILITY | R2: OUT. LOAN BALANCE @30/11/22 | S2: %
S3: %
C4: VIETINBANK - TIEN SON | D4: =SUMIFS('Cash Balance'!$L$4:$L$920,'Cash Balance'!$Y$4:$Y$920,'>>Chart'!$C4,'Cash Balance'!$W$4:$W$920,'>>Chart'!D$1)/1000000000 -> 0.029039515 | E4: =SUMIFS('Cash Balance'!$T$4:$T$920,'Cash Balance'!$Y$4:$Y$920,'>>Chart'!$C4,'Cash Balance'!$W$4:$W$920,'>>Chart'!E$1)/1000000 -> 0.0002 | F4: {=D4*1000/Fx+E4} -> 0.0013094371 | G4: =SUMIFS('Cash Balance'!$L$4:$L$920,'Cash Balance'!$Y$4:$Y$920,'>>Chart'!$C4,'Cash Balance'!$W$4:$W$920,'>>Chart'!G$1)/1000000000 -> 261.65697 | H4: =SUMIFS('Cash Balance'!$T$4:$T$920,'Cash Balance'!$Y$4:$Y$920,'>>Chart'!$C4,'Cash Balance'!$W$4:$W$920,'>>Chart'!H$1)/1000000 -> 0.00043853 | I4: =G4/Fx*1000+H4 -> 9.9968845 | J4: =G4+H4*Fx/1000 -> 261.66845 | K4: =SUMIFS('Cash Balance'!$L$4:$L$920,'Cash Balance'!$Y$4:$Y$920,'>>Chart'!$C4,'Cash Balance'!$W$4:$W$920,'>>Chart'!K$1)/1000000000 -> 538.68454 | L4: =SUMIFS('Cash Balance'!$T$4:$T$920,'Cash Balance'!$Y$4:$Y$920,'>>Chart'!$C4,'Cash Balance'!$W$4:$W$920,'>>Chart'!L$1)/1000000 -> 0.03067331 | M4: =K4*1000/Fx+L4 -> 20.61079 | N4: =D4+G4+K4 -> 800.37055 | O4: =E4+H4+L4 -> 0.03131184 | P4: =N4*1000/Fx+O4 -> 30.608983 | Q4: =SUMIFS(#REF!,#REF!,'>>Chart'!C4) -> #REF! | R4: =SUMIFS(#REF!,#REF!,'>>Chart'!C4) -> #REF! | S4: =Q4/$Q$18 -> #REF!
C5: VIETINBANK - CN1 | D5: =SUMIFS('Cash Balance'!$L$4:$L$920,'Cash Balance'!$Y$4:$Y$920,'>>Chart'!$C5,'Cash Balance'!$W$4:$W$920,'>>Chart'!D$1)/1000000000 -> 0.0908675 | E5: =SUMIFS('Cash Balance'!$T$4:$T$920,'Cash Balance'!$Y$4:$Y$920,'>>Chart'!$C5,'Cash Balance'!$W$4:$W$920,'>>Chart'!E$1)/1000000 -> 0.00074833 | F5: =D5*1000/Fx+E5 -> 0.0042198677 | G5: =SUMIFS('Cash Balance'!$L$4:$L$920,'Cash Balance'!$Y$4:$Y$920,'>>Chart'!$C5,'Cash Balance'!$W$4:$W$920,'>>Chart'!G$1)/1000000000 -> 0.17254312 | H5: =SUMIFS('Cash Balance'!$T$4:$T$920,'Cash Balance'!$Y$4:$Y$920,'>>Chart'!$C5,'Cash Balance'!$W$4:$W$920,'>>Chart'!H$1)/1000000 -> 0.00054176 | I5: =G5/Fx*1000+H5 -> 0.0071336651 | J5: =G5+H5*Fx/1000 -> 0.18672368 | K5: =SUMIFS('Cash Balance'!$L$4:$L$920,'Cash Balance'!$Y$4:$Y$920,'>>Chart'!$C5,'Cash Balance'!$W$4:$W$920,'>>Chart'!K$1)/1000000000 -> 58.610553 | L5: =SUMIFS('Cash Balance'!$T$4:$T$920,'Cash Balance'!$Y$4:$Y$920,'>>Chart'!$C5,'Cash Balance'!$W$4:$W$920,'>>Chart'!L$1)/1000000 -> 0 | M5: =K5*1000/Fx+L5 -> 2.2391806 | N5: =D5+G5+K5 -> 58.873963 | O5: =E5+H5+L5 -> 0.00129009 | P5: =N5*1000/Fx+O5 -> 2.2505342 | Q5: =SUMIFS(#REF!,#REF!,'>>Chart'!C5) -> #REF! | R5: =SUMIFS(#REF!,#REF!,'>>Chart'!C5) -> #REF! | S5: =Q5/$Q$18 -> #REF!
C6: VIETINBANK - BINH DUONG + QM | D6: =SUMIFS('Cash Balance'!$L$4:$L$920,'Cash Balance'!$Y$4:$Y$920,'>>Chart'!$C6,'Cash Balance'!$W$4:$W$920,'>>Chart'!D$1)/1000000000 -> 6.9729213 | E6: =SUMIFS('Cash Balance'!$T$4:$T$920,'Cash Balance'!$Y$4:$Y$920,'>>Chart'!$C6,'Cash Balance'!$W$4:$W$920,'>>Chart'!E$1)/1000000 -> 0.00170392 | F6: =D6*1000/Fx+E6 -> 0.26810015 | G6: =SUMIFS('Cash Balance'!$L$4:$L$920,'Cash Balance'!$Y$4:$Y$920,'>>Chart'!$C6,'Cash Balance'!$W$4:$W$920,'>>Chart'!G$1)/1000000000 -> 110.4278 | H6: =SUMIFS('Cash Balance'!$T$4:$T$920,'Cash Balance'!$Y$4:$Y$920,'>>Chart'!$C6,'Cash Balance'!$W$4:$W$920,'>>Chart'!H$1)/1000000 -> 0.00181222 | I6: =G6/Fx*1000+H6 -> 4.2206393 | J6: =G6+H6*Fx/1000 -> 110.47523 | K6: =SUMIFS('Cash Balance'!$L$4:$L$920,'Cash Balance'!$Y$4:$Y$920,'>>Chart'!$C6,'Cash Balance'!$W$4:$W$920,'>>Chart'!K$1)/1000000000 -> 427.3377 | L6: =SUMIFS('Cash Balance'!$T$4:$T$920,'Cash Balance'!$Y$4:$Y$920,'>>Chart'!$C6,'Cash Balance'!$W$4:$W$920,'>>Chart'!L$1)/1000000 -> 0 | M6: =K6*1000/Fx+L6 -> 16.326178 | N6: =D6+G6+K6 -> 544.73842 | O6: =E6+H6+L6 -> 0.00351614 | P6: =N6*1000/Fx+O6 -> 20.814917 | Q6: =SUMIFS(#REF!,#REF!,'>>Chart'!C6) -> #REF! | R6: =SUMIFS(#REF!,#REF!,'>>Chart'!C6) -> #REF! | S6: =Q6/$Q$18 -> #REF!
C7: VIETINBANK - DONG SAI GON | D7: =SUMIFS('Cash Balance'!$L$4:$L$920,'Cash Balance'!$Y$4:$Y$920,'>>Chart'!$C7,'Cash Balance'!$W$4:$W$920,'>>Chart'!D$1)/1000000000 -> 0 | E7: =SUMIFS('Cash Balance'!$T$4:$T$920,'Cash Balance'!$Y$4:$Y$920,'>>Chart'!$C7,'Cash Balance'!$W$4:$W$920,'>>Chart'!E$1)/1000000 -> 0.000769 | F7: =D7*1000/Fx+E7 -> 0.000769 | G7: =SUMIFS('Cash Balance'!$L$4:$L$920,'Cash Balance'!$Y$4:$Y$920,'>>Chart'!$C7,'Cash Balance'!$W$4:$W$920,'>>Chart'!G$1)/1000000000 -> 0.004095449 | H7: =SUMIFS('Cash Balance'!$T$4:$T$920,'Cash Balance'!$Y$4:$Y$920,'>>Chart'!$C7,'Cash Balance'!$W$4:$W$920,'>>Chart'!H$1)/1000000 -> 0 | I7: =G7/Fx*1000+H7 -> 0.00015646415 | J7: =G7+H7*Fx/1000 -> 0.004095449 | K7: =SUMIFS('Cash Balance'!$L$4:$L$920,'Cash Balance'!$Y$4:$Y$920,'>>Chart'!$C7,'Cash Balance'!$W$4:$W$920,'>>Chart'!K$1)/1000000000 -> 105.91062 | L7: =SUMIFS('Cash Balance'!$T$4:$T$920,'Cash Balance'!$Y$4:$Y$920,'>>Chart'!$C7,'Cash Balance'!$W$4:$W$920,'>>Chart'!L$1)/1000000 -> 0 | M7: =K7*1000/Fx+L7 -> 4.0462508 | N7: =D7+G7+K7 -> 105.91471 | O7: =E7+H7+L7 -> 0.000769 | P7: =N7*1000/Fx+O7 -> 4.0471763 | Q7: =SUMIFS(#REF!,#REF!,'>>Chart'!C7) -> #REF! | R7: =SUMIFS(#REF!,#REF!,'>>Chart'!C7) -> #REF! | S7: =Q7/$Q$18 -> #REF!
C8: VIETCOMBANK - BA DINH | D8: =SUMIFS('Cash Balance'!$L$4:$L$920,'Cash Balance'!$Y$4:$Y$920,'>>Chart'!$C8,'Cash Balance'!$W$4:$W$920,'>>Chart'!D$1)/1000000000 -> 0.42946304 | E8: =SUMIFS('Cash Balance'!$T$4:$T$920,'Cash Balance'!$Y$4:$Y$920,'>>Chart'!$C8,'Cash Balance'!$W$4:$W$920,'>>Chart'!E$1)/1000000 -> 0.00064269 | F8: =D8*1000/Fx+E8 -> 0.017050065 | G8: =SUMIFS('Cash Balance'!$L$4:$L$920,'Cash Balance'!$Y$4:$Y$920,'>>Chart'!$C8,'Cash Balance'!$W$4:$W$920,'>>Chart'!G$1)/1000000000 -> 2.0349262 | H8: =SUMIFS('Cash Balance'!$T$4:$T$920,'Cash Balance'!$Y$4:$Y$920,'>>Chart'!$C8,'Cash Balance'!$W$4:$W$920,'>>Chart'!H$1)/1000000 -> 0.0006062 | I8: =G8/Fx*1000+H8 -> 0.078349322 | J8: =G8+H8*Fx/1000 -> 2.0507935 | K8: =SUMIFS('Cash Balance'!$L$4:$L$920,'Cash Balance'!$Y$4:$Y$920,'>>Chart'!$C8,'Cash Balance'!$W$4:$W$920,'>>Chart'!K$1)/1000000000 -> 119.04302 | L8: =SUMIFS('Cash Balance'!$T$4:$T$920,'Cash Balance'!$Y$4:$Y$920,'>>Chart'!$C8,'Cash Balance'!$W$4:$W$920,'>>Chart'!L$1)/1000000 -> 0 | M8: =K8*1000/Fx+L8 -> 4.5479666 | N8: =D8+G8+K8 -> 121.50741 | O8: =E8+H8+L8 -> 0.00124889 | P8: =N8*1000/Fx+O8 -> 4.643366 | Q8: =SUMIFS(#REF!,#REF!,'>>Chart'!C8) -> #REF! | R8: =SUMIFS(#REF!,#REF!,'>>Chart'!C8) -> #REF! | S8: =Q8/$Q$18 -> #REF!
C9: VIETCOMBANK - HCM | D9: =SUMIFS('Cash Balance'!$L$4:$L$920,'Cash Balance'!$Y$4:$Y$920,'>>Chart'!$C9,'Cash Balance'!$W$4:$W$920,'>>Chart'!D$1)/1000000000 -> 0.28224182 | E9: =SUMIFS('Cash Balance'!$T$4:$T$920,'Cash Balance'!$Y$4:$Y$920,'>>Chart'!$C9,'Cash Balance'!$W$4:$W$920,'>>Chart'!E$1)/1000000 -> 0.00106836 | F9: =D9*1000/Fx+E9 -> 0.011851238 | G9: =SUMIFS('Cash Balance'!$L$4:$L$920,'Cash Balance'!$Y$4:$Y$920,'>>Chart'!$C9,'Cash Balance'!$W$4:$W$920,'>>Chart'!G$1)/1000000000 -> 1267.8364 | H9: =SUMIFS('Cash Balance'!$T$4:$T$920,'Cash Balance'!$Y$4:$Y$920,'>>Chart'!$C9,'Cash Balance'!$W$4:$W$920,'>>Chart'!H$1)/1000000 -> 9.25e-05 | I9: =G9/Fx*1000+H9 -> 48.437015 | J9: =G9+H9*Fx/1000 -> 1267.8389 | K9: =SUMIFS('Cash Balance'!$L$4:$L$920,'Cash Balance'!$Y$4:$Y$920,'>>Chart'!$C9,'Cash Balance'!$W$4:$W$920,'>>Chart'!K$1)/1000000000 -> 171.24825 | L9: =SUMIFS('Cash Balance'!$T$4:$T$920,'Cash Balance'!$Y$4:$Y$920,'>>Chart'!$C9,'Cash Balance'!$W$4:$W$920,'>>Chart'!L$1)/1000000 -> 0.00558932 | M9: =K9*1000/Fx+L9 -> 6.548025 | N9: =D9+G9+K9 -> 1439.3669 | O9: =E9+H9+L9 -> 0.00675018 | P9: =N9*1000/Fx+O9 -> 54.996891 | Q9: =SUMIFS(#REF!,#REF!,'>>Chart'!C9) -> #REF! | R9: =SUMIFS(#REF!,#REF!,'>>Chart'!C9) -> #REF! | S9: =Q9/$Q$18 -> #REF!
C10: BIDV - THANH XUAN | D10: =SUMIFS('Cash Balance'!$L$4:$L$920,'Cash Balance'!$Y$4:$Y$920,'>>Chart'!$C10,'Cash Balance'!$W$4:$W$920,'>>Chart'!D$1)/1000000000 -> 0.038060079 | E10: =SUMIFS('Cash Balance'!$T$4:$T$920,'Cash Balance'!$Y$4:$Y$920,'>>Chart'!$C10,'Cash Balance'!$W$4:$W$920,'>>Chart'!E$1)/1000000 -> 6.48e-05 | F10: =D10*1000/Fx+E10 -> 0.0015188622 | G10: =SUMIFS('Cash Balance'!$L$4:$L$920,'Cash Balance'!$Y$4:$Y$920,'>>Chart'!$C10,'Cash Balance'!$W$4:$W$920,'>>Chart'!G$1)/1000000000 -> 5.4521297 | H10: =SUMIFS('Cash Balance'!$T$4:$T$920,'Cash Balance'!$Y$4:$Y$920,'>>Chart'!$C10,'Cash Balance'!$W$4:$W$920,'>>Chart'!H$1)/1000000 -> 0.00021161 | I10: =G10/Fx*1000+H10 -> 0.20850692 | J10: =G10+H10*Fx/1000 -> 5.4576686 | K10: =SUMIFS('Cash Balance'!$L$4:$L$920,'Cash Balance'!$Y$4:$Y$920,'>>Chart'!$C10,'Cash Balance'!$W$4:$W$920,'>>Chart'!K$1)/1000000000 -> 288.1883 | L10: =SUMIFS('Cash Balance'!$T$4:$T$920,'Cash Balance'!$Y$4:$Y$920,'>>Chart'!$C10,'Cash Balance'!$W$4:$W$920,'>>Chart'!L$1)/1000000 -> 0.00016149 | M10: =K10*1000/Fx+L10 -> 11.010221 | N10: =D10+G10+K10 -> 293.67849 | O10: =E10+H10+L10 -> 0.0004379 | P10: =N10*1000/Fx+O10 -> 11.220247 | Q10: =SUMIFS(#REF!,#REF!,'>>Chart'!C10) -> #REF! | R10: =SUMIFS(#REF!,#REF!,'>>Chart'!C10) -> #REF! | S10: =Q10/$Q$18 -> #REF!
C11: BIDV - NAM SAI GON | D11: =SUMIFS('Cash Balance'!$L$4:$L$920,'Cash Balance'!$Y$4:$Y$920,'>>Chart'!$C11,'Cash Balance'!$W$4:$W$920,'>>Chart'!D$1)/1000000000 -> 0 | E11: =SUMIFS('Cash Balance'!$T$4:$T$920,'Cash Balance'!$Y$4:$Y$920,'>>Chart'!$C11,'Cash Balance'!$W$4:$W$920,'>>Chart'!E$1)/1000000 -> 0 | F11: =D11*1000/Fx+E11 -> 0 | G11: =SUMIFS('Cash Balance'!$L$4:$L$920,'Cash Balance'!$Y$4:$Y$920,'>>Chart'!$C11,'Cash Balance'!$W$4:$W$920,'>>Chart'!G$1)/1000000000 -> 0 | H11: =SUMIFS('Cash Balance'!$T$4:$T$920,'Cash Balance'!$Y$4:$Y$920,'>>Chart'!$C11,'Cash Balance'!$W$4:$W$920,'>>Chart'!H$1)/1000000 -> 0 | I11: =G11/Fx*1000+H11 -> 0 | J11: =G11+H11*Fx/1000 -> 0 | K11: =SUMIFS('Cash Balance'!$L$4:$L$920,'Cash Balance'!$Y$4:$Y$920,'>>Chart'!$C11,'Cash Balance'!$W$4:$W$920,'>>Chart'!K$1)/1000000000 -> 82.158268 | L11: =SUMIFS('Cash Balance'!$T$4:$T$920,'Cash Balance'!$Y$4:$Y$920,'>>Chart'!$C11,'Cash Balance'!$W$4:$W$920,'>>Chart'!L$1)/1000000 -> 0 | M11: =K11*1000/Fx+L11 -> 3.1388068 | N11: =D11+G11+K11 -> 82.158268 | O11: =E11+H11+L11 -> 0 | P11: =N11*1000/Fx+O11 -> 3.1388068 | Q11: =SUMIFS(#REF!,#REF!,'>>Chart'!C11) -> #REF! | R11: =SUMIFS(#REF!,#REF!,'>>Chart'!C11) -> #REF! | S11: =Q11/$Q$18 -> #REF!
C12: BIDV - LONG BIEN | D12: =SUMIFS('Cash Balance'!$L$4:$L$920,'Cash Balance'!$Y$4:$Y$920,'>>Chart'!$C12,'Cash Balance'!$W$4:$W$920,'>>Chart'!D$1)/1000000000 -> 0 | E12: =SUMIFS('Cash Balance'!$T$4:$T$920,'Cash Balance'!$Y$4:$Y$920,'>>Chart'!$C12,'Cash Balance'!$W$4:$W$920,'>>Chart'!E$1)/1000000 -> 0 | F12: =D12*1000/Fx+E12 -> 0 | G12: =SUMIFS('Cash Balance'!$L$4:$L$920,'Cash Balance'!$Y$4:$Y$920,'>>Chart'!$C12,'Cash Balance'!$W$4:$W$920,'>>Chart'!G$1)/1000000000 -> 0 | H12: =SUMIFS('Cash Balance'!$T$4:$T$920,'Cash Balance'!$Y$4:$Y$920,'>>Chart'!$C12,'Cash Balance'!$W$4:$W$920,'>>Chart'!H$1)/1000000 -> 0 | I12: =G12/Fx*1000+H12 -> 0 | J12: =G12+H12*Fx/1000 -> 0 | K12: =SUMIFS('Cash Balance'!$L$4:$L$920,'Cash Balance'!$Y$4:$Y$920,'>>Chart'!$C12,'Cash Balance'!$W$4:$W$920,'>>Chart'!K$1)/1000000000 -> 0.1016279 | L12: =SUMIFS('Cash Balance'!$T$4:$T$920,'Cash Balance'!$Y$4:$Y$920,'>>Chart'!$C12,'Cash Balance'!$W$4:$W$920,'>>Chart'!L$1)/1000000 -> 0.0001412 | M12: =K12*1000/Fx+L12 -> 0.0040238321 | N12: =D12+G12+K12 -> 0.1016279 | O12: =E12+H12+L12 -> 0.0001412 | P12: =N12*1000/Fx+O12 -> 0.0040238321 | Q12: =SUMIFS(#REF!,#REF!,'>>Chart'!C12) -> #REF! | R12: =SUMIFS(#REF!,#REF!,'>>Chart'!C12) -> #REF! | S12: =Q12/$Q$18 -> #REF!
C13: OCB - BINH DUONG | D13: =SUMIFS('Cash Balance'!$L$4:$L$920,'Cash Balance'!$Y$4:$Y$920,'>>Chart'!$C13,'Cash Balance'!$W$4:$W$920,'>>Chart'!D$1)/1000000000 -> 0.069627514 | E13: =SUMIFS('Cash Balance'!$T$4:$T$920,'Cash Balance'!$Y$4:$Y$920,'>>Chart'!$C13,'Cash Balance'!$W$4:$W$920,'>>Chart'!E$1)/1000000 -> 0.00015 | F13: =D13*1000/Fx+E13 -> 0.0028100769 | G13: =SUMIFS('Cash Balance'!$L$4:$L$920,'Cash Balance'!$Y$4:$Y$920,'>>Chart'!$C13,'Cash Balance'!$W$4:$W$920,'>>Chart'!G$1)/1000000000 -> 0.056483173 | H13: =SUMIFS('Cash Balance'!$T$4:$T$920,'Cash Balance'!$Y$4:$Y$920,'>>Chart'!$C13,'Cash Balance'!$W$4:$W$920,'>>Chart'!H$1)/1000000 -> 0.0001 | I13: =G13/Fx*1000+H13 -> 0.0022579054 | J13: =G13+H13*Fx/1000 -> 0.059100673 | K13: =SUMIFS('Cash Balance'!$L$4:$L$920,'Cash Balance'!$Y$4:$Y$920,'>>Chart'!$C13,'Cash Balance'!$W$4:$W$920,'>>Chart'!K$1)/1000000000 -> 0.47251851 | L13: =SUMIFS('Cash Balance'!$T$4:$T$920,'Cash Balance'!$Y$4:$Y$920,'>>Chart'!$C13,'Cash Balance'!$W$4:$W$920,'>>Chart'!L$1)/1000000 -> 0 | M13: =K13*1000/Fx+L13 -> 0.018052283 | N13: =D13+G13+K13 -> 0.5986292 | O13: =E13+H13+L13 -> 0.00025 | P13: =N13*1000/Fx+O13 -> 0.023120266 | Q13: =SUMIFS(#REF!,#REF!,'>>Chart'!C13) -> #REF! | R13: =SUMIFS(#REF!,#REF!,'>>Chart'!C13) -> #REF! | S13: =Q13/$Q$18 -> #REF!
C14: VIB - HOI SO | D14: =SUMIFS('Cash Balance'!$L$4:$L$920,'Cash Balance'!$Y$4:$Y$920,'>>Chart'!$C14,'Cash Balance'!$W$4:$W$920,'>>Chart'!D$1)/1000000000 -> 0.013672907 | E14: =SUMIFS('Cash Balance'!$T$4:$T$920,'Cash Balance'!$Y$4:$Y$920,'>>Chart'!$C14,'Cash Balance'!$W$4:$W$920,'>>Chart'!E$1)/1000000 -> 5.16e-05 | F14: =D14*1000/Fx+E14 -> 0.00057396512 | G14: =SUMIFS('Cash Balance'!$L$4:$L$920,'Cash Balance'!$Y$4:$Y$920,'>>Chart'!$C14,'Cash Balance'!$W$4:$W$920,'>>Chart'!G$1)/1000000000 -> 170.18762 | H14: =SUMIFS('Cash Balance'!$T$4:$T$920,'Cash Balance'!$Y$4:$Y$920,'>>Chart'!$C14,'Cash Balance'!$W$4:$W$920,'>>Chart'!H$1)/1000000 -> 0.0001 | I14: =G14/Fx*1000+H14 -> 6.5020148 | J14: =G14+H14*Fx/1000 -> 170.19024 | K14: =SUMIFS('Cash Balance'!$L$4:$L$920,'Cash Balance'!$Y$4:$Y$920,'>>Chart'!$C14,'Cash Balance'!$W$4:$W$920,'>>Chart'!K$1)/1000000000 -> 4.1944989 | L14: =SUMIFS('Cash Balance'!$T$4:$T$920,'Cash Balance'!$Y$4:$Y$920,'>>Chart'!$C14,'Cash Balance'!$W$4:$W$920,'>>Chart'!L$1)/1000000 -> 0 | M14: =K14*1000/Fx+L14 -> 0.16024829 | N14: =D14+G14+K14 -> 174.39579 | O14: =E14+H14+L14 -> 0.0001516 | P14: =N14*1000/Fx+O14 -> 6.662837 | Q14: =SUMIFS(#REF!,#REF!,'>>Chart'!C14) -> #REF! | R14: =SUMIFS(#REF!,#REF!,'>>Chart'!C14) -> #REF! | S14: =Q14/$Q$18 -> #REF!
C15: MB - BAC SAI GON | D15: =SUMIFS('Cash Balance'!$L$4:$L$920,'Cash Balance'!$Y$4:$Y$920,'>>Chart'!$C15,'Cash Balance'!$W$4:$W$920,'>>Chart'!D$1)/1000000000 -> 0 | E15: =SUMIFS('Cash Balance'!$T$4:$T$920,'Cash Balance'!$Y$4:$Y$920,'>>Chart'!$C15,'Cash Balance'!$W$4:$W$920,'>>Chart'!E$1)/1000000 -> 0 | F15: =D15*1000/Fx+E15 -> 0 | G15: =SUMIFS('Cash Balance'!$L$4:$L$920,'Cash Balance'!$Y$4:$Y$920,'>>Chart'!$C15,'Cash Balance'!$W$4:$W$920,'>>Chart'!G$1)/1000000000 -> 0.007958304 | H15: =SUMIFS('Cash Balance'!$T$4:$T$920,'Cash Balance'!$Y$4:$Y$920,'>>Chart'!$C15,'Cash Balance'!$W$4:$W$920,'>>Chart'!H$1)/1000000 -> 9e-05 | I15: =G15/Fx*1000+H15 -> 0.00039404218 | J15: =G15+H15*Fx/1000 -> 0.010314054 | K15: =SUMIFS('Cash Balance'!$L$4:$L$920,'Cash Balance'!$Y$4:$Y$920,'>>Chart'!$C15,'Cash Balance'!$W$4:$W$920,'>>Chart'!K$1)/1000000000 -> 0 | L15: =SUMIFS('Cash Balance'!$T$4:$T$920,'Cash Balance'!$Y$4:$Y$920,'>>Chart'!$C15,'Cash Balance'!$W$4:$W$920,'>>Chart'!L$1)/1000000 -> 0 | M15: =K15*1000/Fx+L15 -> 0 | N15: =D15+G15+K15 -> 0.007958304 | O15: =E15+H15+L15 -> 9e-05 | P15: =N15*1000/Fx+O15 -> 0.00039404218 | Q15: =SUMIFS(#REF!,#REF!,'>>Chart'!C15) -> #REF! | R15: =SUMIFS(#REF!,#REF!,'>>Chart'!C15) -> #REF! | S15: =Q15/$Q$18 -> #REF!
C16: SINOPAC | D16: =SUMIFS('Cash Balance'!$L$4:$L$920,'Cash Balance'!$Y$4:$Y$920,'>>Chart'!$C16,'Cash Balance'!$W$4:$W$920,'>>Chart'!D$1)/1000000000 -> 30.613469 | E16: =SUMIFS('Cash Balance'!$T$4:$T$920,'Cash Balance'!$Y$4:$Y$920,'>>Chart'!$C16,'Cash Balance'!$W$4:$W$920,'>>Chart'!E$1)/1000000 -> 0.01311974 | F16: =D16*1000/Fx+E16 -> 1.1826887 | G16: =SUMIFS('Cash Balance'!$L$4:$L$920,'Cash Balance'!$Y$4:$Y$920,'>>Chart'!$C16,'Cash Balance'!$W$4:$W$920,'>>Chart'!G$1)/1000000000 -> 40.074819 | H16: =SUMIFS('Cash Balance'!$T$4:$T$920,'Cash Balance'!$Y$4:$Y$920,'>>Chart'!$C16,'Cash Balance'!$W$4:$W$920,'>>Chart'!H$1)/1000000 -> 0 | I16: =G16/Fx*1000+H16 -> 1.5310342 | J16: =G16+H16*Fx/1000 -> 40.074819 | K16: =SUMIFS('Cash Balance'!$L$4:$L$920,'Cash Balance'!$Y$4:$Y$920,'>>Chart'!$C16,'Cash Balance'!$W$4:$W$920,'>>Chart'!K$1)/1000000000 -> 69.120993 | L16: =SUMIFS('Cash Balance'!$T$4:$T$920,'Cash Balance'!$Y$4:$Y$920,'>>Chart'!$C16,'Cash Balance'!$W$4:$W$920,'>>Chart'!L$1)/1000000 -> 0 | M16: =K16*1000/Fx+L16 -> 2.6407256 | N16: =D16+G16+K16 -> 139.80928 | O16: =E16+H16+L16 -> 0.01311974 | P16: =N16*1000/Fx+O16 -> 5.3544485 | Q16: =SUMIFS(#REF!,#REF!,'>>Chart'!C16) -> #REF! | R16: =SUMIFS(#REF!,#REF!,'>>Chart'!C16) -> #REF!
C17: OTHERS | D17: =SUMIFS('Cash Balance'!$L$4:$L$920,'Cash Balance'!$Y$4:$Y$920,'>>Chart'!$C17,'Cash Balance'!$W$4:$W$920,'>>Chart'!D$1)/1000000000 -> 0.18018878 | E17: =SUMIFS('Cash Balance'!$T$4:$T$920,'Cash Balance'!$Y$4:$Y$920,'>>Chart'!$C17,'Cash Balance'!$W$4:$W$920,'>>Chart'!E$1)/1000000 -> 3e-08 | F17: =D17*1000/Fx+E17 -> 0.0068840332 | G17: =SUMIFS('Cash Balance'!$L$4:$L$920,'Cash Balance'!$Y$4:$Y$920,'>>Chart'!$C17,'Cash Balance'!$W$4:$W$920,'>>Chart'!G$1)/1000000000 -> 0.64734746 | H17: =SUMIFS('Cash Balance'!$T$4:$T$920,'Cash Balance'!$Y$4:$Y$920,'>>Chart'!$C17,'Cash Balance'!$W$4:$W$920,'>>Chart'!H$1)/1000000 -> 0 | I17: =G17/Fx*1000+H17 -> 0.024731517 | J17: =G17+H17*Fx/1000 -> 0.64734746 | K17: =SUMIFS('Cash Balance'!$L$4:$L$920,'Cash Balance'!$Y$4:$Y$920,'>>Chart'!$C17,'Cash Balance'!$W$4:$W$920,'>>Chart'!K$1)/1000000000 -> 219.91921 | L17: =SUMIFS('Cash Balance'!$T$4:$T$920,'Cash Balance'!$Y$4:$Y$920,'>>Chart'!$C17,'Cash Balance'!$W$4:$W$920,'>>Chart'!L$1)/1000000 -> 0 | M17: =K17*1000/Fx+L17 -> 8.4018801 | N17: =D17+G17+K17 -> 220.74675 | O17: =E17+H17+L17 -> 3e-08 | P17: =N17*1000/Fx+O17 -> 8.4334957 | Q17: =SUMIFS(#REF!,#REF!,'>>Chart'!C17) -> #REF! | R17: =SUMIFS(#REF!,#REF!,'>>Chart'!C17) -> #REF! | S17: =Q17/$Q$18 -> #REF!
C18: TOTAL | D18: =SUM(D4:D17) -> 38.719551 | E18: =SUM(E4:E17) -> 0.01851847 | F18: =SUM(F4:F17) -> 1.4977754 | G18: =SUM(G4:G17) -> 1858.5591 | H18: =SUM(H4:H17) -> 0.00399282 | I18: =SUM(I4:I17) -> 71.009117 | J18: =SUM(J4:J17) -> 1858.6636 | K18: =SUM(K4:K17) -> 2084.9901 | ... M18: =SUM(M4:M17) -> 79.692348 | N18: =D18+G18+K18 -> 3982.2688 | O18: =E18+H18+L18 -> 0.05907661 | P18: =N18*1000/Fx+O18 -> 152.19924 | Q18: =SUM(Q4:Q17) -> #REF! | R18: =SUM(R4:R17) -> #REF! | S18: =Q18/$Q$18 -> #REF!
C21: Row Labels | D21: Sum of BW_Total_USD_mn | E21: Sum of VC3_Total_USD_mn | F21: Sum of SUB_TOTAL_USD_mn | G21: Sum of Total
C22: BIDV - LONG BIEN | D22: 0 | E22: 0 | F22: 1.2728541 | G22: 1.2728541
C23: BIDV - NAM SAI GON | D23: 0 | E23: 0 | F23: 3.0989018 | G23: 3.0989018
C24: BIDV - THANH XUAN | D24: 0.0015521126 | E24: 1.9329444 | F24: 12.531195 | G24: 14.465691
C25: MB - BAC SAI GON | D25: 0 | E25: 0.00039601238 | F25: 0 | G25: 0.00039601238
C26: OCB - BINH DUONG | D26: 0.0028399669 | E26: 0.0022845483 | F26: 0.052526566 | G26: 0.057651081
C27: OTHERS | D27: 0.0069283002 | E27: 0.016659581 | F27: 3.3959035 | G27: 3.4194914
C28: SINOPAC | D28: 1.1683116 | E28: 1.945968 | F28: 2.8833237 | G28: 5.9976034
C29: VIB - HOI SO | D29: 0.00058975969 | E29: 6.5457686 | F29: 0.12115174 | G29: 6.6675101
C30: VIETCOMBANK - BA DINH | D30: 0.017156796 | E30: 0.078774524 | F30: 5.2258423 | G30: 5.3217736
C31: VIETCOMBANK - HCM | D31: 0.011771033 | E31: 44.040424 | F31: 3.872738 | G31: 47.924933
C32: VIETINBANK - BINH DUONG + QM | D32: 0.50274374 | E32: 7.0234828 | F32: 8.9906742 | G32: 16.516901
C33: VIETINBANK - CN1 | D33: 0.004238503 | E33: 0.0071696772 | F33: 3.4427433 | G33: 3.4541514
... C36: Grand Total | D36: 1.7182163 | E36: 64.181634 | F36: 67.113845 | G36: 133.0137
D42: =ROUND(SUM(F4:F17),0)=ROUND(SUM(D45:D61),0) -> TRUE | E42: =ROUND(SUM(I4:I17),0)=ROUND(SUM(E45:E61),0) -> TRUE | F42: =ROUND(SUM(M4:M17),0)=ROUND(SUM(F45:F61),0) -> TRUE | G42: =ROUND(SUM(P4:P17),0)=ROUND(SUM(G45:G61),0) -> TRUE
R43: Bank
C44: Bank | D44: BW | E44: VC3 | F44: Subs | G44: Total | H44: FA | J44: % | K44: %/FA | N44: % | R44: VTB | S44: =SUMIFS($G$45:$G$61,$A$45:$A$61,'>>Chart'!R44)/'>>Chart'!$P$18 -> 0.37925032
A45: VTB | B45: VTB TS | C45: VIETINBANK - TIEN SON | D45: =_xlfn.XLOOKUP($C45,$C$4:$C$17,$F$4:$F$17,0,0,1) -> 0.0013094371 | E45: =_xlfn.XLOOKUP($C45,$C$4:$C$17,$I$4:$I$17,0,0,1) -> 9.9968845 | F45: =_xlfn.XLOOKUP($C45,$C$4:$C$17,$M$4:$M$17,0,0,1) -> 20.61079 | G45: =SUM(D45:F45) -> 30.608983 | H45: =_xlfn.XLOOKUP($C45,$C$4:$C$17,$Q$4:$Q$17,0,0,1) -> #REF! | J45: =G45/SUM($G$45:$G$61) -> 0.20111128 | K45: =IFERROR(H45/SUM($H$45:$H$61),0) -> 0 | N45: =J45 -> 0.20111128 | R45: VCB | S45: =SUMIFS($G$45:$G$61,$A$45:$A$61,'>>Chart'!R45)/'>>Chart'!$P$18 -> 0.39185647
A46: VTB | B46: VTB BD + QM | C46: VIETINBANK - BINH DUONG + QM | D46: =_xlfn.XLOOKUP($C46,$C$4:$C$17,$F$4:$F$17,0,0,1) -> 0.26810015 | E46: =_xlfn.XLOOKUP($C46,$C$4:$C$17,$I$4:$I$17,0,0,1) -> 4.2206393 | F46: =_xlfn.XLOOKUP($C46,$C$4:$C$17,$M$4:$M$17,0,0,1) -> 16.326178 | G46: =SUM(D46:F46) -> 20.814917 | H46: =_xlfn.XLOOKUP($C46,$C$4:$C$17,$Q$4:$Q$17,0,0,1) -> #REF! | J46: =G46/SUM($G$45:$G$61) -> 0.13676098 | K46: =IFERROR(H46/SUM($H$45:$H$61),0) -> 0 | N46: =J46 -> 0.13676098 | R46: BIDV | S46: =SUMIFS($G$45:$G$61,$A$45:$A$61,'>>Chart'!R46)/'>>Chart'!$P$18 -> 0.094370229
A47: VTB | B47: VTB DSG | C47: VIETINBANK - DONG SAI GON | D47: =_xlfn.XLOOKUP($C47,$C$4:$C$17,$F$4:$F$17,0,0,1) -> 0.000769 | E47: =_xlfn.XLOOKUP($C47,$C$4:$C$17,$I$4:$I$17,0,0,1) -> 0.00015646415 | F47: =_xlfn.XLOOKUP($C47,$C$4:$C$17,$M$4:$M$17,0,0,1) -> 4.0462508 | G47: =SUM(D47:F47) -> 4.0471763 | H47: =_xlfn.XLOOKUP($C47,$C$4:$C$17,$Q$4:$Q$17,0,0,1) -> #REF! | J47: =G47/SUM($G$45:$G$61) -> 0.026591304 | K47: =IFERROR(H47/SUM($H$45:$H$61),0) -> 0 | N47: =J47 -> 0.026591304 | R47: OCB | S47: =SUMIFS($G$45:$G$61,$A$45:$A$61,'>>Chart'!R47)/'>>Chart'!$P$18 -> 0.00015190789
A48: VTB | B48: VTB CN1 | C48: VIETINBANK - CN1 | D48: =_xlfn.XLOOKUP($C48,$C$4:$C$17,$F$4:$F$17,0,0,1) -> 0.0042198677 | E48: =_xlfn.XLOOKUP($C48,$C$4:$C$17,$I$4:$I$17,0,0,1) -> 0.0071336651 | F48: =_xlfn.XLOOKUP($C48,$C$4:$C$17,$M$4:$M$17,0,0,1) -> 2.2391806 | G48: =SUM(D48:F48) -> 2.2505342 | H48: =_xlfn.XLOOKUP($C48,$C$4:$C$17,$Q$4:$Q$17,0,0,1) -> #REF! | J48: =G48/SUM($G$45:$G$61) -> 0.014786763 | K48: =IFERROR(H48/SUM($H$45:$H$61),0) -> 0 | N48: =J48 -> 0.014786763 | R48: VIB | S48: =SUMIFS($G$45:$G$61,$A$45:$A$61,'>>Chart'!R48)/'>>Chart'!$P$18 -> 0.043777072
D49: =_xlfn.XLOOKUP($C49,$C$4:$C$17,$F$4:$F$17,0,0,1) -> 0 | E49: =_xlfn.XLOOKUP($C49,$C$4:$C$17,$I$4:$I$17,0,0,1) -> 0 | F49: =_xlfn.XLOOKUP($C49,$C$4:$C$17,$M$4:$M$17,0,0,1) -> 0 | H49: =_xlfn.XLOOKUP($C49,$C$4:$C$17,$Q$4:$Q$17,0,0,1) -> 0 | L49: =SUM(G45:G48) -> 57.721611 | R49: MBB | S49: =SUMIFS($G$45:$G$61,$A$45:$A$61,'>>Chart'!R49)/'>>Chart'!$P$18 -> 2.5889891e-06
A50: VCB | B50: VCB HCM | C50: VIETCOMBANK - HCM | D50: =_xlfn.XLOOKUP($C50,$C$4:$C$17,$F$4:$F$17,0,0,1) -> 0.011851238 | E50: =_xlfn.XLOOKUP($C50,$C$4:$C$17,$I$4:$I$17,0,0,1) -> 48.437015 | F50: =_xlfn.XLOOKUP($C50,$C$4:$C$17,$M$4:$M$17,0,0,1) -> 6.548025 | G50: =SUM(D50:F50) -> 54.996891 | H50: =_xlfn.XLOOKUP($C50,$C$4:$C$17,$Q$4:$Q$17,0,0,1) -> #REF! | J50: =G50/SUM($G$45:$G$61) -> 0.361348 | K50: =IFERROR(H50/SUM($H$45:$H$61),0) -> 0 | N50: =J50 -> 0.361348 | R50: SINOPAC | S50: =SUMIFS($G$45:$G$61,$A$45:$A$61,'>>Chart'!R50)/'>>Chart'!$P$18 -> 0.035180521
A51: VCB | B51: VCB BD | C51: =C8 -> VIETCOMBANK - BA DINH | D51: =_xlfn.XLOOKUP($C51,$C$4:$C$17,$F$4:$F$17,0,0,1) -> 0.017050065 | E51: =_xlfn.XLOOKUP($C51,$C$4:$C$17,$I$4:$I$17,0,0,1) -> 0.078349322 | F51: =_xlfn.XLOOKUP($C51,$C$4:$C$17,$M$4:$M$17,0,0,1) -> 4.5479666 | G51: =SUM(D51:F51) -> 4.643366 | H51: =_xlfn.XLOOKUP($C51,$C$4:$C$17,$Q$4:$Q$17,0,0,1) -> #REF! | J51: =G51/SUM($G$45:$G$61) -> 0.03050847 | K51: =IFERROR(H51/SUM($H$45:$H$61),0) -> 0 | N51: =J51 -> 0.03050847 | R51: OTHERS | S51: =SUMIFS($G$45:$G$61,$A$45:$A$61,'>>Chart'!R51)/'>>Chart'!$P$18 -> 0.055410892
D52: =_xlfn.XLOOKUP($C52,$C$4:$C$17,$F$4:$F$17,0,0,1) -> 0 | E52: =_xlfn.XLOOKUP($C52,$C$4:$C$17,$I$4:$I$17,0,0,1) -> 0 | F52: =_xlfn.XLOOKUP($C52,$C$4:$C$17,$M$4:$M$17,0,0,1) -> 0 | H52: =_xlfn.XLOOKUP($C52,$C$4:$C$17,$Q$4:$Q$17,0,0,1) -> 0 | L52: =SUM(G50:G51) -> 59.640257
A53: BIDV | B53: BIDV TX | C53: BIDV - THANH XUAN | D53: =_xlfn.XLOOKUP($C53,$C$4:$C$17,$F$4:$F$17,0,0,1) -> 0.0015188622 | E53: =_xlfn.XLOOKUP($C53,$C$4:$C$17,$I$4:$I$17,0,0,1) -> 0.20850692 | F53: =_xlfn.XLOOKUP($C53,$C$4:$C$17,$M$4:$M$17,0,0,1) -> 11.010221 | G53: =SUM(D53:F53) -> 11.220247 | H53: =_xlfn.XLOOKUP($C53,$C$4:$C$17,$Q$4:$Q$17,0,0,1) -> #REF! | J53: =G53/SUM($G$45:$G$61) -> 0.073720779 | K53: =IFERROR(H53/SUM($H$45:$H$61),0) -> 0 | N53: =J53 -> 0.073720779 | S53: =SUM(S44:S51) -> 1
A54: BIDV | B54: BIDV NSG | C54: =C11 -> BIDV - NAM SAI GON | D54: =_xlfn.XLOOKUP($C54,$C$4:$C$17,$F$4:$F$17,0,0,1) -> 0 | E54: =_xlfn.XLOOKUP($C54,$C$4:$C$17,$I$4:$I$17,0,0,1) -> 0 | F54: =_xlfn.XLOOKUP($C54,$C$4:$C$17,$M$4:$M$17,0,0,1) -> 3.1388068 | G54: =SUM(D54:F54) -> 3.1388068 | H54: =_xlfn.XLOOKUP($C54,$C$4:$C$17,$Q$4:$Q$17,0,0,1) -> #REF! | J54: =G54/SUM($G$45:$G$61) -> 0.020623012 | K54: =IFERROR(H54/SUM($H$45:$H$61),0) -> 0 | N54: =J54 -> 0.020623012
A55: BIDV | B55: BIDV LB | C55: BIDV - LONG BIEN | D55: =_xlfn.XLOOKUP($C55,$C$4:$C$17,$F$4:$F$17,0,0,1) -> 0 | E55: =_xlfn.XLOOKUP($C55,$C$4:$C$17,$I$4:$I$17,0,0,1) -> 0 | F55: =_xlfn.XLOOKUP($C55,$C$4:$C$17,$M$4:$M$17,0,0,1) -> 0.0040238321 | G55: =SUM(D55:F55) -> 0.0040238321 | H55: =_xlfn.XLOOKUP($C55,$C$4:$C$17,$Q$4:$Q$17,0,0,1) -> #REF! | J55: =G55/SUM($G$45:$G$61) -> 2.6437925e-05 | K55: =IFERROR(H55/SUM($H$45:$H$61),0) -> 0 | N55: =J55 -> 2.6437925e-05
D56: =_xlfn.XLOOKUP($C56,$C$4:$C$17,$F$4:$F$17,0,0,1) -> 0 | E56: =_xlfn.XLOOKUP($C56,$C$4:$C$17,$I$4:$I$17,0,0,1) -> 0 | F56: =_xlfn.XLOOKUP($C56,$C$4:$C$17,$M$4:$M$17,0,0,1) -> 0 | H56: =_xlfn.XLOOKUP($C56,$C$4:$C$17,$Q$4:$Q$17,0,0,1) -> 0 | L56: =SUM(G53:G55) -> 14.363077
A57: OCB | B57: OCB BD | C57: OCB - BINH DUONG | D57: =_xlfn.XLOOKUP($C57,$C$4:$C$17,$F$4:$F$17,0,0,1) -> 0.0028100769 | E57: =_xlfn.XLOOKUP($C57,$C$4:$C$17,$I$4:$I$17,0,0,1) -> 0.0022579054 | F57: =_xlfn.XLOOKUP($C57,$C$4:$C$17,$M$4:$M$17,0,0,1) -> 0.018052283 | G57: =SUM(D57:F57) -> 0.023120266 | H57: =_xlfn.XLOOKUP($C57,$C$4:$C$17,$Q$4:$Q$17,0,0,1) -> #REF! | J57: =G57/SUM($G$45:$G$61) -> 0.00015190789 | K57: =IFERROR(H57/SUM($H$45:$H$61),0) -> 0 | N57: =J57 -> 0.00015190789
A58: MBB | B58: MBB BSG | C58: MB - BAC SAI GON | D58: =_xlfn.XLOOKUP($C58,$C$4:$C$17,$F$4:$F$17,0,0,1) -> 0 | E58: =_xlfn.XLOOKUP($C58,$C$4:$C$17,$I$4:$I$17,0,0,1) -> 0.00039404218 | F58: =_xlfn.XLOOKUP($C58,$C$4:$C$17,$M$4:$M$17,0,0,1) -> 0 | G58: =SUM(D58:F58) -> 0.00039404218 | H58: =_xlfn.XLOOKUP($C58,$C$4:$C$17,$Q$4:$Q$17,0,0,1) -> #REF! | J58: =G58/SUM($G$45:$G$61) -> 2.5889891e-06 | K58: =IFERROR(H58/SUM($H$45:$H$61),0) -> 0 | N58: =J58 -> 2.5889891e-06
A59: VIB | B59: VIB HO | C59: VIB - HOI SO | D59: =_xlfn.XLOOKUP($C59,$C$4:$C$17,$F$4:$F$17,0,0,1) -> 0.00057396512 | E59: =_xlfn.XLOOKUP($C59,$C$4:$C$17,$I$4:$I$17,0,0,1) -> 6.5020148 | F59: =_xlfn.XLOOKUP($C59,$C$4:$C$17,$M$4:$M$17,0,0,1) -> 0.16024829 | G59: =SUM(D59:F59) -> 6.662837 | H59: =_xlfn.XLOOKUP($C59,$C$4:$C$17,$Q$4:$Q$17,0,0,1) -> #REF! | J59: =G59/SUM($G$45:$G$61) -> 0.043777072 | K59: =IFERROR(H59/SUM($H$45:$H$61),0) -> 0 | N59: =J59 -> 0.043777072
A60: SINOPAC | B60: SINOPAC | C60: SINOPAC | D60: =_xlfn.XLOOKUP($C60,$C$4:$C$17,$F$4:$F$17,0,0,1) -> 1.1826887 | E60: =_xlfn.XLOOKUP($C60,$C$4:$C$17,$I$4:$I$17,0,0,1) -> 1.5310342 | F60: =_xlfn.XLOOKUP($C60,$C$4:$C$17,$M$4:$M$17,0,0,1) -> 2.6407256 | G60: =SUM(D60:F60) -> 5.3544485 | H60: =_xlfn.XLOOKUP($C60,$C$4:$C$17,$Q$4:$Q$17,0,0,1) -> #REF! | J60: =G60/SUM($G$45:$G$61) -> 0.035180521 | K60: =IFERROR(H60/SUM($H$45:$H$61),0) -> 0 | N60: =J60 -> 0.035180521
A61: OTHERS | B61: OTHERS | C61: OTHERS | D61: =_xlfn.XLOOKUP($C61,$C$4:$C$17,$F$4:$F$17,0,0,1) -> 0.0068840332 | E61: =_xlfn.XLOOKUP($C61,$C$4:$C$17,$I$4:$I$17,0,0,1) -> 0.024731517 | F61: =_xlfn.XLOOKUP($C61,$C$4:$C$17,$M$4:$M$17,0,0,1) -> 8.4018801 | G61: =SUM(D61:F61) -> 8.4334957 | H61: =_xlfn.XLOOKUP($C61,$C$4:$C$17,$Q$4:$Q$17,0,0,1) -> #REF! | J61: =G61/SUM($G$45:$G$61) -> 0.055410892 | K61: =IFERROR(H61/SUM($H$45:$H$61),0) -> 0 | N61: =J61 -> 0.055410892
L63: =SUM(G57:G62) -> 20.474296 | N63: =SUM(N45:N61) -> 1
G64: =SUM(G45:G61)=P18 -> TRUE
C103: Entity | E103: USD | F103: VND | G103: Total | J103: OB | K103: EB
C104: BWID JSC | D104: O.Balance | E104: =SUMIFS('Cash Balance'!$Q$4:$Q$920,'Cash Balance'!$W$4:$W$920,'>>Chart'!$C104,'Cash Balance'!$E$4:$E$920,'>>Chart'!E$103)/1000000 -> 0.04452867 | F104: =SUMIFS('Cash Balance'!$H$4:$H$920,'Cash Balance'!$W$4:$W$920,'>>Chart'!$C104,'Cash Balance'!$E$4:$E$920,'>>Chart'!F$103)/1000000/Fx_rate -> 1.4933719 | G104: =SUM(E104:F104) -> 1.5379006 | I104: BWID JSC | J104: =G104/SUM($G$104,$G$106,$G$108) -> 0.011432416 | K104: =G105/SUM($G$105,$G$107,$G$109) -> 0.0092765121
D105: E.Balance | E105: =SUMIFS('Cash Balance'!$T$4:$T$920,'Cash Balance'!$W$4:$W$920,'>>Chart'!$C104,'Cash Balance'!$E$4:$E$920,'>>Chart'!E$103)/1000000 -> 0.01946847 | F105: =SUMIFS('Cash Balance'!$L$4:$L$920,'Cash Balance'!$W$4:$W$920,'>>Chart'!$C104,'Cash Balance'!$E$4:$E$920,'>>Chart'!F$103)/1000000/Fx_rate -> 1.4846825 | G105: =SUM(E105:F105) -> 1.504151 | I105: VC3 | J105: =G106/SUM($G$104,$G$106,$G$108) -> 0.39482229 | K105: =G107/SUM($G$105,$G$107,$G$109) -> 0.4418772
C106: VC3 | D106: O.Balance | E106: =SUMIFS('Cash Balance'!$Q$4:$Q$920,'Cash Balance'!$W$4:$W$920,'>>Chart'!$C106,'Cash Balance'!$E$4:$E$920,'>>Chart'!E$103)/1000000 -> 0.00963126 | F106: =SUMIFS('Cash Balance'!$H$4:$H$920,'Cash Balance'!$W$4:$W$920,'>>Chart'!$C106,'Cash Balance'!$E$4:$E$920,'>>Chart'!F$103)/1000000/Fx_rate -> 53.102277 | G106: =SUM(E106:F106) -> 53.111909 | I106: Subsidiaries | J106: =G108/SUM($G$104,$G$106,$G$108) -> 0.59374529 | K106: =G109/SUM($G$105,$G$107,$G$109) -> 0.54884629
D107: E.Balance | E107: =SUMIFS('Cash Balance'!$T$4:$T$920,'Cash Balance'!$W$4:$W$920,'>>Chart'!$C106,'Cash Balance'!$E$4:$E$920,'>>Chart'!E$103)/1000000 -> 0.00962906 | F107: =SUMIFS('Cash Balance'!$L$4:$L$920,'Cash Balance'!$W$4:$W$920,'>>Chart'!$C106,'Cash Balance'!$E$4:$E$920,'>>Chart'!F$103)/1000000/Fx_rate -> 71.63907 | G107: =SUM(E107:F107) -> 71.648699 | J107: =SUM(J104:J106) -> 1 | K107: =SUM(K104:K106) -> 1
C108: Subsidiaries | D108: O.Balance | E108: =SUMIFS('Cash Balance'!$Q$4:$Q$920,'Cash Balance'!$W$4:$W$920,'>>Chart'!$C108,'Cash Balance'!$E$4:$E$920,'>>Chart'!E$103)/1000000 -> 0.03662991 | F108: =SUMIFS('Cash Balance'!$H$4:$H$920,'Cash Balance'!$W$4:$W$920,'>>Chart'!$C108,'Cash Balance'!$E$4:$E$920,'>>Chart'!F$103)/1000000/Fx_rate -> 79.83461 | G108: =SUM(E108:F108) -> 79.87124
D109: E.Balance | E109: =SUMIFS('Cash Balance'!$T$4:$T$920,'Cash Balance'!$W$4:$W$920,'>>Chart'!$C108,'Cash Balance'!$E$4:$E$920,'>>Chart'!E$103)/1000000 -> 0.03657006 | F109: =SUMIFS('Cash Balance'!$L$4:$L$920,'Cash Balance'!$W$4:$W$920,'>>Chart'!$C108,'Cash Balance'!$E$4:$E$920,'>>Chart'!F$103)/1000000/Fx_rate -> 88.956757 | G109: =SUM(E109:F109) -> 88.993328
C110: Total | D110: O.Balance | E110: =E104+E106+E108 -> 0.09078984 | F110: =F104+F106+F108 -> 134.43026 | G110: =G104+G106+G108 -> 134.52105
D111: E.Balance | E111: =E105+E107+E109 -> 0.06566759 | F111: =F105+F107+F109 -> 162.08051 | G111: =G105+G107+G109 -> 162.14618
D136: Value | E136: Cummulative | F136: Start & End | G136: Before | H136: After | I136: Data Label Position
B137: B.O.P | C137: B.O.P | D137: =G104+G106+G108 -> 134.52105 | E137: =D137 -> 134.52105 | F137: =E137 -> 134.52105
B138: Rental income | C138: Receipt from tenants | D138: =(SUMIFS(Movement!$H$4:$H$2133,Movement!$L$4:$L$2133,'>>Chart'!C138,Movement!$O$4:$O$2133,Summary!$B$4,Movement!$M$4:$M$2133,"VND"))/Fx_rate/1000000+(SUMIFS(Movement!$H$4:$H$2133,Movement!$L$4:$L$2133,'>>Chart'!C138,Movement!$O$4:$O$2133,Summary!$B$4,Movement!$M$4:$M$2133,"USD"))/1000000 -> 12.486122 | E138: =E137+D138 -> 147.00717 | G138: =SUM($D$137:D137) -> 134.52105 | H138: =SUM($D$137:D138) -> 147.00717 | I138: =IF(D138<0,G138,H138) -> 147.00717
B139: Refund deposit | C139: Refund land/deal deposit payment | D139: =(SUMIFS(Movement!$H$4:$H$2133,Movement!$L$4:$L$2133,'>>Chart'!C139,Movement!$O$4:$O$2133,Summary!$B$4,Movement!$M$4:$M$2133,"VND"))/Fx_rate/1000000+(SUMIFS(Movement!$H$4:$H$2133,Movement!$L$4:$L$2133,'>>Chart'!C139,Movement!$O$4:$O$2133,Summary!$B$4,Movement!$M$4:$M$2133,"USD"))/1000000 -> 0 | E139: =E138+D139 -> 147.00717 | G139: =SUM($D$137:D138) -> 147.00717 | H139: =SUM($D$137:D139) -> 147.00717 | I139: =IF(D139<0,G139,H139) -> 147.00717
B140: VAT refund | C140: VAT refund | D140: =(SUMIFS(Movement!$H$4:$H$2133,Movement!$L$4:$L$2133,'>>Chart'!C140,Movement!$O$4:$O$2133,Summary!$B$4,Movement!$M$4:$M$2133,"VND"))/Fx_rate/1000000+(SUMIFS(Movement!$H$4:$H$2133,Movement!$L$4:$L$2133,'>>Chart'!C140,Movement!$O$4:$O$2133,Summary!$B$4,Movement!$M$4:$M$2133,"USD"))/1000000 -> 0 | E140: =E139+D140 -> 147.00717 | G140: =SUM($D$137:D139) -> 147.00717 | H140: =SUM($D$137:D140) -> 147.00717 | I140: =IF(D140<0,G140,H140) -> 147.00717
B141: Other receipts | C141: Other receipts | D141: =(SUMIFS(Movement!$H$4:$H$2133,Movement!$L$4:$L$2133,'>>Chart'!C141,Movement!$O$4:$O$2133,Summary!$B$4,Movement!$M$4:$M$2133,"VND"))/Fx_rate/1000000+(SUMIFS(Movement!$H$4:$H$2133,Movement!$L$4:$L$2133,'>>Chart'!C141,Movement!$O$4:$O$2133,Summary!$B$4,Movement!$M$4:$M$2133,"USD"))/1000000 -> 0.18555249 | E141: =E140+D141 -> 147.19272 | G141: =SUM($D$137:D140) -> 147.00717 | H141: =SUM($D$137:D141) -> 147.19272 | I141: =IF(D141<0,G141,H141) -> 147.19272
B142: Operating expense | C142: Operating expense | D142: =(SUMIFS(Movement!$H$4:$H$2133,Movement!$L$4:$L$2133,'>>Chart'!C142,Movement!$O$4:$O$2133,Summary!$B$4,Movement!$M$4:$M$2133,"VND"))/Fx_rate/1000000+(SUMIFS(Movement!$H$4:$H$2133,Movement!$L$4:$L$2133,'>>Chart'!C142,Movement!$O$4:$O$2133,Summary!$B$4,Movement!$M$4:$M$2133,"USD"))/1000000 -> -3.082988 | E142: =E141+D142 -> 144.10974 | G142: =SUM($D$137:D141) -> 147.19272 | H142: =SUM($D$137:D142) -> 144.10974 | I142: =IF(D142<0,G142,H142) -> 147.19272
B143: Refinancing | C143: Refinancing | D143: =(SUMIFS(Movement!$H$4:$H$2133,Movement!$L$4:$L$2133,'>>Chart'!C143,Movement!$O$4:$O$2133,Summary!$B$4,Movement!$M$4:$M$2133,"VND"))/Fx_rate/1000000+(SUMIFS(Movement!$H$4:$H$2133,Movement!$L$4:$L$2133,'>>Chart'!C143,Movement!$O$4:$O$2133,Summary!$B$4,Movement!$M$4:$M$2133,"USD"))/1000000 -> 0 | E143: =E142+D143 -> 144.10974 | G143: =SUM($D$137:D142) -> 144.10974 | H143: =SUM($D$137:D143) -> 144.10974 | I143: =IF(D143<0,G143,H143) -> 144.10974
B144: Loan receipts | C144: Loan receipts | D144: =(SUMIFS(Movement!$H$4:$H$2133,Movement!$L$4:$L$2133,'>>Chart'!C144,Movement!$O$4:$O$2133,Summary!$B$4,Movement!$M$4:$M$2133,"VND"))/Fx_rate/1000000+(SUMIFS(Movement!$H$4:$H$2133,Movement!$L$4:$L$2133,'>>Chart'!C144,Movement!$O$4:$O$2133,Summary!$B$4,Movement!$M$4:$M$2133,"USD"))/1000000 -> 0 | E144: =E143+D144 -> 144.10974 | G144: =SUM($D$137:D143) -> 144.10974 | H144: =SUM($D$137:D144) -> 144.10974 | I144: =IF(D144<0,G144,H144) -> 144.10974
B145: Loan repayment | C145: Loan repayment | D145: =(SUMIFS(Movement!$H$4:$H$2133,Movement!$L$4:$L$2133,'>>Chart'!C145,Movement!$O$4:$O$2133,Summary!$B$4,Movement!$M$4:$M$2133,"VND"))/Fx_rate/1000000+(SUMIFS(Movement!$H$4:$H$2133,Movement!$L$4:$L$2133,'>>Chart'!C145,Movement!$O$4:$O$2133,Summary!$B$4,Movement!$M$4:$M$2133,"USD"))/1000000 -> -0.072605406 | E145: =E144+D145 -> 144.03713 | G145: =SUM($D$137:D144) -> 144.10974 | H145: =SUM($D$137:D145) -> 144.03713 | I145: =IF(D145<0,G145,H145) -> 144.10974
B146: Loan interest | C146: Loan interest | D146: =(SUMIFS(Movement!$H$4:$H$2133,Movement!$L$4:$L$2133,'>>Chart'!C146,Movement!$O$4:$O$2133,Summary!$B$4,Movement!$M$4:$M$2133,"VND"))/Fx_rate/1000000+(SUMIFS(Movement!$H$4:$H$2133,Movement!$L$4:$L$2133,'>>Chart'!C146,Movement!$O$4:$O$2133,Summary!$B$4,Movement!$M$4:$M$2133,"USD"))/1000000 -> 0 | E146: =E145+D146 -> 144.03713 | G146: =SUM($D$137:D145) -> 144.03713 | H146: =SUM($D$137:D146) -> 144.03713 | I146: =IF(D146<0,G146,H146) -> 144.03713
B147: Construction exp. | C147: Construction expense | D147: =(SUMIFS(Movement!$H$4:$H$2133,Movement!$L$4:$L$2133,'>>Chart'!C147,Movement!$O$4:$O$2133,Summary!$B$4,Movement!$M$4:$M$2133,"VND"))/Fx_rate/1000000+(SUMIFS(Movement!$H$4:$H$2133,Movement!$L$4:$L$2133,'>>Chart'!C147,Movement!$O$4:$O$2133,Summary!$B$4,Movement!$M$4:$M$2133,"USD"))/1000000 -> -4.8135884 | E147: =E146+D147 -> 139.22354 | G147: =SUM($D$137:D146) -> 144.03713 | H147: =SUM($D$137:D147) -> 139.22354 | I147: =IF(D147<0,G147,H147) -> 144.03713
B148: Corp Loan | C148: Corporate Loan drawdown | D148: =(SUMIFS(Movement!$H$4:$H$2133,Movement!$L$4:$L$2133,'>>Chart'!C148,Movement!$O$4:$O$2133,Summary!$B$4,Movement!$M$4:$M$2133,"VND"))/Fx_rate/1000000+(SUMIFS(Movement!$H$4:$H$2133,Movement!$L$4:$L$2133,'>>Chart'!C148,Movement!$O$4:$O$2133,Summary!$B$4,Movement!$M$4:$M$2133,"USD"))/1000000 -> 0 | E148: =E147+D148 -> 139.22354 | G148: =SUM($D$137:D147) -> 139.22354 | H148: =SUM($D$137:D148) -> 139.22354 | I148: =IF(D148<0,G148,H148) -> 139.22354
B149: Land acquisition | C149: Land acquisition | D149: =(SUMIFS(Movement!$H$4:$H$2133,Movement!$L$4:$L$2133,'>>Chart'!C149,Movement!$O$4:$O$2133,Summary!$B$4,Movement!$M$4:$M$2133,"VND"))/Fx_rate/1000000+(SUMIFS(Movement!$H$4:$H$2133,Movement!$L$4:$L$2133,'>>Chart'!C149,Movement!$O$4:$O$2133,Summary!$B$4,Movement!$M$4:$M$2133,"USD"))/1000000 -> 0 | E149: =E148+D149 -> 139.22354 | G149: =SUM($D$137:D148) -> 139.22354 | H149: =SUM($D$137:D149) -> 139.22354 | I149: =IF(D149<0,G149,H149) -> 139.22354
... B152: Contribution | C152: Contribution | D152: =(SUMIFS(Movement!$H$4:$H$2133,Movement!$L$4:$L$2133,'>>Chart'!C152,Movement!$O$4:$O$2133,Summary!$B$4,Movement!$M$4:$M$2133,"VND"))/Fx_rate/1000000+(SUMIFS(Movement!$H$4:$H$2133,Movement!$L$4:$L$2133,'>>Chart'!C152,Movement!$O$4:$O$2133,Summary!$B$4,Movement!$M$4:$M$2133,"USD"))/1000000 -> 0 | E152: =E151+D152 -> 139.22354 | G152: =SUM($D$137:D151) -> 139.22354 | H152: =SUM($D$137:D152) -> 139.22354 | I152: =IF(D152<0,G152,H152) -> 139.22354
B153: Fx.diff | C153: Fx.diff | D153: =G111-SUM(D137:D152) -> 22.922636 | E153: =E152+D153 -> 162.14618 | G153: =SUM($D$137:D152) -> 139.22354 | H153: =SUM($D$137:D153) -> 162.14618 | I153: =IF(D153<0,G153,H153) -> 162.14618
B154: E.O.P | C154: E.O.P | F154: =SUM(D137:D153) -> 162.14618
D161: Pre-allocation | E161: Post-allocation | F161: Spacing | G161: Positive error | H161: Negative error
B162: VIETINBANK - TIEN SON | C162: VTB-TS | D162: =(SUMIFS(CM_Cash!$B$68:$B$91,CM_Cash!$A$68:$A$91,'>>Chart'!$B162)+SUMIFS(CM_Cash!$D$68:$D$91,CM_Cash!$A$68:$A$91,'>>Chart'!$B162)+SUMIFS(CM_Cash!$E$68:$E$91,CM_Cash!$A$68:$A$91,'>>Chart'!$B162))/1000000000 -> 800.37055 | E162: =(SUMIFS(CM_Cash!$I$68:$I$91,CM_Cash!$A$68:$A$91,'>>Chart'!$B162)+SUMIFS(CM_Cash!$J$68:$J$91,CM_Cash!$A$68:$A$91,'>>Chart'!$B162)+SUMIFS(CM_Cash!$K$68:$K$91,CM_Cash!$A$68:$A$91,'>>Chart'!$B162))/1000000000 -> 800.37055 | F162: =F163+1 -> 14 | G162: =IF(E162>D162,E162-D162,0) -> 0 | H162: =IF(E162<D162,D162-E162,0) -> 0
B163: VIETINBANK - BINH DUONG | C163: VTB-BD | D163: =(SUMIFS(CM_Cash!$B$68:$B$91,CM_Cash!$A$68:$A$91,'>>Chart'!$B163)+SUMIFS(CM_Cash!$D$68:$D$91,CM_Cash!$A$68:$A$91,'>>Chart'!$B163)+SUMIFS(CM_Cash!$E$68:$E$91,CM_Cash!$A$68:$A$91,'>>Chart'!$B163))/1000000000 -> 481.76923 | E163: =(SUMIFS(CM_Cash!$I$68:$I$91,CM_Cash!$A$68:$A$91,'>>Chart'!$B163)+SUMIFS(CM_Cash!$J$68:$J$91,CM_Cash!$A$68:$A$91,'>>Chart'!$B163)+SUMIFS(CM_Cash!$K$68:$K$91,CM_Cash!$A$68:$A$91,'>>Chart'!$B163))/1000000000 -> 481.76923 | F163: =F164+1 -> 13 | G163: =IF(E163>D163,E163-D163,0) -> 0 | H163: =IF(E163<D163,D163-E163,0) -> 0
B164: VIETINBANK - QUANG MINH | C164: VTB-QM | D164: =(SUMIFS(CM_Cash!$B$68:$B$91,CM_Cash!$A$68:$A$91,'>>Chart'!$B164)+SUMIFS(CM_Cash!$D$68:$D$91,CM_Cash!$A$68:$A$91,'>>Chart'!$B164)+SUMIFS(CM_Cash!$E$68:$E$91,CM_Cash!$A$68:$A$91,'>>Chart'!$B164))/1000000000 -> 62.969189 | E164: =(SUMIFS(CM_Cash!$I$68:$I$91,CM_Cash!$A$68:$A$91,'>>Chart'!$B164)+SUMIFS(CM_Cash!$J$68:$J$91,CM_Cash!$A$68:$A$91,'>>Chart'!$B164)+SUMIFS(CM_Cash!$K$68:$K$91,CM_Cash!$A$68:$A$91,'>>Chart'!$B164))/1000000000 -> 62.969189 | F164: =F165+1 -> 12 | G164: =IF(E164>D164,E164-D164,0) -> 0 | H164: =IF(E164<D164,D164-E164,0) -> 0
B165: VIETINBANK - DONG SAI GON | C165: VTB-DSG | D165: =(SUMIFS(CM_Cash!$B$68:$B$91,CM_Cash!$A$68:$A$91,'>>Chart'!$B165)+SUMIFS(CM_Cash!$D$68:$D$91,CM_Cash!$A$68:$A$91,'>>Chart'!$B165)+SUMIFS(CM_Cash!$E$68:$E$91,CM_Cash!$A$68:$A$91,'>>Chart'!$B165))/1000000000 -> 105.91471 | E165: =(SUMIFS(CM_Cash!$I$68:$I$91,CM_Cash!$A$68:$A$91,'>>Chart'!$B165)+SUMIFS(CM_Cash!$J$68:$J$91,CM_Cash!$A$68:$A$91,'>>Chart'!$B165)+SUMIFS(CM_Cash!$K$68:$K$91,CM_Cash!$A$68:$A$91,'>>Chart'!$B165))/1000000000 -> 105.91471 | F165: =F166+1 -> 11 | G165: =IF(E165>D165,E165-D165,0) -> 0 | H165: =IF(E165<D165,D165-E165,0) -> 0
B166: VIETINBANK - CN1 | C166: VTB-CN1 | D166: =(SUMIFS(CM_Cash!$B$68:$B$91,CM_Cash!$A$68:$A$91,'>>Chart'!$B166)+SUMIFS(CM_Cash!$D$68:$D$91,CM_Cash!$A$68:$A$91,'>>Chart'!$B166)+SUMIFS(CM_Cash!$E$68:$E$91,CM_Cash!$A$68:$A$91,'>>Chart'!$B166))/1000000000 -> 58.873963 | E166: =(SUMIFS(CM_Cash!$I$68:$I$91,CM_Cash!$A$68:$A$91,'>>Chart'!$B166)+SUMIFS(CM_Cash!$J$68:$J$91,CM_Cash!$A$68:$A$91,'>>Chart'!$B166)+SUMIFS(CM_Cash!$K$68:$K$91,CM_Cash!$A$68:$A$91,'>>Chart'!$B166))/1000000000 -> 58.873963 | F166: =F167+1 -> 10 | G166: =IF(E166>D166,E166-D166,0) -> 0 | H166: =IF(E166<D166,D166-E166,0) -> 0
B167: BIDV - THANH XUAN | C167: BIDV-TX | D167: =(SUMIFS(CM_Cash!$B$68:$B$91,CM_Cash!$A$68:$A$91,'>>Chart'!$B167)+SUMIFS(CM_Cash!$D$68:$D$91,CM_Cash!$A$68:$A$91,'>>Chart'!$B167)+SUMIFS(CM_Cash!$E$68:$E$91,CM_Cash!$A$68:$A$91,'>>Chart'!$B167))/1000000000 -> 293.67849 | E167: =(SUMIFS(CM_Cash!$I$68:$I$91,CM_Cash!$A$68:$A$91,'>>Chart'!$B167)+SUMIFS(CM_Cash!$J$68:$J$91,CM_Cash!$A$68:$A$91,'>>Chart'!$B167)+SUMIFS(CM_Cash!$K$68:$K$91,CM_Cash!$A$68:$A$91,'>>Chart'!$B167))/1000000000 -> 293.67849 | F167: =F168+1 -> 9 | G167: =IF(E167>D167,E167-D167,0) -> 0 | H167: =IF(E167<D167,D167-E167,0) -> 0
B168: BIDV - NAM SAI GON | C168: BIDV-NSG | D168: =(SUMIFS(CM_Cash!$B$68:$B$91,CM_Cash!$A$68:$A$91,'>>Chart'!$B168)+SUMIFS(CM_Cash!$D$68:$D$91,CM_Cash!$A$68:$A$91,'>>Chart'!$B168)+SUMIFS(CM_Cash!$E$68:$E$91,CM_Cash!$A$68:$A$91,'>>Chart'!$B168))/1000000000 -> 82.158268 | E168: =(SUMIFS(CM_Cash!$I$68:$I$91,CM_Cash!$A$68:$A$91,'>>Chart'!$B168)+SUMIFS(CM_Cash!$J$68:$J$91,CM_Cash!$A$68:$A$91,'>>Chart'!$B168)+SUMIFS(CM_Cash!$K$68:$K$91,CM_Cash!$A$68:$A$91,'>>Chart'!$B168))/1000000000 -> 82.158268 | F168: =F169+1 -> 8 | G168: =IF(E168>D168,E168-D168,0) -> 0 | H168: =IF(E168<D168,D168-E168,0) -> 0
B169: BIDV - LONG BIEN | C169: BIDV-LB | D169: =(SUMIFS(CM_Cash!$B$68:$B$91,CM_Cash!$A$68:$A$91,'>>Chart'!$B169)+SUMIFS(CM_Cash!$D$68:$D$91,CM_Cash!$A$68:$A$91,'>>Chart'!$B169)+SUMIFS(CM_Cash!$E$68:$E$91,CM_Cash!$A$68:$A$91,'>>Chart'!$B169))/1000000000 -> 0.1016279 | E169: =(SUMIFS(CM_Cash!$I$68:$I$91,CM_Cash!$A$68:$A$91,'>>Chart'!$B169)+SUMIFS(CM_Cash!$J$68:$J$91,CM_Cash!$A$68:$A$91,'>>Chart'!$B169)+SUMIFS(CM_Cash!$K$68:$K$91,CM_Cash!$A$68:$A$91,'>>Chart'!$B169))/1000000000 -> 0.1016279 | F169: =F170+1 -> 7 | G169: =IF(E169>D169,E169-D169,0) -> 0 | H169: =IF(E169<D169,D169-E169,0) -> 0
B170: VIETCOMBANK - HCM | C170: VCB-HCM | D170: =(SUMIFS(CM_Cash!$B$68:$B$91,CM_Cash!$A$68:$A$91,'>>Chart'!$B170)+SUMIFS(CM_Cash!$D$68:$D$91,CM_Cash!$A$68:$A$91,'>>Chart'!$B170)+SUMIFS(CM_Cash!$E$68:$E$91,CM_Cash!$A$68:$A$91,'>>Chart'!$B170))/1000000000 -> 1439.3669 | E170: =(SUMIFS(CM_Cash!$I$68:$I$91,CM_Cash!$A$68:$A$91,'>>Chart'!$B170)+SUMIFS(CM_Cash!$J$68:$J$91,CM_Cash!$A$68:$A$91,'>>Chart'!$B170)+SUMIFS(CM_Cash!$K$68:$K$91,CM_Cash!$A$68:$A$91,'>>Chart'!$B170))/1000000000 -> 1439.3669 | F170: =F171+1 -> 6 | G170: =IF(E170>D170,E170-D170,0) -> 0 | H170: =IF(E170<D170,D170-E170,0) -> 0
B171: VIETCOMBANK - BA DINH | C171: VCB-BD | D171: =(SUMIFS(CM_Cash!$B$68:$B$91,CM_Cash!$A$68:$A$91,'>>Chart'!$B171)+SUMIFS(CM_Cash!$D$68:$D$91,CM_Cash!$A$68:$A$91,'>>Chart'!$B171)+SUMIFS(CM_Cash!$E$68:$E$91,CM_Cash!$A$68:$A$91,'>>Chart'!$B171))/1000000000 -> 121.50741 | E171: =(SUMIFS(CM_Cash!$I$68:$I$91,CM_Cash!$A$68:$A$91,'>>Chart'!$B171)+SUMIFS(CM_Cash!$J$68:$J$91,CM_Cash!$A$68:$A$91,'>>Chart'!$B171)+SUMIFS(CM_Cash!$K$68:$K$91,CM_Cash!$A$68:$A$91,'>>Chart'!$B171))/1000000000 -> 121.50741 | F171: =F172+1 -> 5 | G171: =IF(E171>D171,E171-D171,0) -> 0 | H171: =IF(E171<D171,D171-E171,0) -> 0
B172: OCB - BINH DUONG | C172: OCB-BD | D172: =(SUMIFS(CM_Cash!$B$68:$B$91,CM_Cash!$A$68:$A$91,'>>Chart'!$B172)+SUMIFS(CM_Cash!$D$68:$D$91,CM_Cash!$A$68:$A$91,'>>Chart'!$B172)+SUMIFS(CM_Cash!$E$68:$E$91,CM_Cash!$A$68:$A$91,'>>Chart'!$B172))/1000000000 -> 0.5986292 | E172: =(SUMIFS(CM_Cash!$I$68:$I$91,CM_Cash!$A$68:$A$91,'>>Chart'!$B172)+SUMIFS(CM_Cash!$J$68:$J$91,CM_Cash!$A$68:$A$91,'>>Chart'!$B172)+SUMIFS(CM_Cash!$K$68:$K$91,CM_Cash!$A$68:$A$91,'>>Chart'!$B172))/1000000000 -> 0.5986292 | F172: =F173+1 -> 4 | G172: =IF(E172>D172,E172-D172,0) -> 0 | H172: =IF(E172<D172,D172-E172,0) -> 0
B173: VIB - HOI SO | C173: VIB-HO | D173: =(SUMIFS(CM_Cash!$B$68:$B$91,CM_Cash!$A$68:$A$91,'>>Chart'!$B173)+SUMIFS(CM_Cash!$D$68:$D$91,CM_Cash!$A$68:$A$91,'>>Chart'!$B173)+SUMIFS(CM_Cash!$E$68:$E$91,CM_Cash!$A$68:$A$91,'>>Chart'!$B173))/1000000000 -> 174.39579 | E173: =(SUMIFS(CM_Cash!$I$68:$I$91,CM_Cash!$A$68:$A$91,'>>Chart'!$B173)+SUMIFS(CM_Cash!$J$68:$J$91,CM_Cash!$A$68:$A$91,'>>Chart'!$B173)+SUMIFS(CM_Cash!$K$68:$K$91,CM_Cash!$A$68:$A$91,'>>Chart'!$B173))/1000000000 -> 174.39579 | F173: =F174+1 -> 3 | G173: =IF(E173>D173,E173-D173,0) -> 0 | H173: =IF(E173<D173,D173-E173,0) -> 0
B174: MB - BAC SAI GON | C174: MB-BSG | D174: =(SUMIFS(CM_Cash!$B$68:$B$91,CM_Cash!$A$68:$A$91,'>>Chart'!$B174)+SUMIFS(CM_Cash!$D$68:$D$91,CM_Cash!$A$68:$A$91,'>>Chart'!$B174)+SUMIFS(CM_Cash!$E$68:$E$91,CM_Cash!$A$68:$A$91,'>>Chart'!$B174))/1000000000 -> 0.007958304 | E174: =(SUMIFS(CM_Cash!$I$68:$I$91,CM_Cash!$A$68:$A$91,'>>Chart'!$B174)+SUMIFS(CM_Cash!$J$68:$J$91,CM_Cash!$A$68:$A$91,'>>Chart'!$B174)+SUMIFS(CM_Cash!$K$68:$K$91,CM_Cash!$A$68:$A$91,'>>Chart'!$B174))/1000000000 -> 0.007958304 | F174: =F175+1 -> 2 | G174: =IF(E174>D174,E174-D174,0) -> 0 | H174: =IF(E174<D174,D174-E174,0) -> 0
B175: SINOPAC | C175: SINO | D175: =(SUMIFS(CM_Cash!$B$68:$B$91,CM_Cash!$A$68:$A$91,'>>Chart'!$B175)+SUMIFS(CM_Cash!$D$68:$D$91,CM_Cash!$A$68:$A$91,'>>Chart'!$B175)+SUMIFS(CM_Cash!$E$68:$E$91,CM_Cash!$A$68:$A$91,'>>Chart'!$B175))/1000000000 -> 139.80928 | E175: =(SUMIFS(CM_Cash!$I$68:$I$91,CM_Cash!$A$68:$A$91,'>>Chart'!$B175)+SUMIFS(CM_Cash!$J$68:$J$91,CM_Cash!$A$68:$A$91,'>>Chart'!$B175)+SUMIFS(CM_Cash!$K$68:$K$91,CM_Cash!$A$68:$A$91,'>>Chart'!$B175))/1000000000 -> 139.80928 | F175: 1 | G175: =IF(E175>D175,E175-D175,0) -> 0 | H175: =IF(E175<D175,D175-E175,0) -> 0
D179: Pre-allocation | E179: Post-allocation | F179: Spacing | G179: Positive error | H179: Negative error
B180: VIETINBANK - TIEN SON | C180: VTB-TS | D180: =(SUMIFS(CM_Cash!$O$68:$O$91,CM_Cash!$A$68:$A$91,'>>Chart'!$B180)+SUMIFS(CM_Cash!$P$68:$P$91,CM_Cash!$A$68:$A$91,'>>Chart'!$B180)+SUMIFS(CM_Cash!$Q$68:$Q$91,CM_Cash!$A$68:$A$91,'>>Chart'!$B180))/1000000 -> 0.03131184 | E180: =(SUMIFS(CM_Cash!$U$68:$U$91,CM_Cash!$A$68:$A$91,'>>Chart'!$B180)+SUMIFS(CM_Cash!$V$68:$V$91,CM_Cash!$A$68:$A$91,'>>Chart'!$B180)+SUMIFS(CM_Cash!$W$68:$W$91,CM_Cash!$A$68:$A$91,'>>Chart'!$B180))/1000000 -> 0.03131184 | F180: =F181+1 -> 14 | G180: =IF(E180>D180,E180-D180,0) -> 0 | H180: =IF(E180<D180,D180-E180,0) -> 0
B181: VIETINBANK - BINH DUONG | C181: VTB-BD | D181: =(SUMIFS(CM_Cash!$O$68:$O$91,CM_Cash!$A$68:$A$91,'>>Chart'!$B181)+SUMIFS(CM_Cash!$P$68:$P$91,CM_Cash!$A$68:$A$91,'>>Chart'!$B181)+SUMIFS(CM_Cash!$Q$68:$Q$91,CM_Cash!$A$68:$A$91,'>>Chart'!$B181))/1000000 -> 0.00331614 | E181: =(SUMIFS(CM_Cash!$U$68:$U$91,CM_Cash!$A$68:$A$91,'>>Chart'!$B181)+SUMIFS(CM_Cash!$V$68:$V$91,CM_Cash!$A$68:$A$91,'>>Chart'!$B181)+SUMIFS(CM_Cash!$W$68:$W$91,CM_Cash!$A$68:$A$91,'>>Chart'!$B181))/1000000 -> 0.00331614 | F181: =F182+1 -> 13 | G181: =IF(E181>D181,E181-D181,0) -> 0 | H181: =IF(E181<D181,D181-E181,0) -> 0
B182: VIETINBANK - QUANG MINH | C182: VTB-QM | D182: =(SUMIFS(CM_Cash!$O$68:$O$91,CM_Cash!$A$68:$A$91,'>>Chart'!$B182)+SUMIFS(CM_Cash!$P$68:$P$91,CM_Cash!$A$68:$A$91,'>>Chart'!$B182)+SUMIFS(CM_Cash!$Q$68:$Q$91,CM_Cash!$A$68:$A$91,'>>Chart'!$B182))/1000000 -> 0.0002 | E182: =(SUMIFS(CM_Cash!$U$68:$U$91,CM_Cash!$A$68:$A$91,'>>Chart'!$B182)+SUMIFS(CM_Cash!$V$68:$V$91,CM_Cash!$A$68:$A$91,'>>Chart'!$B182)+SUMIFS(CM_Cash!$W$68:$W$91,CM_Cash!$A$68:$A$91,'>>Chart'!$B182))/1000000 -> 0.0002 | F182: =F183+1 -> 12 | G182: =IF(E182>D182,E182-D182,0) -> 0 | H182: =IF(E182<D182,D182-E182,0) -> 0
B183: VIETINBANK - DONG SAI GON | C183: VTB-DSG | D183: =(SUMIFS(CM_Cash!$O$68:$O$91,CM_Cash!$A$68:$A$91,'>>Chart'!$B183)+SUMIFS(CM_Cash!$P$68:$P$91,CM_Cash!$A$68:$A$91,'>>Chart'!$B183)+SUMIFS(CM_Cash!$Q$68:$Q$91,CM_Cash!$A$68:$A$91,'>>Chart'!$B183))/1000000 -> 0.000769 | E183: =(SUMIFS(CM_Cash!$U$68:$U$91,CM_Cash!$A$68:$A$91,'>>Chart'!$B183)+SUMIFS(CM_Cash!$V$68:$V$91,CM_Cash!$A$68:$A$91,'>>Chart'!$B183)+SUMIFS(CM_Cash!$W$68:$W$91,CM_Cash!$A$68:$A$91,'>>Chart'!$B183))/1000000 -> 0.000769 | F183: =F184+1 -> 11 | G183: =IF(E183>D183,E183-D183,0) -> 0 | H183: =IF(E183<D183,D183-E183,0) -> 0
...

Sheet Sheet5
A1: Grouping | B1: Subsidiaries
A3: Row Labels | B3: Sum of Net
A4: Internal transfer in | B4: 8200000000 | D4: =B4/24000/10^6 -> 0.34166667
A5: Other receipts | B5: 738950017 | D5: =B5/24000/10^6 -> 0.030789584
A6: Receipt from tenants | B6: 15707326732 | D6: =B6/24000/10^6 -> 0.65447195
A7: Grand Total | B7: 24646276749 | D7: =B7/24000/10^6 -> 1.0269282
D8: =B8/24000/10^6 -> 0
D9: =B9/24000/10^6 -> 0
D10: =B10/24000/10^6 -> 0
D11: =B11/24000/10^6 -> 0
D12: =B12/24000/10^6 -> 0 | E12: ok

Sheet Summary
A1: Date | B1: 46037
A2: Ver | B2: 1
A3: FX rate (VND/USD) | B3: 26175
A4: Week | B4: W1-2Jan26
A5: Opening date | B5: 46023
A6: Ending date | B6: 46037
A8: ="1. Outstanding cash @ "&TEXT(B6,"dd/mm/yyyy") -> 1. Outstanding cash @ 15/01/2026
A10: ="Total cash ending balance of BWID Group was US"&TEXT($D$18,"$#,###.00")&"mn equivalent, in which US"&TEXT(D15,"$#,###.00")&"mn at BWID JSC ("&TEXT($D$15/$D$18,"#.00%")&"), US"&TEXT($D$16,"$#,###.00")&"mn at VC3 ("&TEXT($D$16/$D$18,"#.00%")&"), and US"&TEXT(D17,"$#,###.00")&"mn at Subsidiaries ("&TEXT($D$17/$D$18,"#.00%")&")" -> Total cash ending balance of BWID Group was US$162,14618mn equivalent, in which US$1,50415mn at BWID JSC (01%), US$71,64870mn at VC3 (44%), and US$88,99333mn at Subsidiaries (55%)
A11: ="Total cash of BWID group from "&TEXT($B$5,"dd-mmm-yy")&" to "&TEXT($B$6,"dd-mmm-yy")&" "&IF($E$78+$E$94>0,"increased",IF($E$78+$E$94=0,"remained unchange","decreased"))&" by "&TEXT(ABS($E$78+$E$94),"$##0.0")&"mn ("&TEXT(($E$78+$E$94)/$E$77,"#0.00%")&")" -> Total cash of BWID group from 01-Jan-26 to 15-Jan-26 increased by $28mn (021%)
A13: Entity | B13: Cash in original VND | C13: Cash in original USD | D13: Total cash
B14: in USDmn equivalent | C14: in USDmn | D14: in USDmn equivalent | F14: Cash in original VND
A15: BWID JSC | B15: =SUMIFS('Cash Balance'!$L$4:$L$920,'Cash Balance'!$W$4:$W$920,Summary!$A15)/1000000/Fx_rate -> 1.4846825 | C15: =SUMIFS('Cash Balance'!$T$4:$T$920,'Cash Balance'!$W$4:$W$920,Summary!$A15)/1000000 -> 0.01946847 | D15: =B15+C15 -> 1.504151 | F15: =SUMIFS('Cash Balance'!$L$4:$L$920,'Cash Balance'!$W$4:$W$920,Summary!$A15) -> 38861564578
A16: VC3 | B16: =SUMIFS('Cash Balance'!$L$4:$L$920,'Cash Balance'!$W$4:$W$920,Summary!$A16)/1000000/Fx_rate -> 71.63907 | C16: =SUMIFS('Cash Balance'!$T$4:$T$920,'Cash Balance'!$W$4:$W$920,Summary!$A16)/1000000 -> 0.00962906 | D16: =B16+C16 -> 71.648699 | F16: =SUMIFS('Cash Balance'!$L$4:$L$920,'Cash Balance'!$W$4:$W$920,Summary!$A16) -> 1875152665621
A17: Subsidiaries | B17: =SUMIFS('Cash Balance'!$L$4:$L$920,'Cash Balance'!$W$4:$W$920,Summary!$A17)/1000000/Fx_rate -> 88.956757 | C17: =SUMIFS('Cash Balance'!$T$4:$T$920,'Cash Balance'!$W$4:$W$920,Summary!$A17)/1000000 -> 0.03657006 | D17: =B17+C17 -> 88.993328 | F17: =SUMIFS('Cash Balance'!$L$4:$L$920,'Cash Balance'!$W$4:$W$920,Summary!$A17) -> 2328443126281
A18: Total | B18: =SUM(B15:B17) -> 162.08051 | C18: =SUM(C15:C17) -> 0.06566759 | D18: =SUM(D15:D17) -> 162.14618 | F18: =SUM(F15:F17) -> 4242457356480
A30: ="In which, BWID Group's cash is mainly at VIETINBANK: US"&TEXT(E34,"$#,###.00")&"mn ("&TEXT(F34,"#.00%")&") , VIETCOMBANK: USD"&TEXT(E42,"$#,###.00")&"mn ("&TEXT(F42,"#.00%")&"), and BIDV: USD"&TEXT(E47,"$#,###.00")&"mn ("&TEXT(F47,"#.00%")&")" -> In which, BWID Group's cash is mainly at VIETINBANK: US$63,76119mn (39%) , VIETCOMBANK: USD$59,64026mn (37%), and BIDV: USD$14,36308mn (09%)
B32: BWID JSC | C32: VC3 | D32: Subsidiaries | E32: Total | F32: %
B33: in USDmn equivalent | C33: in USDmn equivalent | D33: in USDmn equivalent | E33: in USDmn equivalent
A34: VIETINBANK | B34: =SUBTOTAL(9,B35:B41) -> 0.27439845 | C34: =SUBTOTAL(9,C35:C41) -> 14.281298 | D34: =SUBTOTAL(9,D35:D41) -> 49.205493 | E34: =SUBTOTAL(9,E35:E41) -> 63.76119 | F34: =SUBTOTAL(9,F35:F41) -> 0.39323276
A35: VIETINBANK - TIEN SON | B35: =SUMIFS('Cash Balance'!$L$4:$L$920,'Cash Balance'!$W$4:$W$920,Summary!B$32,'Cash Balance'!$Y$4:$Y$920,Summary!$A35)/Fx_rate/1000000+SUMIFS('Cash Balance'!$T$4:$T$920,'Cash Balance'!$W$4:$W$920,Summary!B$32,'Cash Balance'!$Y$4:$Y$920,Summary!$A35)/1000000 -> 0.0013094371 | C35: =SUMIFS('Cash Balance'!$L$4:$L$920,'Cash Balance'!$W$4:$W$920,Summary!C$32,'Cash Balance'!$Y$4:$Y$920,Summary!$A35)/Fx_rate/1000000+SUMIFS('Cash Balance'!$T$4:$T$920,'Cash Balance'!$W$4:$W$920,Summary!C$32,'Cash Balance'!$Y$4:$Y$920,Summary!$A35)/1000000 -> 9.9968845 | D35: =SUMIFS('Cash Balance'!$L$4:$L$920,'Cash Balance'!$W$4:$W$920,Summary!D$32,'Cash Balance'!$Y$4:$Y$920,Summary!$A35)/Fx_rate/1000000+SUMIFS('Cash Balance'!$T$4:$T$920,'Cash Balance'!$W$4:$W$920,Summary!D$32,'Cash Balance'!$Y$4:$Y$920,Summary!$A35)/1000000 -> 20.61079 | E35: =SUM(B35:D35) -> 30.608983 | F35: =E35/$E$63 -> 0.18877401
A36: VIETINBANK - BINH DUONG + QM | B36: =SUMIFS('Cash Balance'!$L$4:$L$920,'Cash Balance'!$W$4:$W$920,Summary!B$32,'Cash Balance'!$Y$4:$Y$920,Summary!$A36)/Fx_rate/1000000+SUMIFS('Cash Balance'!$T$4:$T$920,'Cash Balance'!$W$4:$W$920,Summary!B$32,'Cash Balance'!$Y$4:$Y$920,Summary!$A36)/1000000 -> 0.26810015 | C36: =SUMIFS('Cash Balance'!$L$4:$L$920,'Cash Balance'!$W$4:$W$920,Summary!C$32,'Cash Balance'!$Y$4:$Y$920,Summary!$A36)/Fx_rate/1000000+SUMIFS('Cash Balance'!$T$4:$T$920,'Cash Balance'!$W$4:$W$920,Summary!C$32,'Cash Balance'!$Y$4:$Y$920,Summary!$A36)/1000000 -> 4.2206393 | D36: =SUMIFS('Cash Balance'!$L$4:$L$920,'Cash Balance'!$W$4:$W$920,Summary!D$32,'Cash Balance'!$Y$4:$Y$920,Summary!$A36)/Fx_rate/1000000+SUMIFS('Cash Balance'!$T$4:$T$920,'Cash Balance'!$W$4:$W$920,Summary!D$32,'Cash Balance'!$Y$4:$Y$920,Summary!$A36)/1000000 -> 16.326178 | E36: =SUM(B36:D36) -> 20.814917 | F36: =E36/$E$63 -> 0.12837131
A37: VIETINBANK - DONG SAI GON | B37: =SUMIFS('Cash Balance'!$L$4:$L$920,'Cash Balance'!$W$4:$W$920,Summary!B$32,'Cash Balance'!$Y$4:$Y$920,Summary!$A37)/Fx_rate/1000000+SUMIFS('Cash Balance'!$T$4:$T$920,'Cash Balance'!$W$4:$W$920,Summary!B$32,'Cash Balance'!$Y$4:$Y$920,Summary!$A37)/1000000 -> 0.000769 | C37: =SUMIFS('Cash Balance'!$L$4:$L$920,'Cash Balance'!$W$4:$W$920,Summary!C$32,'Cash Balance'!$Y$4:$Y$920,Summary!$A37)/Fx_rate/1000000+SUMIFS('Cash Balance'!$T$4:$T$920,'Cash Balance'!$W$4:$W$920,Summary!C$32,'Cash Balance'!$Y$4:$Y$920,Summary!$A37)/1000000 -> 0.00015646415 | D37: =SUMIFS('Cash Balance'!$L$4:$L$920,'Cash Balance'!$W$4:$W$920,Summary!D$32,'Cash Balance'!$Y$4:$Y$920,Summary!$A37)/Fx_rate/1000000+SUMIFS('Cash Balance'!$T$4:$T$920,'Cash Balance'!$W$4:$W$920,Summary!D$32,'Cash Balance'!$Y$4:$Y$920,Summary!$A37)/1000000 -> 4.0462508 | E37: =SUM(B37:D37) -> 4.0471763 | F37: =E37/$E$63 -> 0.024960048
A38: VIETINBANK - CN1 | B38: =SUMIFS('Cash Balance'!$L$4:$L$920,'Cash Balance'!$W$4:$W$920,Summary!B$32,'Cash Balance'!$Y$4:$Y$920,Summary!$A38)/Fx_rate/1000000+SUMIFS('Cash Balance'!$T$4:$T$920,'Cash Balance'!$W$4:$W$920,Summary!B$32,'Cash Balance'!$Y$4:$Y$920,Summary!$A38)/1000000 -> 0.0042198677 | C38: =SUMIFS('Cash Balance'!$L$4:$L$920,'Cash Balance'!$W$4:$W$920,Summary!C$32,'Cash Balance'!$Y$4:$Y$920,Summary!$A38)/Fx_rate/1000000+SUMIFS('Cash Balance'!$T$4:$T$920,'Cash Balance'!$W$4:$W$920,Summary!C$32,'Cash Balance'!$Y$4:$Y$920,Summary!$A38)/1000000 -> 0.0071336651 | D38: =SUMIFS('Cash Balance'!$L$4:$L$920,'Cash Balance'!$W$4:$W$920,Summary!D$32,'Cash Balance'!$Y$4:$Y$920,Summary!$A38)/Fx_rate/1000000+SUMIFS('Cash Balance'!$T$4:$T$920,'Cash Balance'!$W$4:$W$920,Summary!D$32,'Cash Balance'!$Y$4:$Y$920,Summary!$A38)/1000000 -> 2.2391806 | E38: =SUM(B38:D38) -> 2.2505342 | F38: =E38/$E$63 -> 0.013879662
A39: VIETINBANK - HA NOI | B39: =SUMIFS('Cash Balance'!$L$4:$L$920,'Cash Balance'!$W$4:$W$920,Summary!B$32,'Cash Balance'!$Y$4:$Y$920,Summary!$A39)/Fx_rate/1000000+SUMIFS('Cash Balance'!$T$4:$T$920,'Cash Balance'!$W$4:$W$920,Summary!B$32,'Cash Balance'!$Y$4:$Y$920,Summary!$A39)/1000000 -> 0 | C39: =SUMIFS('Cash Balance'!$L$4:$L$920,'Cash Balance'!$W$4:$W$920,Summary!C$32,'Cash Balance'!$Y$4:$Y$920,Summary!$A39)/Fx_rate/1000000+SUMIFS('Cash Balance'!$T$4:$T$920,'Cash Balance'!$W$4:$W$920,Summary!C$32,'Cash Balance'!$Y$4:$Y$920,Summary!$A39)/1000000 -> 0 | D39: =SUMIFS('Cash Balance'!$L$4:$L$920,'Cash Balance'!$W$4:$W$920,Summary!D$32,'Cash Balance'!$Y$4:$Y$920,Summary!$A39)/Fx_rate/1000000+SUMIFS('Cash Balance'!$T$4:$T$920,'Cash Balance'!$W$4:$W$920,Summary!D$32,'Cash Balance'!$Y$4:$Y$920,Summary!$A39)/1000000 -> 0 | E39: =SUM(B39:D39) -> 0 | F39: =E39/$E$63 -> 0
A40: VIETINBANK - TPHCM | B40: =SUMIFS('Cash Balance'!$L$4:$L$920,'Cash Balance'!$W$4:$W$920,Summary!B$32,'Cash Balance'!$Y$4:$Y$920,Summary!$A40)/Fx_rate/1000000+SUMIFS('Cash Balance'!$T$4:$T$920,'Cash Balance'!$W$4:$W$920,Summary!B$32,'Cash Balance'!$Y$4:$Y$920,Summary!$A40)/1000000 -> 0 | C40: =SUMIFS('Cash Balance'!$L$4:$L$920,'Cash Balance'!$W$4:$W$920,Summary!C$32,'Cash Balance'!$Y$4:$Y$920,Summary!$A40)/Fx_rate/1000000+SUMIFS('Cash Balance'!$T$4:$T$920,'Cash Balance'!$W$4:$W$920,Summary!C$32,'Cash Balance'!$Y$4:$Y$920,Summary!$A40)/1000000 -> 0.05648412 | D40: =SUMIFS('Cash Balance'!$L$4:$L$920,'Cash Balance'!$W$4:$W$920,Summary!D$32,'Cash Balance'!$Y$4:$Y$920,Summary!$A40)/Fx_rate/1000000+SUMIFS('Cash Balance'!$T$4:$T$920,'Cash Balance'!$W$4:$W$920,Summary!D$32,'Cash Balance'!$Y$4:$Y$920,Summary!$A40)/1000000 -> 5.9830946 | E40: =SUM(B40:D40) -> 6.0395787 | F40: =E40/$E$63 -> 0.03724774
A41: VIETINBANK - CN6 | B41: =SUMIFS('Cash Balance'!$L$4:$L$920,'Cash Balance'!$W$4:$W$920,Summary!B$32,'Cash Balance'!$Y$4:$Y$920,Summary!$A41)/Fx_rate/1000000+SUMIFS('Cash Balance'!$T$4:$T$920,'Cash Balance'!$W$4:$W$920,Summary!B$32,'Cash Balance'!$Y$4:$Y$920,Summary!$A41)/1000000 -> 0 | C41: =SUMIFS('Cash Balance'!$L$4:$L$920,'Cash Balance'!$W$4:$W$920,Summary!C$32,'Cash Balance'!$Y$4:$Y$920,Summary!$A41)/Fx_rate/1000000+SUMIFS('Cash Balance'!$T$4:$T$920,'Cash Balance'!$W$4:$W$920,Summary!C$32,'Cash Balance'!$Y$4:$Y$920,Summary!$A41)/1000000 -> 0 | D41: =SUMIFS('Cash Balance'!$L$4:$L$920,'Cash Balance'!$W$4:$W$920,Summary!D$32,'Cash Balance'!$Y$4:$Y$920,Summary!$A41)/Fx_rate/1000000+SUMIFS('Cash Balance'!$T$4:$T$920,'Cash Balance'!$W$4:$W$920,Summary!D$32,'Cash Balance'!$Y$4:$Y$920,Summary!$A41)/1000000 -> 0 | E41: =SUM(B41:D41) -> 0 | F41: =E41/$E$63 -> 0
A42: VIETCOMBANK | B42: =SUBTOTAL(9,B43:B44) -> 0.028901303 | C42: =SUBTOTAL(9,C43:C44) -> 48.515364 | D42: =SUBTOTAL(9,D43:D44) -> 11.095992 | E42: =SUBTOTAL(9,E43:E44) -> 59.640257 | F42: =SUBTOTAL(9,F43:F44) -> 0.36781784
A43: VIETCOMBANK - HCM | B43: =SUMIFS('Cash Balance'!$L$4:$L$920,'Cash Balance'!$W$4:$W$920,Summary!B$32,'Cash Balance'!$Y$4:$Y$920,Summary!$A43)/Fx_rate/1000000+SUMIFS('Cash Balance'!$T$4:$T$920,'Cash Balance'!$W$4:$W$920,Summary!B$32,'Cash Balance'!$Y$4:$Y$920,Summary!$A43)/1000000 -> 0.011851238 | C43: =SUMIFS('Cash Balance'!$L$4:$L$920,'Cash Balance'!$W$4:$W$920,Summary!C$32,'Cash Balance'!$Y$4:$Y$920,Summary!$A43)/Fx_rate/1000000+SUMIFS('Cash Balance'!$T$4:$T$920,'Cash Balance'!$W$4:$W$920,Summary!C$32,'Cash Balance'!$Y$4:$Y$920,Summary!$A43)/1000000 -> 48.437015 | D43: =SUMIFS('Cash Balance'!$L$4:$L$920,'Cash Balance'!$W$4:$W$920,Summary!D$32,'Cash Balance'!$Y$4:$Y$920,Summary!$A43)/Fx_rate/1000000+SUMIFS('Cash Balance'!$T$4:$T$920,'Cash Balance'!$W$4:$W$920,Summary!D$32,'Cash Balance'!$Y$4:$Y$920,Summary!$A43)/1000000 -> 6.548025 | E43: =SUM(B43:D43) -> 54.996891 | F43: =E43/$E$63 -> 0.33918093
A44: VIETCOMBANK - BA DINH | B44: =SUMIFS('Cash Balance'!$L$4:$L$920,'Cash Balance'!$W$4:$W$920,Summary!B$32,'Cash Balance'!$Y$4:$Y$920,Summary!$A44)/Fx_rate/1000000+SUMIFS('Cash Balance'!$T$4:$T$920,'Cash Balance'!$W$4:$W$920,Summary!B$32,'Cash Balance'!$Y$4:$Y$920,Summary!$A44)/1000000 -> 0.017050065 | C44: =SUMIFS('Cash Balance'!$L$4:$L$920,'Cash Balance'!$W$4:$W$920,Summary!C$32,'Cash Balance'!$Y$4:$Y$920,Summary!$A44)/Fx_rate/1000000+SUMIFS('Cash Balance'!$T$4:$T$920,'Cash Balance'!$W$4:$W$920,Summary!C$32,'Cash Balance'!$Y$4:$Y$920,Summary!$A44)/1000000 -> 0.078349322 | D44: =SUMIFS('Cash Balance'!$L$4:$L$920,'Cash Balance'!$W$4:$W$920,Summary!D$32,'Cash Balance'!$Y$4:$Y$920,Summary!$A44)/Fx_rate/1000000+SUMIFS('Cash Balance'!$T$4:$T$920,'Cash Balance'!$W$4:$W$920,Summary!D$32,'Cash Balance'!$Y$4:$Y$920,Summary!$A44)/1000000 -> 4.5479666 | E44: =SUM(B44:D44) -> 4.643366 | F44: =E44/$E$63 -> 0.028636913
A45: VIETCOMBANK - NAM BINH DUONG | B45: =SUMIFS('Cash Balance'!$L$4:$L$920,'Cash Balance'!$W$4:$W$920,Summary!B$32,'Cash Balance'!$Y$4:$Y$920,Summary!$A45)/Fx_rate/1000000+SUMIFS('Cash Balance'!$T$4:$T$920,'Cash Balance'!$W$4:$W$920,Summary!B$32,'Cash Balance'!$Y$4:$Y$920,Summary!$A45)/1000000 -> 0 | C45: =SUMIFS('Cash Balance'!$L$4:$L$920,'Cash Balance'!$W$4:$W$920,Summary!C$32,'Cash Balance'!$Y$4:$Y$920,Summary!$A45)/Fx_rate/1000000+SUMIFS('Cash Balance'!$T$4:$T$920,'Cash Balance'!$W$4:$W$920,Summary!C$32,'Cash Balance'!$Y$4:$Y$920,Summary!$A45)/1000000 -> 0 | D45: =SUMIFS('Cash Balance'!$L$4:$L$920,'Cash Balance'!$W$4:$W$920,Summary!D$32,'Cash Balance'!$Y$4:$Y$920,Summary!$A45)/Fx_rate/1000000+SUMIFS('Cash Balance'!$T$4:$T$920,'Cash Balance'!$W$4:$W$920,Summary!D$32,'Cash Balance'!$Y$4:$Y$920,Summary!$A45)/1000000 -> 0.00031520745 | E45: =SUM(B45:D45) -> 0.00031520745 | F45: =E45/$E$63 -> 1.9439709e-06
A46: VIETCOMBANK - BINH TAY | B46: =SUMIFS('Cash Balance'!$L$4:$L$920,'Cash Balance'!$W$4:$W$920,Summary!B$32,'Cash Balance'!$Y$4:$Y$920,Summary!$A46)/Fx_rate/1000000+SUMIFS('Cash Balance'!$T$4:$T$920,'Cash Balance'!$W$4:$W$920,Summary!B$32,'Cash Balance'!$Y$4:$Y$920,Summary!$A46)/1000000 -> 0 | C46: =SUMIFS('Cash Balance'!$L$4:$L$920,'Cash Balance'!$W$4:$W$920,Summary!C$32,'Cash Balance'!$Y$4:$Y$920,Summary!$A46)/Fx_rate/1000000+SUMIFS('Cash Balance'!$T$4:$T$920,'Cash Balance'!$W$4:$W$920,Summary!C$32,'Cash Balance'!$Y$4:$Y$920,Summary!$A46)/1000000 -> 0 | D46: =SUMIFS('Cash Balance'!$L$4:$L$920,'Cash Balance'!$W$4:$W$920,Summary!D$32,'Cash Balance'!$Y$4:$Y$920,Summary!$A46)/Fx_rate/1000000+SUMIFS('Cash Balance'!$T$4:$T$920,'Cash Balance'!$W$4:$W$920,Summary!D$32,'Cash Balance'!$Y$4:$Y$920,Summary!$A46)/1000000 -> 7.1023075e-05 | E46: =SUM(B46:D46) -> 7.1023075e-05 | F46: =E46/$E$63 -> 4.3801881e-07
A47: BIDV | B47: =SUBTOTAL(9,B48:B51) -> 0.0015188622 | C47: =SUBTOTAL(9,C48:C51) -> 0.20850692 | D47: =SUBTOTAL(9,D48:D51) -> 14.153051 | E47: =SUBTOTAL(9,E48:E50) -> 14.363077 | F47: =SUBTOTAL(9,F48:F50) -> 0.08858104
A48: BIDV - THANH XUAN | B48: =SUMIFS('Cash Balance'!$L$4:$L$920,'Cash Balance'!$W$4:$W$920,Summary!B$32,'Cash Balance'!$Y$4:$Y$920,Summary!$A48)/Fx_rate/1000000+SUMIFS('Cash Balance'!$T$4:$T$920,'Cash Balance'!$W$4:$W$920,Summary!B$32,'Cash Balance'!$Y$4:$Y$920,Summary!$A48)/1000000 -> 0.0015188622 | C48: =SUMIFS('Cash Balance'!$L$4:$L$920,'Cash Balance'!$W$4:$W$920,Summary!C$32,'Cash Balance'!$Y$4:$Y$920,Summary!$A48)/Fx_rate/1000000+SUMIFS('Cash Balance'!$T$4:$T$920,'Cash Balance'!$W$4:$W$920,Summary!C$32,'Cash Balance'!$Y$4:$Y$920,Summary!$A48)/1000000 -> 0.20850692 | D48: =SUMIFS('Cash Balance'!$L$4:$L$920,'Cash Balance'!$W$4:$W$920,Summary!D$32,'Cash Balance'!$Y$4:$Y$920,Summary!$A48)/Fx_rate/1000000+SUMIFS('Cash Balance'!$T$4:$T$920,'Cash Balance'!$W$4:$W$920,Summary!D$32,'Cash Balance'!$Y$4:$Y$920,Summary!$A48)/1000000 -> 11.010221 | E48: =SUM(B48:D48) -> 11.220247 | F48: =E48/$E$63 -> 0.069198341
A49: BIDV - NAM SAI GON | B49: =SUMIFS('Cash Balance'!$L$4:$L$920,'Cash Balance'!$W$4:$W$920,Summary!B$32,'Cash Balance'!$Y$4:$Y$920,Summary!$A49)/Fx_rate/1000000+SUMIFS('Cash Balance'!$T$4:$T$920,'Cash Balance'!$W$4:$W$920,Summary!B$32,'Cash Balance'!$Y$4:$Y$920,Summary!$A49)/1000000 -> 0 | C49: =SUMIFS('Cash Balance'!$L$4:$L$920,'Cash Balance'!$W$4:$W$920,Summary!C$32,'Cash Balance'!$Y$4:$Y$920,Summary!$A49)/Fx_rate/1000000+SUMIFS('Cash Balance'!$T$4:$T$920,'Cash Balance'!$W$4:$W$920,Summary!C$32,'Cash Balance'!$Y$4:$Y$920,Summary!$A49)/1000000 -> 0 | D49: =SUMIFS('Cash Balance'!$L$4:$L$920,'Cash Balance'!$W$4:$W$920,Summary!D$32,'Cash Balance'!$Y$4:$Y$920,Summary!$A49)/Fx_rate/1000000+SUMIFS('Cash Balance'!$T$4:$T$920,'Cash Balance'!$W$4:$W$920,Summary!D$32,'Cash Balance'!$Y$4:$Y$920,Summary!$A49)/1000000 -> 3.1388068 | E49: =SUM(B49:D49) -> 3.1388068 | F49: =E49/$E$63 -> 0.019357883
A50: BIDV - LONG BIEN | B50: =SUMIFS('Cash Balance'!$L$4:$L$920,'Cash Balance'!$W$4:$W$920,Summary!B$32,'Cash Balance'!$Y$4:$Y$920,Summary!$A50)/Fx_rate/1000000+SUMIFS('Cash Balance'!$T$4:$T$920,'Cash Balance'!$W$4:$W$920,Summary!B$32,'Cash Balance'!$Y$4:$Y$920,Summary!$A50)/1000000 -> 0 | C50: =SUMIFS('Cash Balance'!$L$4:$L$920,'Cash Balance'!$W$4:$W$920,Summary!C$32,'Cash Balance'!$Y$4:$Y$920,Summary!$A50)/Fx_rate/1000000+SUMIFS('Cash Balance'!$T$4:$T$920,'Cash Balance'!$W$4:$W$920,Summary!C$32,'Cash Balance'!$Y$4:$Y$920,Summary!$A50)/1000000 -> 0 | D50: =SUMIFS('Cash Balance'!$L$4:$L$920,'Cash Balance'!$W$4:$W$920,Summary!D$32,'Cash Balance'!$Y$4:$Y$920,Summary!$A50)/Fx_rate/1000000+SUMIFS('Cash Balance'!$T$4:$T$920,'Cash Balance'!$W$4:$W$920,Summary!D$32,'Cash Balance'!$Y$4:$Y$920,Summary!$A50)/1000000 -> 0.0040238321 | E50: =SUM(B50:D50) -> 0.0040238321 | F50: =E50/$E$63 -> 2.4816078e-05
A51: BIDV - GIA DINH | B51: =SUMIFS('Cash Balance'!$L$4:$L$920,'Cash Balance'!$W$4:$W$920,Summary!B$32,'Cash Balance'!$Y$4:$Y$920,Summary!$A51)/Fx_rate/1000000+SUMIFS('Cash Balance'!$T$4:$T$920,'Cash Balance'!$W$4:$W$920,Summary!B$32,'Cash Balance'!$Y$4:$Y$920,Summary!$A51)/1000000 -> 0 | C51: =SUMIFS('Cash Balance'!$L$4:$L$920,'Cash Balance'!$W$4:$W$920,Summary!C$32,'Cash Balance'!$Y$4:$Y$920,Summary!$A51)/Fx_rate/1000000+SUMIFS('Cash Balance'!$T$4:$T$920,'Cash Balance'!$W$4:$W$920,Summary!C$32,'Cash Balance'!$Y$4:$Y$920,Summary!$A51)/1000000 -> 0 | D51: =SUMIFS('Cash Balance'!$L$4:$L$920,'Cash Balance'!$W$4:$W$920,Summary!D$32,'Cash Balance'!$Y$4:$Y$920,Summary!$A51)/Fx_rate/1000000+SUMIFS('Cash Balance'!$T$4:$T$920,'Cash Balance'!$W$4:$W$920,Summary!D$32,'Cash Balance'!$Y$4:$Y$920,Summary!$A51)/1000000 -> 0 | E51: =SUM(B51:D51) -> 0 | F51: =E51/$E$63 -> 0
A52: OCB | B52: =SUMIFS(Table11[CLOSING BALANCE (VND)2],Table11[NAME],Summary!B$32,Table11[Bank_1],Summary!$A52)/Fx_rate/1000000+SUMIFS(Table11[CLOSING BALANCE (USD)],Table11[NAME],Summary!B$32,Table11[Bank_1],Summary!$A52)/1000000 -> 0.0028100769 | C52: =SUMIFS(Table11[CLOSING BALANCE (VND)2],Table11[NAME],Summary!C$32,Table11[Bank_1],Summary!$A52)/Fx_rate/1000000+SUMIFS(Table11[CLOSING BALANCE (USD)],Table11[NAME],Summary!C$32,Table11[Bank_1],Summary!$A52)/1000000 -> 0.0022579054 | D52: =SUMIFS(Table11[CLOSING BALANCE (VND)2],Table11[NAME],Summary!D$32,Table11[Bank_1],Summary!$A52)/Fx_rate/1000000+SUMIFS(Table11[CLOSING BALANCE (USD)],Table11[NAME],Summary!D$32,Table11[Bank_1],Summary!$A52)/1000000 -> 0.018052283 | E52: =SUM(B52:D52) -> 0.023120266 | F52: =E52/$E$63 -> 0.00014258903
A53: MBB | B53: =SUMIFS(Table11[CLOSING BALANCE (VND)2],Table11[NAME],Summary!B$32,Table11[Bank_1],Summary!$A53)/Fx_rate/1000000+SUMIFS(Table11[CLOSING BALANCE (USD)],Table11[NAME],Summary!B$32,Table11[Bank_1],Summary!$A53)/1000000 -> 0 | C53: =SUMIFS(Table11[CLOSING BALANCE (VND)2],Table11[NAME],Summary!C$32,Table11[Bank_1],Summary!$A53)/Fx_rate/1000000+SUMIFS(Table11[CLOSING BALANCE (USD)],Table11[NAME],Summary!C$32,Table11[Bank_1],Summary!$A53)/1000000 -> 0.00039404218 | D53: =SUMIFS(Table11[CLOSING BALANCE (VND)2],Table11[NAME],Summary!D$32,Table11[Bank_1],Summary!$A53)/Fx_rate/1000000+SUMIFS(Table11[CLOSING BALANCE (USD)],Table11[NAME],Summary!D$32,Table11[Bank_1],Summary!$A53)/1000000 -> 0 | E53: =SUM(B53:D53) -> 0.00039404218 | F53: =E53/$E$63 -> 2.4301663e-06
A54: VIB | B54: =SUMIFS(Table11[CLOSING BALANCE (VND)2],Table11[NAME],Summary!B$32,Table11[Bank_1],Summary!$A54)/Fx_rate/1000000+SUMIFS(Table11[CLOSING BALANCE (USD)],Table11[NAME],Summary!B$32,Table11[Bank_1],Summary!$A54)/1000000 -> 0.00057396512 | C54: =SUMIFS(Table11[CLOSING BALANCE (VND)2],Table11[NAME],Summary!C$32,Table11[Bank_1],Summary!$A54)/Fx_rate/1000000+SUMIFS(Table11[CLOSING BALANCE (USD)],Table11[NAME],Summary!C$32,Table11[Bank_1],Summary!$A54)/1000000 -> 6.5020148 | D54: =SUMIFS(Table11[CLOSING BALANCE (VND)2],Table11[NAME],Summary!D$32,Table11[Bank_1],Summary!$A54)/Fx_rate/1000000+SUMIFS(Table11[CLOSING BALANCE (USD)],Table11[NAME],Summary!D$32,Table11[Bank_1],Summary!$A54)/1000000 -> 0.16024829 | E54: =SUM(B54:D54) -> 6.662837 | F54: =E54/$E$63 -> 0.041091545
A55: DB - Singapore | B55: =SUMIFS(Table11[CLOSING BALANCE (VND)2],Table11[NAME],Summary!B$32,Table11[BRANCH],Summary!$A55)/Fx_rate/1000000+SUMIFS(Table11[CLOSING BALANCE (USD)],Table11[NAME],Summary!B$32,Table11[BRANCH],Summary!$A55)/1000000 -> 0 | C55: =SUMIFS(Table11[CLOSING BALANCE (VND)2],Table11[NAME],Summary!C$32,Table11[BRANCH],Summary!$A55)/Fx_rate/1000000+SUMIFS(Table11[CLOSING BALANCE (USD)],Table11[NAME],Summary!C$32,Table11[BRANCH],Summary!$A55)/1000000 -> 0 | D55: =SUMIFS(Table11[CLOSING BALANCE (VND)2],Table11[NAME],Summary!D$32,Table11[BRANCH],Summary!$A55)/Fx_rate/1000000+SUMIFS(Table11[CLOSING BALANCE (USD)],Table11[NAME],Summary!D$32,Table11[BRANCH],Summary!$A55)/1000000 -> 0 | E55: =SUM(B55:D55) -> 0 | F55: =E55/$E$63 -> 0
A56: SNP | B56: =SUMIFS(Table11[CLOSING BALANCE (VND)2],Table11[NAME],Summary!B$32,Table11[Bank_1],Summary!$A56)/Fx_rate/1000000+SUMIFS(Table11[CLOSING BALANCE (USD)],Table11[NAME],Summary!B$32,Table11[Bank_1],Summary!$A56)/1000000 -> 1.1826887 | C56: =SUMIFS(Table11[CLOSING BALANCE (VND)2],Table11[NAME],Summary!C$32,Table11[Bank_1],Summary!$A56)/Fx_rate/1000000+SUMIFS(Table11[CLOSING BALANCE (USD)],Table11[NAME],Summary!C$32,Table11[Bank_1],Summary!$A56)/1000000 -> 1.5310342 | D56: =SUMIFS(Table11[CLOSING BALANCE (VND)2],Table11[NAME],Summary!D$32,Table11[Bank_1],Summary!$A56)/Fx_rate/1000000+SUMIFS(Table11[CLOSING BALANCE (USD)],Table11[NAME],Summary!D$32,Table11[Bank_1],Summary!$A56)/1000000 -> 2.6407256 | E56: =SUM(B56:D56) -> 5.3544485 | F56: =E56/$E$63 -> 0.033022354
A57: TCB | B57: =SUMIFS(Table11[CLOSING BALANCE (VND)2],Table11[NAME],Summary!B$32,Table11[Bank_1],Summary!$A57)/Fx_rate/1000000+SUMIFS(Table11[CLOSING BALANCE (USD)],Table11[NAME],Summary!B$32,Table11[Bank_1],Summary!$A57)/1000000 -> 5.2225864e-05 | C57: =SUMIFS(Table11[CLOSING BALANCE (VND)2],Table11[NAME],Summary!C$32,Table11[Bank_1],Summary!$A57)/Fx_rate/1000000+SUMIFS(Table11[CLOSING BALANCE (USD)],Table11[NAME],Summary!C$32,Table11[Bank_1],Summary!$A57)/1000000 -> 0.059635535 | D57: =SUMIFS(Table11[CLOSING BALANCE (VND)2],Table11[NAME],Summary!D$32,Table11[Bank_1],Summary!$A57)/Fx_rate/1000000+SUMIFS(Table11[CLOSING BALANCE (USD)],Table11[NAME],Summary!D$32,Table11[Bank_1],Summary!$A57)/1000000 -> 1.2941962 | E57: =SUM(B57:D57) -> 1.353884 | F57: =E57/$E$63 -> 0.0083497744
A58: ACB | B58: =SUMIFS(Table11[CLOSING BALANCE (VND)2],Table11[NAME],Summary!B$32,Table11[Bank_1],Summary!$A58)/Fx_rate/1000000+SUMIFS(Table11[CLOSING BALANCE (USD)],Table11[NAME],Summary!B$32,Table11[Bank_1],Summary!$A58)/1000000 -> 0.002648365 | C58: =SUMIFS(Table11[CLOSING BALANCE (VND)2],Table11[NAME],Summary!C$32,Table11[Bank_1],Summary!$A58)/Fx_rate/1000000+SUMIFS(Table11[CLOSING BALANCE (USD)],Table11[NAME],Summary!C$32,Table11[Bank_1],Summary!$A58)/1000000 -> 0.0096837425 | D58: =SUMIFS(Table11[CLOSING BALANCE (VND)2],Table11[NAME],Summary!D$32,Table11[Bank_1],Summary!$A58)/Fx_rate/1000000+SUMIFS(Table11[CLOSING BALANCE (USD)],Table11[NAME],Summary!D$32,Table11[Bank_1],Summary!$A58)/1000000 -> 0.0042042962 | E58: =SUM(B58:D58) -> 0.016536404 | F58: =E58/$E$63 -> 0.00010198454
A59: STANDARD CHARTERED | B59: =SUMIFS(Table11[CLOSING BALANCE (VND)2],Table11[NAME],Summary!B$32,Table11[Bank_1],Summary!$A59)/Fx_rate/1000000+SUMIFS(Table11[CLOSING BALANCE (USD)],Table11[NAME],Summary!B$32,Table11[Bank_1],Summary!$A59)/1000000 -> 0 | C59: =SUMIFS(Table11[CLOSING BALANCE (VND)2],Table11[NAME],Summary!C$32,Table11[Bank_1],Summary!$A59)/Fx_rate/1000000+SUMIFS(Table11[CLOSING BALANCE (USD)],Table11[NAME],Summary!C$32,Table11[Bank_1],Summary!$A59)/1000000 -> 0 | D59: =SUMIFS(Table11[CLOSING BALANCE (VND)2],Table11[NAME],Summary!D$32,Table11[Bank_1],Summary!$A59)/Fx_rate/1000000+SUMIFS(Table11[CLOSING BALANCE (USD)],Table11[NAME],Summary!D$32,Table11[Bank_1],Summary!$A59)/1000000 -> 0.056006643 | E59: =SUM(B59:D59) -> 0.056006643 | F59: =E59/$E$63 -> 0.00034540834
A60: UOB | B60: =SUMIFS(Table11[CLOSING BALANCE (VND)2],Table11[NAME],Summary!B$32,Table11[Bank_1],Summary!$A60)/Fx_rate/1000000+SUMIFS(Table11[CLOSING BALANCE (USD)],Table11[NAME],Summary!B$32,Table11[Bank_1],Summary!$A60)/1000000 -> 0.0036749453 | C60: =SUMIFS(Table11[CLOSING BALANCE (VND)2],Table11[NAME],Summary!C$32,Table11[Bank_1],Summary!$A60)/Fx_rate/1000000+SUMIFS(Table11[CLOSING BALANCE (USD)],Table11[NAME],Summary!C$32,Table11[Bank_1],Summary!$A60)/1000000 -> 0.51377891 | D60: =SUMIFS(Table11[CLOSING BALANCE (VND)2],Table11[NAME],Summary!D$32,Table11[Bank_1],Summary!$A60)/Fx_rate/1000000+SUMIFS(Table11[CLOSING BALANCE (USD)],Table11[NAME],Summary!D$32,Table11[Bank_1],Summary!$A60)/1000000 -> 0.00094395973 | E60: =SUM(B60:D60) -> 0.51839782 | F60: =E60/$E$63 -> 0.0031971017
A61: KEB Hana | B61: =SUMIFS(Table11[CLOSING BALANCE (VND)2],Table11[NAME],Summary!B$32,Table11[Bank_1],Summary!$A61)/Fx_rate/1000000+SUMIFS(Table11[CLOSING BALANCE (USD)],Table11[NAME],Summary!B$32,Table11[Bank_1],Summary!$A61)/1000000 -> 0 | C61: =SUMIFS(Table11[CLOSING BALANCE (VND)2],Table11[NAME],Summary!C$32,Table11[Bank_1],Summary!$A61)/Fx_rate/1000000+SUMIFS(Table11[CLOSING BALANCE (USD)],Table11[NAME],Summary!C$32,Table11[Bank_1],Summary!$A61)/1000000 -> 0 | D61: =SUMIFS(Table11[CLOSING BALANCE (VND)2],Table11[NAME],Summary!D$32,Table11[Bank_1],Summary!$A61)/Fx_rate/1000000+SUMIFS(Table11[CLOSING BALANCE (USD)],Table11[NAME],Summary!D$32,Table11[Bank_1],Summary!$A61)/1000000 -> 1.9621477 | E61: =SUM(B61:D61) -> 1.9621477 | F61: =E61/$E$63 -> 0.012101104
A62: OTHERS | B62: =SUMIFS(Table11[CLOSING BALANCE (VND)2],Table11[NAME],Summary!B$32,Table11[Bank_1],Summary!$A62)/Fx_rate/1000000+SUMIFS(Table11[CLOSING BALANCE (USD)],Table11[NAME],Summary!B$32,Table11[Bank_1],Summary!$A62)/1000000-B55 -> 0.0068840332 | C62: =SUMIFS(Table11[CLOSING BALANCE (VND)2],Table11[NAME],Summary!C$32,Table11[Bank_1],Summary!$A62)/Fx_rate/1000000+SUMIFS(Table11[CLOSING BALANCE (USD)],Table11[NAME],Summary!C$32,Table11[Bank_1],Summary!$A62)/1000000-C55 -> 0.024731517 | D62: =SUMIFS(Table11[CLOSING BALANCE (VND)2],Table11[NAME],Summary!D$32,Table11[Bank_1],Summary!$A62)/Fx_rate/1000000+SUMIFS(Table11[CLOSING BALANCE (USD)],Table11[NAME],Summary!D$32,Table11[Bank_1],Summary!$A62)/1000000-D55 -> 8.4018801 | E62: =SUM(B62:D62) -> 8.4334957 | F62: =E62/$E$63 -> 0.052011683
A63: TOTAL | B63: =SUBTOTAL(9,B34:B62) -> 1.504151 | C63: =SUBTOTAL(9,C34:C62) -> 71.648699 | D63: =SUBTOTAL(9,D34:D62) -> 88.993328 | E63: =SUBTOTAL(9,E34:E62) -> 162.14618 | F63: =E63/$E$63 -> 1
B64: =ROUND(B63*1000000,0)=ROUND(D15*1000000,0) -> TRUE | C64: =C63=D16 -> TRUE | D64: =ROUND(D63*1000000,0)=ROUND(D17*1000000,0) -> TRUE | E64: =ROUND(E63*1000000,0)=ROUND(D18*1000000,0) -> TRUE
D65: =ROUND(D63*1000000,0)-ROUND(D17*1000000,0) -> 0
A70: 2. Cash movement
A72: ="In "&$B$4&", BWID Group received total of US"&TEXT($E$79,"$#,##0.00")&"mn, in which, rental income is US"&TEXT($E$80,"$#,##0.00")&"mn. " -> In W1-2Jan26, BWID Group received total of US$12,67167mn, in which, rental income is US$12,48612mn.
A73: ="Total cash payment is US"&TEXT(-E95,"$#,##0.00")&"mn, in which, payment for deal is US"&TEXT(-E97,"$#,##0.00")&"mn, payment for operating expense is US"&TEXT(-E99,"$#,##0.00")&"mn, payment for Land acquisition and Construction is US"&TEXT(-E96-E98,"$#,##0.00")&"mn, and loan's principle and interest payment is "&TEXT(-E100-E101,"$#,##0.00")&"mn." -> Total cash payment is US$7,96918mn, in which, payment for deal is US$,000mn, payment for operating expense is US$3,08299mn, payment for Land acquisition and Construction is US$4,81359mn, and loan's principle and interest payment is $,07261mn.
B75: BWID JSC | C75: VC3 | D75: Subsidiaries | E75: Total
B76: In $Usmn | C76: In $Usmn | D76: In $Usmn | E76: In $Usmn
A77: B.O.P | B77: =SUMIFS('Cash Balance'!$H$4:$H$920,'Cash Balance'!$W$4:$W$920,B$75,'Cash Balance'!$E$4:$E$920,"VND")/1000000/Fx_rate+SUMIFS('Cash Balance'!$Q$4:$Q$920,'Cash Balance'!$W$4:$W$920,B$75,'Cash Balance'!$E$4:$E$920,"USD")/1000000 -> 1.5379006 | C77: =SUMIFS('Cash Balance'!$H$4:$H$920,'Cash Balance'!$W$4:$W$920,C$75,'Cash Balance'!$E$4:$E$920,"VND")/1000000/Fx_rate+SUMIFS('Cash Balance'!$Q$4:$Q$920,'Cash Balance'!$W$4:$W$920,C$75,'Cash Balance'!$E$4:$E$920,"USD")/1000000 -> 53.111909 | D77: =SUMIFS('Cash Balance'!$H$4:$H$920,'Cash Balance'!$W$4:$W$920,D$75,'Cash Balance'!$E$4:$E$920,"VND")/1000000/Fx_rate+SUMIFS('Cash Balance'!$Q$4:$Q$920,'Cash Balance'!$W$4:$W$920,D$75,'Cash Balance'!$E$4:$E$920,"USD")/1000000 -> 79.87124 | E77: =SUM(B77:D77) -> 134.52105
A78: Total cash-in | B78: =SUBTOTAL(9,B79:B93) -> 2.3013678 | C78: =SUBTOTAL(9,C79:C93) -> 52.043071 | D78: =SUBTOTAL(9,D79:D93) -> 18.406773 | E78: =SUM(B78:D78) -> 72.751212
A79: Ordinary receipt | B79: =SUBTOTAL(9,B80:B88) -> 0.0091042269 | C79: =SUBTOTAL(9,C80:C88) -> 0.2487225 | D79: =SUBTOTAL(9,D80:D88) -> 12.413848 | E79: =SUM(B79:D79) -> 12.671675
A80: Receipt from tenants | B80: =SUMIFS(Movement!$F$4:$F$2137,Movement!$K$4:$K$2137,Summary!B$75,Movement!$L$4:$L$2137,Summary!$A80,Movement!$M$4:$M$2137,"VND")/1000000/Fx_rate+SUMIFS(Movement!$F$4:$F$2137,Movement!$K$4:$K$2137,Summary!B$75,Movement!$L$4:$L$2137,Summary!$A80,Movement!$M$4:$M$2137,"USD")/1000000 -> 0 | C80: =SUMIFS(Movement!$F$4:$F$2137,Movement!$K$4:$K$2137,Summary!C$75,Movement!$L$4:$L$2137,Summary!$A80,Movement!$M$4:$M$2137,"VND")/1000000/Fx_rate+SUMIFS(Movement!$F$4:$F$2137,Movement!$K$4:$K$2137,Summary!C$75,Movement!$L$4:$L$2137,Summary!$A80,Movement!$M$4:$M$2137,"USD")/1000000 -> 0.23338632 | D80: =SUMIFS(Movement!$F$4:$F$2137,Movement!$K$4:$K$2137,Summary!D$75,Movement!$L$4:$L$2137,Summary!$A80,Movement!$M$4:$M$2137,"VND")/1000000/Fx_rate+SUMIFS(Movement!$F$4:$F$2137,Movement!$K$4:$K$2137,Summary!D$75,Movement!$L$4:$L$2137,Summary!$A80,Movement!$M$4:$M$2137,"USD")/1000000 -> 12.252736 | E80: =SUM(B80:D80) -> 12.486122
A81: Refund land/deal deposit payment | B81: =SUMIFS(Movement!$F$4:$F$2137,Movement!$K$4:$K$2137,Summary!B$75,Movement!$L$4:$L$2137,Summary!$A81,Movement!$M$4:$M$2137,"VND")/1000000/Fx_rate+SUMIFS(Movement!$F$4:$F$2137,Movement!$K$4:$K$2137,Summary!B$75,Movement!$L$4:$L$2137,Summary!$A81,Movement!$M$4:$M$2137,"USD")/1000000 -> 0 | C81: =SUMIFS(Movement!$F$4:$F$2137,Movement!$K$4:$K$2137,Summary!C$75,Movement!$L$4:$L$2137,Summary!$A81,Movement!$M$4:$M$2137,"VND")/1000000/Fx_rate+SUMIFS(Movement!$F$4:$F$2137,Movement!$K$4:$K$2137,Summary!C$75,Movement!$L$4:$L$2137,Summary!$A81,Movement!$M$4:$M$2137,"USD")/1000000 -> 0 | D81: =SUMIFS(Movement!$F$4:$F$2137,Movement!$K$4:$K$2137,Summary!D$75,Movement!$L$4:$L$2137,Summary!$A81,Movement!$M$4:$M$2137,"VND")/1000000/Fx_rate+SUMIFS(Movement!$F$4:$F$2137,Movement!$K$4:$K$2137,Summary!D$75,Movement!$L$4:$L$2137,Summary!$A81,Movement!$M$4:$M$2137,"USD")/1000000 -> 0 | E81: =SUM(B81:D81) -> 0
A82: Refinancing | B82: =SUMIFS(Movement!$F$4:$F$2137,Movement!$K$4:$K$2137,Summary!B$75,Movement!$L$4:$L$2137,Summary!$A82,Movement!$M$4:$M$2137,"VND")/1000000/Fx_rate+SUMIFS(Movement!$F$4:$F$2137,Movement!$K$4:$K$2137,Summary!B$75,Movement!$L$4:$L$2137,Summary!$A82,Movement!$M$4:$M$2137,"USD")/1000000 -> 0 | C82: =SUMIFS(Movement!$F$4:$F$2137,Movement!$K$4:$K$2137,Summary!C$75,Movement!$L$4:$L$2137,Summary!$A82,Movement!$M$4:$M$2137,"VND")/1000000/Fx_rate+SUMIFS(Movement!$F$4:$F$2137,Movement!$K$4:$K$2137,Summary!C$75,Movement!$L$4:$L$2137,Summary!$A82,Movement!$M$4:$M$2137,"USD")/1000000 -> 0 | D82: =SUMIFS(Movement!$F$4:$F$2137,Movement!$K$4:$K$2137,Summary!D$75,Movement!$L$4:$L$2137,Summary!$A82,Movement!$M$4:$M$2137,"VND")/1000000/Fx_rate+SUMIFS(Movement!$F$4:$F$2137,Movement!$K$4:$K$2137,Summary!D$75,Movement!$L$4:$L$2137,Summary!$A82,Movement!$M$4:$M$2137,"USD")/1000000 -> 0 | E82: =SUM(B82:D82) -> 0
A83: Loan drawdown | B83: =SUMIFS(Movement!$F$4:$F$2137,Movement!$K$4:$K$2137,Summary!B$75,Movement!$L$4:$L$2137,Summary!$A83,Movement!$M$4:$M$2137,"VND")/1000000/Fx_rate+SUMIFS(Movement!$F$4:$F$2137,Movement!$K$4:$K$2137,Summary!B$75,Movement!$L$4:$L$2137,Summary!$A83,Movement!$M$4:$M$2137,"USD")/1000000 -> 0 | C83: =SUMIFS(Movement!$F$4:$F$2137,Movement!$K$4:$K$2137,Summary!C$75,Movement!$L$4:$L$2137,Summary!$A83,Movement!$M$4:$M$2137,"VND")/1000000/Fx_rate+SUMIFS(Movement!$F$4:$F$2137,Movement!$K$4:$K$2137,Summary!C$75,Movement!$L$4:$L$2137,Summary!$A83,Movement!$M$4:$M$2137,"USD")/1000000 -> 0 | D83: =SUMIFS(Movement!$F$4:$F$2137,Movement!$K$4:$K$2137,Summary!D$75,Movement!$L$4:$L$2137,Summary!$A83,Movement!$M$4:$M$2137,"VND")/1000000/Fx_rate+SUMIFS(Movement!$F$4:$F$2137,Movement!$K$4:$K$2137,Summary!D$75,Movement!$L$4:$L$2137,Summary!$A83,Movement!$M$4:$M$2137,"USD")/1000000 -> 0 | E83: =SUM(B83:D83) -> 0
A84: VAT refund | B84: =SUMIFS(Movement!$F$4:$F$2137,Movement!$K$4:$K$2137,Summary!B$75,Movement!$L$4:$L$2137,Summary!$A84,Movement!$M$4:$M$2137,"VND")/1000000/Fx_rate+SUMIFS(Movement!$F$4:$F$2137,Movement!$K$4:$K$2137,Summary!B$75,Movement!$L$4:$L$2137,Summary!$A84,Movement!$M$4:$M$2137,"USD")/1000000 -> 0 | C84: =SUMIFS(Movement!$F$4:$F$2137,Movement!$K$4:$K$2137,Summary!C$75,Movement!$L$4:$L$2137,Summary!$A84,Movement!$M$4:$M$2137,"VND")/1000000/Fx_rate+SUMIFS(Movement!$F$4:$F$2137,Movement!$K$4:$K$2137,Summary!C$75,Movement!$L$4:$L$2137,Summary!$A84,Movement!$M$4:$M$2137,"USD")/1000000 -> 0 | D84: =SUMIFS(Movement!$F$4:$F$2137,Movement!$K$4:$K$2137,Summary!D$75,Movement!$L$4:$L$2137,Summary!$A84,Movement!$M$4:$M$2137,"VND")/1000000/Fx_rate+SUMIFS(Movement!$F$4:$F$2137,Movement!$K$4:$K$2137,Summary!D$75,Movement!$L$4:$L$2137,Summary!$A84,Movement!$M$4:$M$2137,"USD")/1000000 -> 0 | E84: =SUM(B84:D84) -> 0
A85: Corporate Loan drawdown | B85: =SUMIFS(Movement!$F$4:$F$2137,Movement!$K$4:$K$2137,Summary!B$75,Movement!$L$4:$L$2137,Summary!$A85,Movement!$M$4:$M$2137,"VND")/1000000/Fx_rate+SUMIFS(Movement!$F$4:$F$2137,Movement!$K$4:$K$2137,Summary!B$75,Movement!$L$4:$L$2137,Summary!$A85,Movement!$M$4:$M$2137,"USD")/1000000 -> 0 | C85: =SUMIFS(Movement!$F$4:$F$2137,Movement!$K$4:$K$2137,Summary!C$75,Movement!$L$4:$L$2137,Summary!$A85,Movement!$M$4:$M$2137,"VND")/1000000/Fx_rate+SUMIFS(Movement!$F$4:$F$2137,Movement!$K$4:$K$2137,Summary!C$75,Movement!$L$4:$L$2137,Summary!$A85,Movement!$M$4:$M$2137,"USD")/1000000 -> 0 | D85: =SUMIFS(Movement!$F$4:$F$2137,Movement!$K$4:$K$2137,Summary!D$75,Movement!$L$4:$L$2137,Summary!$A85,Movement!$M$4:$M$2137,"VND")/1000000/Fx_rate+SUMIFS(Movement!$F$4:$F$2137,Movement!$K$4:$K$2137,Summary!D$75,Movement!$L$4:$L$2137,Summary!$A85,Movement!$M$4:$M$2137,"USD")/1000000 -> 0 | E85: =SUM(B85:D85) -> 0
A86: Loan receipts | B86: =SUMIFS(Movement!$F$4:$F$2137,Movement!$K$4:$K$2137,Summary!B$75,Movement!$L$4:$L$2137,Summary!$A86,Movement!$M$4:$M$2137,"VND")/1000000/Fx_rate+SUMIFS(Movement!$F$4:$F$2137,Movement!$K$4:$K$2137,Summary!B$75,Movement!$L$4:$L$2137,Summary!$A86,Movement!$M$4:$M$2137,"USD")/1000000 -> 0 | C86: =SUMIFS(Movement!$F$4:$F$2137,Movement!$K$4:$K$2137,Summary!C$75,Movement!$L$4:$L$2137,Summary!$A86,Movement!$M$4:$M$2137,"VND")/1000000/Fx_rate+SUMIFS(Movement!$F$4:$F$2137,Movement!$K$4:$K$2137,Summary!C$75,Movement!$L$4:$L$2137,Summary!$A86,Movement!$M$4:$M$2137,"USD")/1000000 -> 0 | D86: =SUMIFS(Movement!$F$4:$F$2137,Movement!$K$4:$K$2137,Summary!D$75,Movement!$L$4:$L$2137,Summary!$A86,Movement!$M$4:$M$2137,"VND")/1000000/Fx_rate+SUMIFS(Movement!$F$4:$F$2137,Movement!$K$4:$K$2137,Summary!D$75,Movement!$L$4:$L$2137,Summary!$A86,Movement!$M$4:$M$2137,"USD")/1000000 -> 0 | E86: =SUM(B86:D86) -> 0
A87: Contribution | B87: =SUMIFS(Movement!$F$4:$F$2137,Movement!$K$4:$K$2137,Summary!B$75,Movement!$L$4:$L$2137,Summary!$A87,Movement!$M$4:$M$2137,"VND")/1000000/Fx_rate+SUMIFS(Movement!$F$4:$F$2137,Movement!$K$4:$K$2137,Summary!B$75,Movement!$L$4:$L$2137,Summary!$A87,Movement!$M$4:$M$2137,"USD")/1000000 -> 0 | C87: =SUMIFS(Movement!$F$4:$F$2137,Movement!$K$4:$K$2137,Summary!C$75,Movement!$L$4:$L$2137,Summary!$A87,Movement!$M$4:$M$2137,"VND")/1000000/Fx_rate+SUMIFS(Movement!$F$4:$F$2137,Movement!$K$4:$K$2137,Summary!C$75,Movement!$L$4:$L$2137,Summary!$A87,Movement!$M$4:$M$2137,"USD")/1000000 -> 0 | D87: =SUMIFS(Movement!$F$4:$F$2137,Movement!$K$4:$K$2137,Summary!D$75,Movement!$L$4:$L$2137,Summary!$A87,Movement!$M$4:$M$2137,"VND")/1000000/Fx_rate+SUMIFS(Movement!$F$4:$F$2137,Movement!$K$4:$K$2137,Summary!D$75,Movement!$L$4:$L$2137,Summary!$A87,Movement!$M$4:$M$2137,"USD")/1000000 -> 0 | E87: =SUM(B87:D87) -> 0
A88: Other receipts | B88: =SUMIFS(Movement!$F$4:$F$2137,Movement!$K$4:$K$2137,Summary!B$75,Movement!$L$4:$L$2137,Summary!$A88,Movement!$M$4:$M$2137,"VND")/1000000/Fx_rate+SUMIFS(Movement!$F$4:$F$2137,Movement!$K$4:$K$2137,Summary!B$75,Movement!$L$4:$L$2137,Summary!$A88,Movement!$M$4:$M$2137,"USD")/1000000 -> 0.0091042269 | C88: =SUMIFS(Movement!$F$4:$F$2137,Movement!$K$4:$K$2137,Summary!C$75,Movement!$L$4:$L$2137,Summary!$A88,Movement!$M$4:$M$2137,"VND")/1000000/Fx_rate+SUMIFS(Movement!$F$4:$F$2137,Movement!$K$4:$K$2137,Summary!C$75,Movement!$L$4:$L$2137,Summary!$A88,Movement!$M$4:$M$2137,"USD")/1000000 -> 0.015336186 | D88: =SUMIFS(Movement!$F$4:$F$2137,Movement!$K$4:$K$2137,Summary!D$75,Movement!$L$4:$L$2137,Summary!$A88,Movement!$M$4:$M$2137,"VND")/1000000/Fx_rate+SUMIFS(Movement!$F$4:$F$2137,Movement!$K$4:$K$2137,Summary!D$75,Movement!$L$4:$L$2137,Summary!$A88,Movement!$M$4:$M$2137,"USD")/1000000 -> 0.16111207 | E88: =SUM(B88:D88) -> 0.18555249
A89: Internal transactions | B89: =SUBTOTAL(9,B90:B93) -> 2.2922636 | C89: =SUBTOTAL(9,C90:C93) -> 51.794349 | D89: =SUBTOTAL(9,D90:D93) -> 5.9929246 | E89: =SUM(B89:D89) -> 60.079537
A90: Internal transfer in | B90: =SUMIFS(Movement!$F$4:$F$2235,Movement!$K$4:$K$2235,Summary!B$75,Movement!$L$4:$L$2235,Summary!$A90,Movement!$M$4:$M$2235,"VND")/1000000/Fx_rate+SUMIFS(Movement!$F$4:$F$2235,Movement!$K$4:$K$2235,Summary!B$75,Movement!$L$4:$L$2235,Summary!$A90,Movement!$M$4:$M$2235,"USD")/1000000 -> 2.2922636 | C90: =SUMIFS(Movement!$F$4:$F$2137,Movement!$K$4:$K$2137,Summary!C$75,Movement!$L$4:$L$2137,Summary!$A90,Movement!$M$4:$M$2137,"VND")/1000000/Fx_rate+SUMIFS(Movement!$F$4:$F$2137,Movement!$K$4:$K$2137,Summary!C$75,Movement!$L$4:$L$2137,Summary!$A90,Movement!$M$4:$M$2137,"USD")/1000000 -> 51.794349 | D90: =SUMIFS(Movement!$F$4:$F$2137,Movement!$K$4:$K$2137,Summary!D$75,Movement!$L$4:$L$2137,Summary!$A90,Movement!$M$4:$M$2137,"VND")/1000000/Fx_rate+SUMIFS(Movement!$F$4:$F$2137,Movement!$K$4:$K$2137,Summary!D$75,Movement!$L$4:$L$2137,Summary!$A90,Movement!$M$4:$M$2137,"USD")/1000000 -> 5.9929246 | E90: =SUM(B90:D90) -> 60.079537
A91: Internal contribution in | B91: =SUMIFS(Movement!$F$4:$F$1230,Movement!$K$4:$K$1230,Summary!B$75,Movement!$L$4:$L$1230,Summary!$A91,Movement!$M$4:$M$1230,"VND")/1000000/Fx_rate+SUMIFS(Movement!$F$4:$F$1230,Movement!$K$4:$K$1230,Summary!B$75,Movement!$L$4:$L$1230,Summary!$A91,Movement!$M$4:$M$1230,"USD")/1000000 -> 0 | C91: =SUMIFS(Movement!$F$4:$F$2137,Movement!$K$4:$K$2137,Summary!C$75,Movement!$L$4:$L$2137,Summary!$A91,Movement!$M$4:$M$2137,"VND")/1000000/Fx_rate+SUMIFS(Movement!$F$4:$F$2137,Movement!$K$4:$K$2137,Summary!C$75,Movement!$L$4:$L$2137,Summary!$A91,Movement!$M$4:$M$2137,"USD")/1000000 -> 0 | D91: =SUMIFS(Movement!$F$4:$F$2137,Movement!$K$4:$K$2137,Summary!D$75,Movement!$L$4:$L$2137,Summary!$A91,Movement!$M$4:$M$2137,"VND")/1000000/Fx_rate+SUMIFS(Movement!$F$4:$F$2137,Movement!$K$4:$K$2137,Summary!D$75,Movement!$L$4:$L$2137,Summary!$A91,Movement!$M$4:$M$2137,"USD")/1000000 -> 0 | E91: =SUM(B91:D91) -> 0
A92: Dividend receipt (inside group) | B92: =SUMIFS(Movement!$F$4:$F$1230,Movement!$K$4:$K$1230,Summary!B$75,Movement!$L$4:$L$1230,Summary!$A92,Movement!$M$4:$M$1230,"VND")/1000000/Fx_rate+SUMIFS(Movement!$F$4:$F$1230,Movement!$K$4:$K$1230,Summary!B$75,Movement!$L$4:$L$1230,Summary!$A92,Movement!$M$4:$M$1230,"USD")/1000000 -> 0 | C92: =SUMIFS(Movement!$F$4:$F$2137,Movement!$K$4:$K$2137,Summary!C$75,Movement!$L$4:$L$2137,Summary!$A92,Movement!$M$4:$M$2137,"VND")/1000000/Fx_rate+SUMIFS(Movement!$F$4:$F$2137,Movement!$K$4:$K$2137,Summary!C$75,Movement!$L$4:$L$2137,Summary!$A92,Movement!$M$4:$M$2137,"USD")/1000000 -> 0 | D92: =SUMIFS(Movement!$F$4:$F$2137,Movement!$K$4:$K$2137,Summary!D$75,Movement!$L$4:$L$2137,Summary!$A92,Movement!$M$4:$M$2137,"VND")/1000000/Fx_rate+SUMIFS(Movement!$F$4:$F$2137,Movement!$K$4:$K$2137,Summary!D$75,Movement!$L$4:$L$2137,Summary!$A92,Movement!$M$4:$M$2137,"USD")/1000000 -> 0 | E92: =SUM(B92:D92) -> 0
A93: Cash received from acquisition | B93: =SUMIFS(Movement!$F$4:$F$1230,Movement!$K$4:$K$1230,Summary!B$75,Movement!$L$4:$L$1230,Summary!$A93,Movement!$M$4:$M$1230,"VND")/1000000/Fx_rate+SUMIFS(Movement!$F$4:$F$1230,Movement!$K$4:$K$1230,Summary!B$75,Movement!$L$4:$L$1230,Summary!$A93,Movement!$M$4:$M$1230,"USD")/1000000 -> 0 | C93: =SUMIFS(Movement!$F$4:$F$2137,Movement!$K$4:$K$2137,Summary!C$75,Movement!$L$4:$L$2137,Summary!$A93,Movement!$M$4:$M$2137,"VND")/1000000/Fx_rate+SUMIFS(Movement!$F$4:$F$2137,Movement!$K$4:$K$2137,Summary!C$75,Movement!$L$4:$L$2137,Summary!$A93,Movement!$M$4:$M$2137,"USD")/1000000 -> 0 | D93: =SUMIFS(Movement!$F$4:$F$2137,Movement!$K$4:$K$2137,Summary!D$75,Movement!$L$4:$L$2137,Summary!$A93,Movement!$M$4:$M$2137,"VND")/1000000/Fx_rate+SUMIFS(Movement!$F$4:$F$2137,Movement!$K$4:$K$2137,Summary!D$75,Movement!$L$4:$L$2137,Summary!$A93,Movement!$M$4:$M$2137,"USD")/1000000 -> 0 | E93: =SUM(B93:D93) -> 0
A94: Total cash-out | B94: =SUBTOTAL(9,B95:B106) -> -2.3351174 | C94: =SUBTOTAL(9,C95:C106) -> -33.506281 | D94: =SUBTOTAL(9,D95:D106) -> -9.2846846 | E94: =SUM(B94:D94) -> -45.126083
A95: Ordinary payment | B95: =SUBTOTAL(9,B96:B101) -> -0.042853812 | C95: =SUBTOTAL(9,C96:C101) -> -0.14358122 | D95: =SUBTOTAL(9,D96:D101) -> -7.7827467 | E95: =SUBTOTAL(9,E96:E101) -> -7.9691818
A96: Land acquisition | B96: =-SUMIFS(Movement!$G$4:$G$2137,Movement!$K$4:$K$2137,Summary!B$75,Movement!$L$4:$L$2137,Summary!$A96,Movement!$M$4:$M$2137,"VND")/1000000/Fx_rate-SUMIFS(Movement!$G$4:$G$2137,Movement!$K$4:$K$2137,Summary!B$75,Movement!$L$4:$L$2137,Summary!$A96,Movement!$M$4:$M$2137,"USD")/1000000 -> 0 | C96: =-SUMIFS(Movement!$G$4:$G$2137,Movement!$K$4:$K$2137,Summary!C$75,Movement!$L$4:$L$2137,Summary!$A96,Movement!$M$4:$M$2137,"VND")/1000000/Fx_rate-SUMIFS(Movement!$G$4:$G$2137,Movement!$K$4:$K$2137,Summary!C$75,Movement!$L$4:$L$2137,Summary!$A96,Movement!$M$4:$M$2137,"USD")/1000000 -> 0 | D96: =-SUMIFS(Movement!$G$4:$G$2137,Movement!$K$4:$K$2137,Summary!D$75,Movement!$L$4:$L$2137,Summary!$A96,Movement!$M$4:$M$2137,"VND")/1000000/Fx_rate-SUMIFS(Movement!$G$4:$G$2137,Movement!$K$4:$K$2137,Summary!D$75,Movement!$L$4:$L$2137,Summary!$A96,Movement!$M$4:$M$2137,"USD")/1000000 -> 0 | E96: =SUM(B96:D96) -> 0
A97: Deal payment | B97: =-SUMIFS(Movement!$G$4:$G$2137,Movement!$K$4:$K$2137,Summary!B$75,Movement!$L$4:$L$2137,Summary!$A97,Movement!$M$4:$M$2137,"VND")/1000000/Fx_rate-SUMIFS(Movement!$G$4:$G$2137,Movement!$K$4:$K$2137,Summary!B$75,Movement!$L$4:$L$2137,Summary!$A97,Movement!$M$4:$M$2137,"USD")/1000000 -> 0 | C97: =-SUMIFS(Movement!$G$4:$G$2137,Movement!$K$4:$K$2137,Summary!C$75,Movement!$L$4:$L$2137,Summary!$A97,Movement!$M$4:$M$2137,"VND")/1000000/Fx_rate-SUMIFS(Movement!$G$4:$G$2137,Movement!$K$4:$K$2137,Summary!C$75,Movement!$L$4:$L$2137,Summary!$A97,Movement!$M$4:$M$2137,"USD")/1000000 -> 0 | D97: =-SUMIFS(Movement!$G$4:$G$2137,Movement!$K$4:$K$2137,Summary!D$75,Movement!$L$4:$L$2137,Summary!$A97,Movement!$M$4:$M$2137,"VND")/1000000/Fx_rate-SUMIFS(Movement!$G$4:$G$2137,Movement!$K$4:$K$2137,Summary!D$75,Movement!$L$4:$L$2137,Summary!$A97,Movement!$M$4:$M$2137,"USD")/1000000 -> 0 | E97: =SUM(B97:D97) -> 0
A98: Construction expense | B98: =-SUMIFS(Movement!$G$4:$G$2137,Movement!$K$4:$K$2137,Summary!B$75,Movement!$L$4:$L$2137,Summary!$A98,Movement!$M$4:$M$2137,"VND")/1000000/Fx_rate-SUMIFS(Movement!$G$4:$G$2137,Movement!$K$4:$K$2137,Summary!B$75,Movement!$L$4:$L$2137,Summary!$A98,Movement!$M$4:$M$2137,"USD")/1000000 -> 0 | C98: =-SUMIFS(Movement!$G$4:$G$2137,Movement!$K$4:$K$2137,Summary!C$75,Movement!$L$4:$L$2137,Summary!$A98,Movement!$M$4:$M$2137,"VND")/1000000/Fx_rate-SUMIFS(Movement!$G$4:$G$2137,Movement!$K$4:$K$2137,Summary!C$75,Movement!$L$4:$L$2137,Summary!$A98,Movement!$M$4:$M$2137,"USD")/1000000 -> 0 | D98: =-SUMIFS(Movement!$G$4:$G$2137,Movement!$K$4:$K$2137,Summary!D$75,Movement!$L$4:$L$2137,Summary!$A98,Movement!$M$4:$M$2137,"VND")/1000000/Fx_rate-SUMIFS(Movement!$G$4:$G$2137,Movement!$K$4:$K$2137,Summary!D$75,Movement!$L$4:$L$2137,Summary!$A98,Movement!$M$4:$M$2137,"USD")/1000000 -> -4.8135884 | E98: =SUM(B98:D98) -> -4.8135884
A99: Operating expense | B99: =-SUMIFS(Movement!$G$4:$G$2137,Movement!$K$4:$K$2137,Summary!B$75,Movement!$L$4:$L$2137,Summary!$A99,Movement!$M$4:$M$2137,"VND")/1000000/Fx_rate-SUMIFS(Movement!$G$4:$G$2137,Movement!$K$4:$K$2137,Summary!B$75,Movement!$L$4:$L$2137,Summary!$A99,Movement!$M$4:$M$2137,"USD")/1000000 -> -0.042853812 | C99: =-SUMIFS(Movement!$G$4:$G$2137,Movement!$K$4:$K$2137,Summary!C$75,Movement!$L$4:$L$2137,Summary!$A99,Movement!$M$4:$M$2137,"VND")/1000000/Fx_rate-SUMIFS(Movement!$G$4:$G$2137,Movement!$K$4:$K$2137,Summary!C$75,Movement!$L$4:$L$2137,Summary!$A99,Movement!$M$4:$M$2137,"USD")/1000000 -> -0.14358122 | D99: =-SUMIFS(Movement!$G$4:$G$2216,Movement!$K$4:$K$2216,Summary!D$75,Movement!$L$4:$L$2216,Summary!$A99,Movement!$M$4:$M$2216,"VND")/1000000/Fx_rate-SUMIFS(Movement!$G$4:$G$2216,Movement!$K$4:$K$2216,Summary!D$75,Movement!$L$4:$L$2216,Summary!$A99,Movement!$M$4:$M$2216,"USD")/1000000 -> -2.896553 | E99: =SUM(B99:D99) -> -3.082988
A100: Loan repayment | B100: =-SUMIFS(Movement!$G$4:$G$2137,Movement!$K$4:$K$2137,Summary!B$75,Movement!$L$4:$L$2137,Summary!$A100,Movement!$M$4:$M$2137,"VND")/1000000/Fx_rate-SUMIFS(Movement!$G$4:$G$2137,Movement!$K$4:$K$2137,Summary!B$75,Movement!$L$4:$L$2137,Summary!$A100,Movement!$M$4:$M$2137,"USD")/1000000 -> 0 | C100: =-SUMIFS(Movement!$G$4:$G$2137,Movement!$K$4:$K$2137,Summary!C$75,Movement!$L$4:$L$2137,Summary!$A100,Movement!$M$4:$M$2137,"VND")/1000000/Fx_rate-SUMIFS(Movement!$G$4:$G$2137,Movement!$K$4:$K$2137,Summary!C$75,Movement!$L$4:$L$2137,Summary!$A100,Movement!$M$4:$M$2137,"USD")/1000000 -> 0 | D100: =-SUMIFS(Movement!$G$4:$G$2137,Movement!$K$4:$K$2137,Summary!D$75,Movement!$L$4:$L$2137,Summary!$A100,Movement!$M$4:$M$2137,"VND")/1000000/Fx_rate-SUMIFS(Movement!$G$4:$G$2137,Movement!$K$4:$K$2137,Summary!D$75,Movement!$L$4:$L$2137,Summary!$A100,Movement!$M$4:$M$2137,"USD")/1000000 -> -0.072605406 | E100: =SUM(B100:D100) -> -0.072605406
A101: Loan interest | B101: =-SUMIFS(Movement!$G$4:$G$2137,Movement!$K$4:$K$2137,Summary!B$75,Movement!$L$4:$L$2137,Summary!$A101,Movement!$M$4:$M$2137,"VND")/1000000/Fx_rate-SUMIFS(Movement!$G$4:$G$2137,Movement!$K$4:$K$2137,Summary!B$75,Movement!$L$4:$L$2137,Summary!$A101,Movement!$M$4:$M$2137,"USD")/1000000 -> 0 | C101: =-SUMIFS(Movement!$G$4:$G$2137,Movement!$K$4:$K$2137,Summary!C$75,Movement!$L$4:$L$2137,Summary!$A101,Movement!$M$4:$M$2137,"VND")/1000000/Fx_rate-SUMIFS(Movement!$G$4:$G$2137,Movement!$K$4:$K$2137,Summary!C$75,Movement!$L$4:$L$2137,Summary!$A101,Movement!$M$4:$M$2137,"USD")/1000000 -> 0 | D101: =-SUMIFS(Movement!$G$4:$G$2137,Movement!$K$4:$K$2137,Summary!D$75,Movement!$L$4:$L$2137,Summary!$A101,Movement!$M$4:$M$2137,"VND")/1000000/Fx_rate-SUMIFS(Movement!$G$4:$G$2137,Movement!$K$4:$K$2137,Summary!D$75,Movement!$L$4:$L$2137,Summary!$A101,Movement!$M$4:$M$2137,"USD")/1000000 -> 0 | E101: =SUM(B101:D101) -> 0
A102: Internal transactions | B102: =SUBTOTAL(9,B103:B106) -> -2.2922636 | C102: =SUBTOTAL(9,C103:C106) -> -33.362699 | D102: =SUBTOTAL(9,D103:D106) -> -1.5019379 | E102: =SUM(B102:D102) -> -37.156901
A103: Internal transfer out | B103: =-SUMIFS(Movement!$G$4:$G$2137,Movement!$K$4:$K$2137,Summary!B$75,Movement!$L$4:$L$2137,Summary!$A103,Movement!$M$4:$M$2137,"VND")/1000000/Fx_rate-SUMIFS(Movement!$G$4:$G$2137,Movement!$K$4:$K$2137,Summary!B$75,Movement!$L$4:$L$2137,Summary!$A103,Movement!$M$4:$M$2137,"USD")/1000000 -> -2.2922636 | C103: =-SUMIFS(Movement!$G$4:$G$2137,Movement!$K$4:$K$2137,Summary!C$75,Movement!$L$4:$L$2137,Summary!$A103,Movement!$M$4:$M$2137,"VND")/1000000/Fx_rate-SUMIFS(Movement!$G$4:$G$2137,Movement!$K$4:$K$2137,Summary!C$75,Movement!$L$4:$L$2137,Summary!$A103,Movement!$M$4:$M$2137,"USD")/1000000 -> -33.362699 | D103: =-SUMIFS(Movement!$G$4:$G$2137,Movement!$K$4:$K$2137,Summary!D$75,Movement!$L$4:$L$2137,Summary!$A103,Movement!$M$4:$M$2137,"VND")/1000000/Fx_rate-SUMIFS(Movement!$G$4:$G$2137,Movement!$K$4:$K$2137,Summary!D$75,Movement!$L$4:$L$2137,Summary!$A103,Movement!$M$4:$M$2137,"USD")/1000000 -> -1.5019379 | E103: =SUM(B103:D103) -> -37.156901
A104: Internal contribution out | B104: =-SUMIFS(Movement!$G$4:$G$2137,Movement!$K$4:$K$2137,Summary!B$75,Movement!$L$4:$L$2137,Summary!$A104,Movement!$M$4:$M$2137,"VND")/1000000/Fx_rate-SUMIFS(Movement!$G$4:$G$2137,Movement!$K$4:$K$2137,Summary!B$75,Movement!$L$4:$L$2137,Summary!$A104,Movement!$M$4:$M$2137,"USD")/1000000 -> 0 | C104: =-SUMIFS(Movement!$G$4:$G$2137,Movement!$K$4:$K$2137,Summary!C$75,Movement!$L$4:$L$2137,Summary!$A104,Movement!$M$4:$M$2137,"VND")/1000000/Fx_rate-SUMIFS(Movement!$G$4:$G$2137,Movement!$K$4:$K$2137,Summary!C$75,Movement!$L$4:$L$2137,Summary!$A104,Movement!$M$4:$M$2137,"USD")/1000000 -> 0 | D104: =-SUMIFS(Movement!$G$4:$G$2137,Movement!$K$4:$K$2137,Summary!D$75,Movement!$L$4:$L$2137,Summary!$A104,Movement!$M$4:$M$2137,"VND")/1000000/Fx_rate-SUMIFS(Movement!$G$4:$G$2137,Movement!$K$4:$K$2137,Summary!D$75,Movement!$L$4:$L$2137,Summary!$A104,Movement!$M$4:$M$2137,"USD")/1000000 -> 0 | E104: =SUM(B104:D104) -> 0
A105: Dividend paid (inside group) | B105: =-SUMIFS(Movement!$G$4:$G$2137,Movement!$K$4:$K$2137,Summary!B$75,Movement!$L$4:$L$2137,Summary!$A105,Movement!$M$4:$M$2137,"VND")/1000000/Fx_rate-SUMIFS(Movement!$G$4:$G$2137,Movement!$K$4:$K$2137,Summary!B$75,Movement!$L$4:$L$2137,Summary!$A105,Movement!$M$4:$M$2137,"USD")/1000000 -> 0 | C105: =-SUMIFS(Movement!$G$4:$G$2137,Movement!$K$4:$K$2137,Summary!C$75,Movement!$L$4:$L$2137,Summary!$A105,Movement!$M$4:$M$2137,"VND")/1000000/Fx_rate-SUMIFS(Movement!$G$4:$G$2137,Movement!$K$4:$K$2137,Summary!C$75,Movement!$L$4:$L$2137,Summary!$A105,Movement!$M$4:$M$2137,"USD")/1000000 -> 0 | D105: =-SUMIFS(Movement!$G$4:$G$2137,Movement!$K$4:$K$2137,Summary!D$75,Movement!$L$4:$L$2137,Summary!$A105,Movement!$M$4:$M$2137,"VND")/1000000/Fx_rate-SUMIFS(Movement!$G$4:$G$2137,Movement!$K$4:$K$2137,Summary!D$75,Movement!$L$4:$L$2137,Summary!$A105,Movement!$M$4:$M$2137,"USD")/1000000 -> 0 | E105: =SUM(B105:D105) -> 0
A106: Payment for acquisition | B106: =-SUMIFS(Movement!$G$4:$G$2137,Movement!$K$4:$K$2137,Summary!B$75,Movement!$L$4:$L$2137,Summary!$A106,Movement!$M$4:$M$2137,"VND")/1000000/Fx_rate-SUMIFS(Movement!$G$4:$G$2137,Movement!$K$4:$K$2137,Summary!B$75,Movement!$L$4:$L$2137,Summary!$A106,Movement!$M$4:$M$2137,"USD")/1000000 -> 0 | C106: =-SUMIFS(Movement!$G$4:$G$2137,Movement!$K$4:$K$2137,Summary!C$75,Movement!$L$4:$L$2137,Summary!$A106,Movement!$M$4:$M$2137,"VND")/1000000/Fx_rate-SUMIFS(Movement!$G$4:$G$2137,Movement!$K$4:$K$2137,Summary!C$75,Movement!$L$4:$L$2137,Summary!$A106,Movement!$M$4:$M$2137,"USD")/1000000 -> 0 | D106: =-SUMIFS(Movement!$G$4:$G$2137,Movement!$K$4:$K$2137,Summary!D$75,Movement!$L$4:$L$2137,Summary!$A106,Movement!$M$4:$M$2137,"VND")/1000000/Fx_rate-SUMIFS(Movement!$G$4:$G$2137,Movement!$K$4:$K$2137,Summary!D$75,Movement!$L$4:$L$2137,Summary!$A106,Movement!$M$4:$M$2137,"USD")/1000000 -> 0 | E106: =SUM(B106:D106) -> 0
A107: E.O.P | B107: =B77+B78+B94 -> 1.504151 | C107: =C77+C78+C94 -> 71.648699 | D107: =D77+D78+D94 -> 88.993328 | E107: =SUM(B107:D107) -> 162.14618
A109: Test E.O.P | B109: =ROUND(B107*1000000,0)=ROUND(B63*1000000,0) -> TRUE | C109: =ROUND(C107*1000000,0)=ROUND(C63*1000000,0) -> TRUE | D109: =ROUND(D107*1000000,0)=ROUND(D63*1000000,0) -> TRUE | E109: =ROUND(E107*1000000,0)=ROUND(E63*1000000,0) -> TRUE
B110: =ROUND(B107*1000000,0)-ROUND(B63*1000000,0) -> 0 | C110: =ROUND(C107*1000000,0)-ROUND(C63*1000000,0) -> 0 | D110: =ROUND(D107*1000000,0)-ROUND(D63*1000000,0) -> 0 | E110: =ROUND(E107*1000000,0)-ROUND(E63*1000000,0) -> 0
B111: =B110*Fx -> 0 | C111: =C110*Fx -> 0 | D111: =D110*Fx -> 0 | E111: =E110*Fx -> 0
A114: 3. VND Deposit Yield
A116: ="At "&TEXT($B$6,"dd-mmm-yy")&", total VND deposit of BWID Group was USD$"&TEXT($B$123/1000000,"#,##0.0")&"mn. The Group is earning an average of "&TEXT(D123,"0.00%")&" p.a of its VND deposit." -> At 15-Jan-26, total VND deposit of BWID Group was USD$103,0149mn. The Group is earning an average of 005% p.a of its VND deposit.
A117: To improve yields on VND cash available moving forwards:
A118: (i) Evaluate the NTM cash projection and move up the tenor curve
A119: (ii) For existing term deposit, wait until maturity to move to higher yielding rate
B121: BWID's VND deposit in USD equivalent | C121: % | D121: Weighted average deposit rate
A122: Current account | B122: =SUMIFS(Table11[[#All],[CLOSING BALANCE (VND)2]],Table11[[#All],[ACCOUNT TYPE]],"<>Saving account")/Fx_rate -> 36143022 | C122: =B122/$B$136 -> 0.25972675 | D122: =VND_rate!I6 -> 0.00470124
A123: Term deposit | B123: =SUBTOTAL(109,B124:B135) -> 1.0301485e+08 | C123: =B123/$B$136 -> 0.74027325 | D123: =SUMPRODUCT(B125:B135,D125:D135)/B123 -> 0.047901407
A124: < 1 month | B124: =SUMIFS(Table1218[CLOSING BALANCE (VND)],Table1218[Term (months)],$A124)/Fx_rate -> 0 | C124: =B124/$B$136 -> 0 | D124: {=IFERROR(SUMPRODUCT((#REF!)*(#REF!)*(#REF!="2 weeks"))/SUMPRODUCT((#REF!)*(#REF!="2 weeks")),0)} -> 0
A125: 1 month | B125: =SUMIFS(Table1218[CLOSING BALANCE (VND)],Table1218[Term (months)],$A125)/Fx_rate -> 73386675 | C125: =B125/$B$136 -> 0.52736272 | D125: {=IFERROR(SUMPRODUCT((Table1218[CLOSING BALANCE (VND)])*(Table1218[Interest rate])*(Table1218[Term (months)]=Summary!$A125))/SUMPRODUCT((Table1218[CLOSING BALANCE (VND)])*(Table1218[Term (months)]=Summary!$A125)),0)} -> 0.047063289
A126: 2 months | B126: =SUMIFS(Table1218[CLOSING BALANCE (VND)],Table1218[Term (months)],$A126)/Fx_rate -> 7362562.5 | C126: =B126/$B$136 -> 0.052907983 | D126: {=IFERROR(SUMPRODUCT((Table1218[CLOSING BALANCE (VND)])*(Table1218[Interest rate])*(Table1218[Term (months)]=Summary!$A126))/SUMPRODUCT((Table1218[CLOSING BALANCE (VND)])*(Table1218[Term (months)]=Summary!$A126)),0)} -> 0.047255921
...

Sheet >>Breakdown

Sheet >>>Detail

Sheet Current_Yield
H2: =H4=Summary!B122*Fx_rate -> FALSE
A3: Original Currency: VND | B3: BWID JSC | C3: Yield | D3: VC3 | E3: Yield | F3: Subsidiaries | G3: Yield | H3: Total (VND) | I3: Weighted average deposit rate | J3: Remark
A4: Current Yield Deposit | B4: =SUM(B5:B17) -> 2661564578 | C4: =SUMPRODUCT(B5:B17,C5:C17)/B4 -> 0.0034058072 | D4: =SUM(D5:D17) -> 355152665621 | E4: =SUMPRODUCT(D5:D17,E5:E17)/D4 -> 0.004779879 | F4: =SUM(F5:F17) -> 536870155427 | G4: =SUMPRODUCT(F5:F17,G5:G17)/F4 -> 0.0046556406 | H4: =SUM(B4,D4,F4) -> 894684385626 | I4: =IFERROR((B4*C4+D4*E4+F4*G4)/H4,0) -> 0.00470124
A5: VTB | B5: =SUMIFS(Table11[CLOSING BALANCE (VND)2],Table11[NAME],B$3,Table11[Bank_1],$A5,Table11[ACCOUNT TYPE],"<>Saving Account") -> 1092828338 | C5: 0.005 | D5: =SUMIFS(Table11[CLOSING BALANCE (VND)2],Table11[NAME],D$3,Table11[Bank_1],$A5,Table11[ACCOUNT TYPE],"<>Saving Account") -> 323739882218 | E5: 0.005 | F5: =SUMIFS(Table11[CLOSING BALANCE (VND)2],Table11[NAME],F$3,Table11[Bank_1],$A5,Table11[ACCOUNT TYPE],"<>Saving Account") -> 257416245151 | G5: 0.005 | H5: =SUM(B5,D5,F5) -> 582248955707 | I5: =IFERROR((B5*C5+D5*E5+F5*G5)/H5,0) -> 0.005
A6: VCB | B6: =SUMIFS(Table11[CLOSING BALANCE (VND)2],Table11[NAME],B$3,Table11[Bank_1],$A6,Table11[ACCOUNT TYPE],"<>Saving Account") -> 511704863 | C6: 0.005 | D6: =SUMIFS(Table11[CLOSING BALANCE (VND)2],Table11[NAME],D$3,Table11[Bank_1],$A6,Table11[ACCOUNT TYPE],"<>Saving Account") -> 9871359781 | E6: 0.005 | F6: =SUMIFS(Table11[CLOSING BALANCE (VND)2],Table11[NAME],F$3,Table11[Bank_1],$A6,Table11[ACCOUNT TYPE],"<>Saving Account") -> 100658315230 | G6: 0.005 | H6: =SUM(B6,D6,F6) -> 111041379874 | I6: =IFERROR((B6*C6+D6*E6+F6*G6)/H6,0) -> 0.005
A7: BIDV | B7: =SUMIFS(Table11[CLOSING BALANCE (VND)2],Table11[NAME],B$3,Table11[Bank_1],$A7,Table11[ACCOUNT TYPE],"<>Saving Account") -> 38060079 | C7: 0.005 | D7: =SUMIFS(Table11[CLOSING BALANCE (VND)2],Table11[NAME],D$3,Table11[Bank_1],$A7,Table11[ACCOUNT TYPE],"<>Saving Account") -> 5452129673 | E7: 0.005 | F7: =SUMIFS(Table11[CLOSING BALANCE (VND)2],Table11[NAME],F$3,Table11[Bank_1],$A7,Table11[ACCOUNT TYPE],"<>Saving Account") -> 99745278620 | G7: 0.005 | H7: =SUM(B7,D7,F7) -> 105235468372 | I7: =IFERROR((B7*C7+D7*E7+F7*G7)/H7,0) -> 0.005
A8: VIB | B8: =SUMIFS(Table11[CLOSING BALANCE (VND)2],Table11[NAME],B$3,Table11[Bank_1],$A8,Table11[ACCOUNT TYPE],"<>Saving Account") -> 13672907 | C8: 0.005 | D8: =SUMIFS(Table11[CLOSING BALANCE (VND)2],Table11[NAME],D$3,Table11[Bank_1],$A8,Table11[ACCOUNT TYPE],"<>Saving Account") -> 187619615 | E8: 0.005 | F8: =SUMIFS(Table11[CLOSING BALANCE (VND)2],Table11[NAME],F$3,Table11[Bank_1],$A8,Table11[ACCOUNT TYPE],"<>Saving Account") -> 1594498896 | G8: 0.005 | H8: =SUM(B8,D8,F8) -> 1795791418 | I8: =IFERROR((B8*C8+D8*E8+F8*G8)/H8,0) -> 0.005
A9: OCB | B9: =SUMIFS(Table11[CLOSING BALANCE (VND)2],Table11[NAME],B$3,Table11[Bank_1],$A9,Table11[ACCOUNT TYPE],"<>Saving Account") -> 69627514 | C9: 0.001 | D9: =SUMIFS(Table11[CLOSING BALANCE (VND)2],Table11[NAME],D$3,Table11[Bank_1],$A9,Table11[ACCOUNT TYPE],"<>Saving Account") -> 56483173 | E9: 0.001 | F9: =SUMIFS(Table11[CLOSING BALANCE (VND)2],Table11[NAME],F$3,Table11[Bank_1],$A9,Table11[ACCOUNT TYPE],"<>Saving Account") -> 472518514 | G9: 0.001 | H9: =SUM(B9,D9,F9) -> 598629201 | I9: =IFERROR((B9*C9+D9*E9+F9*G9)/H9,0) -> 0.001
A10: MBB | B10: =SUMIFS(Table11[CLOSING BALANCE (VND)2],Table11[NAME],B$3,Table11[Bank_1],$A10,Table11[ACCOUNT TYPE],"<>Saving Account") -> 0 | D10: =SUMIFS(Table11[CLOSING BALANCE (VND)2],Table11[NAME],D$3,Table11[Bank_1],$A10,Table11[ACCOUNT TYPE],"<>Saving Account") -> 7958304 | E10: 0.001 | F10: =SUMIFS(Table11[CLOSING BALANCE (VND)2],Table11[NAME],F$3,Table11[Bank_1],$A10,Table11[ACCOUNT TYPE],"<>Saving Account") -> 0 | G10: 0.001 | H10: =SUM(B10,D10,F10) -> 7958304 | I10: =IFERROR((B10*C10+D10*E10+F10*G10)/H10,0) -> 0.001
A11: DB - Singapore | B11: =SUMIFS(Table11[CLOSING BALANCE (VND)2],Table11[NAME],B$3,Table11[Bank_1],$A11,Table11[ACCOUNT TYPE],"<>Saving Account") -> 0 | D11: =SUMIFS(Table11[CLOSING BALANCE (VND)2],Table11[NAME],D$3,Table11[Bank_1],$A11,Table11[ACCOUNT TYPE],"<>Saving Account") -> 0 | F11: =SUMIFS(Table11[CLOSING BALANCE (VND)2],Table11[NAME],F$3,Table11[Bank_1],$A11,Table11[ACCOUNT TYPE],"<>Saving Account") -> 0 | H11: =SUM(B11,D11,F11) -> 0 | I11: =IFERROR((B11*C11+D11*E11+F11*G11)/H11,0) -> 0
A12: SNP | B12: =SUMIFS(Table11[CLOSING BALANCE (VND)2],Table11[NAME],B$3,Table11[Bank_1],$A12,Table11[ACCOUNT TYPE],"<>Saving Account") -> 613468682 | D12: =SUMIFS(Table11[CLOSING BALANCE (VND)2],Table11[NAME],D$3,Table11[Bank_1],$A12,Table11[ACCOUNT TYPE],"<>Saving Account") -> 74818921 | F12: =SUMIFS(Table11[CLOSING BALANCE (VND)2],Table11[NAME],F$3,Table11[Bank_1],$A12,Table11[ACCOUNT TYPE],"<>Saving Account") -> 8987894766 | G12: 0.003 | H12: =SUM(B12,D12,F12) -> 9676182369 | I12: =IFERROR((B12*C12+D12*E12+F12*G12)/H12,0) -> 0.0027866036
A13: ACB | B13: =SUMIFS(Table11[CLOSING BALANCE (VND)2],Table11[NAME],B$3,Table11[Bank_1],$A13,Table11[ACCOUNT TYPE],"<>Saving Account") -> 69320954 | C13: 0.005 | D13: =SUMIFS(Table11[CLOSING BALANCE (VND)2],Table11[NAME],D$3,Table11[Bank_1],$A13,Table11[ACCOUNT TYPE],"<>Saving Account") -> 253471960 | E13: 0.005 | F13: =SUMIFS(Table11[CLOSING BALANCE (VND)2],Table11[NAME],F$3,Table11[Bank_1],$A13,Table11[ACCOUNT TYPE],"<>Saving Account") -> 110047453 | G13: 0.005 | H13: =SUM(B13,D13,F13) -> 432840367 | I13: =IFERROR((B13*C13+D13*E13+F13*G13)/H13,0) -> 0.005
A14: TCB | B14: =SUMIFS(Table11[CLOSING BALANCE (VND)2],Table11[NAME],B$3,Table11[Bank_1],$A14,Table11[ACCOUNT TYPE],"<>Saving Account") -> 1367012 | C14: 0.005 | D14: =SUMIFS(Table11[CLOSING BALANCE (VND)2],Table11[NAME],D$3,Table11[Bank_1],$A14,Table11[ACCOUNT TYPE],"<>Saving Account") -> 1560960116 | F14: =SUMIFS(Table11[CLOSING BALANCE (VND)2],Table11[NAME],F$3,Table11[Bank_1],$A14,Table11[ACCOUNT TYPE],"<>Saving Account") -> 13875586656 | G14: 0.005 | H14: =SUM(B14,D14,F14) -> 15437913784 | I14: =IFERROR((B14*C14+D14*E14+F14*G14)/H14,0) -> 0.0044944394
A15: Standard Chartered | B15: =SUMIFS(Table11[CLOSING BALANCE (VND)2],Table11[NAME],B$3,Table11[Bank_1],$A15,Table11[ACCOUNT TYPE],"<>Saving Account") -> 0 | C15: 0 | D15: =SUMIFS(Table11[CLOSING BALANCE (VND)2],Table11[NAME],D$3,Table11[Bank_1],$A15,Table11[ACCOUNT TYPE],"<>Saving Account") -> 0 | E15: 0 | F15: =SUMIFS(Table11[CLOSING BALANCE (VND)2],Table11[NAME],F$3,Table11[Bank_1],$A15,Table11[ACCOUNT TYPE],"<>Saving Account") -> 1465849798 | G15: 0 | H15: =SUM(B15,D15,F15) -> 1465849798 | I15: 0
A16: UOB | B16: =SUMIFS(Table11[CLOSING BALANCE (VND)2],Table11[NAME],B$3,Table11[Bank_1],$A16,Table11[ACCOUNT TYPE],"<>Saving Account") -> 71325444 | C16: 0 | D16: =SUMIFS(Table11[CLOSING BALANCE (VND)2],Table11[NAME],D$3,Table11[Bank_1],$A16,Table11[ACCOUNT TYPE],"<>Saving Account") -> 13300634401 | E16: 0 | F16: =SUMIFS(Table11[CLOSING BALANCE (VND)2],Table11[NAME],F$3,Table11[Bank_1],$A16,Table11[ACCOUNT TYPE],"<>Saving Account") -> 24708146 | G16: 0 | H16: =SUM(B16,D16,F16) -> 13396667991 | I16: 0
A17: Others | B17: =SUMIFS(Table11[CLOSING BALANCE (VND)2],Table11[NAME],B$3,Table11[Bank_1],$A17,Table11[ACCOUNT TYPE],"<>Saving Account") -> 180188785 | C17: 0.002 | D17: =SUMIFS(Table11[CLOSING BALANCE (VND)2],Table11[NAME],D$3,Table11[Bank_1],$A17,Table11[ACCOUNT TYPE],"<>Saving Account") -> 647347459 | E17: 0 | F17: =SUMIFS(Table11[CLOSING BALANCE (VND)2],Table11[NAME],F$3,Table11[Bank_1],$A17,Table11[ACCOUNT TYPE],"<>Saving Account") -> 52519212197 | G17: 0.002 | H17: =SUM(B17,D17,F17) -> 53346748441 | I17: =IFERROR((B17*C17+D17*E17+F17*G17)/H17,0) -> 0.0019757306
A18: Total | B18: =SUM(B5:B17) -> 2661564578 | D18: =SUM(D5:D17) -> 355152665621 | F18: =SUM(F5:F17) -> 536870155427 | H18: =SUM(H5:H17) -> 894684385626

Sheet VND_rate
A2: ="At "&TEXT(Summary!$B$6,"dd-mmm-yy")&", total VND deposit of BWID Group was VND"&TEXT($H$19/1000000000,"#,###.0")&"bn (or US"&TEXT($H$21/1000000,"$#,###.0")&"mn equivalent), accounted for "&TEXT($H$19/$H$20,"#.00%")&" of total cash, in which VND"&TEXT(VND_rate!D19/1000000000,"#,###.0")&"bn at VC3 (accounted for "&TEXT($D$19/$D$20,"#.00%")&" VC3's cash), VND"&TEXT(VND_rate!$F$19/1000000000,"#,###.0")&"bn at Subsidiaries (accounted for "&TEXT($F$19/$F$20,"0.00%")&" Sub's cash) and VND"&TEXT($B$19/1000000000,"#,###.0")&"bn at BWID JSC (accounted for "&TEXT($B$19/$B$20,"0.00%")&"BWID JSC's cash). The Group is earning an average of "&TEXT($I$19,"0.00%")&" p.a of its VND deposit." -> At 15-Jan-26, total VND deposit of BWID Group was VND2696,4138bn (or US$103,0149mn equivalent), accounted for 74% of total cash, in which VND920,0bn at VC3 (accounted for 72% VC3's cash), VND1740,2138bn at Subsidiaries (accounted for 075% Sub's cash) and VND36,20bn at BWID JSC (accounted for 093%BWID JSC's cash). The Group is earning an average of 000% p.a of its VND deposit.
B4: =VND_rate!B19=GETPIVOTDATA("CLOSING BALANCE (VND)",$A$46) -> FALSE | D4: =VND_rate!D19=GETPIVOTDATA("CLOSING BALANCE (VND)",$A$101) -> FALSE | F4: =VND_rate!F19=GETPIVOTDATA("CLOSING BALANCE (VND)",$A$130) -> FALSE | H4: =H19=GETPIVOTDATA("CLOSING BALANCE (VND)",$A$173) -> FALSE
B5: BWID JSC | C5: Yield | D5: VC3 | E5: Yield | F5: Subsidiaries | G5: Yield | H5: Total | I5: Weighted average deposit rate
A6: Current account | B6: =SUMIFS(Table11[CLOSING BALANCE (VND)2],Table11[ACCOUNT TYPE],"<>Saving account",Table11[NAME],VND_rate!B$5) -> 2661564578 | C6: =Current_Yield!C4 -> 0.0034058072 | D6: =SUMIFS(Table11[CLOSING BALANCE (VND)2],Table11[ACCOUNT TYPE],"<>Saving account",Table11[NAME],VND_rate!D$5) -> 355152665621 | E6: =Current_Yield!E4 -> 0.004779879 | F6: =SUMIFS(Table11[CLOSING BALANCE (VND)2],Table11[ACCOUNT TYPE],"<>Saving account",Table11[NAME],VND_rate!F$5) -> 588229372137 | G6: =Current_Yield!G4 -> 0.0046556406 | H6: =SUMIFS(Table11[CLOSING BALANCE (VND)2],Table11[ACCOUNT TYPE],"<>Saving account") -> 946043602336 | I6: =Current_Yield!I4 -> 0.00470124
A7: 2 weeks | B7: =SUMIFS(Table1218[[#All],[CLOSING BALANCE (VND)]],Table1218[[#All],[Term (months)]],VND_rate!$A7,Table1218[[#All],[NAME]],VND_rate!B$5) -> 0 | C7: {=IFERROR(SUMPRODUCT(('Saving Account'!$F$4:$F$259)*('Saving Account'!$L$4:$L$259)*('Saving Account'!$M$4:$M$259=VND_rate!B$5)*('Saving Account'!$H$4:$H$259=VND_rate!$A7))/SUMPRODUCT(('Saving Account'!$F$4:$F$259)*('Saving Account'!$M$4:$M$259=VND_rate!B$5)*('Saving Account'!$H$4:$H$259=VND_rate!$A7)),0)} -> 0 | D7: =SUMIFS(Table1218[[#All],[CLOSING BALANCE (VND)]],Table1218[[#All],[Term (months)]],VND_rate!$A7,Table1218[[#All],[NAME]],VND_rate!D$5) -> 0 | E7: {=IFERROR(SUMPRODUCT(('Saving Account'!$F$4:$F$259)*('Saving Account'!$L$4:$L$259)*('Saving Account'!$M$4:$M$259=VND_rate!D$5)*('Saving Account'!$H$4:$H$259=VND_rate!$A7))/SUMPRODUCT(('Saving Account'!$F$4:$F$259)*('Saving Account'!$M$4:$M$259=VND_rate!D$5)*('Saving Account'!$H$4:$H$259=VND_rate!$A7)),0)} -> 0 | F7: =SUMIFS(Table1218[[#All],[CLOSING BALANCE (VND)]],Table1218[[#All],[Term (months)]],VND_rate!$A7,Table1218[[#All],[NAME]],VND_rate!F$5) -> 0 | G7: {=IFERROR(SUMPRODUCT(('Saving Account'!$F$4:$F$259)*('Saving Account'!$L$4:$L$259)*('Saving Account'!$M$4:$M$259=VND_rate!F$5)*('Saving Account'!$H$4:$H$259=VND_rate!$A7))/SUMPRODUCT(('Saving Account'!$F$4:$F$259)*('Saving Account'!$M$4:$M$259=VND_rate!F$5)*('Saving Account'!$H$4:$H$259=VND_rate!$A7)),0)} -> 0 | H7: =B7+D7+F7 -> 0 | I7: =IFERROR((B7*C7+D7*E7+F7*G7)/H7,0) -> 0
A8: 1 month | B8: =SUMIFS(Table1218[[#All],[CLOSING BALANCE (VND)]],Table1218[[#All],[Term (months)]],VND_rate!$A8,Table1218[[#All],[NAME]],VND_rate!B$5) -> 36100000000 | C8: {=IFERROR(SUMPRODUCT(('Saving Account'!$F$4:$F$259)*('Saving Account'!$L$4:$L$259)*('Saving Account'!$M$4:$M$259=VND_rate!B$5)*('Saving Account'!$H$4:$H$259=VND_rate!$A8))/SUMPRODUCT(('Saving Account'!$F$4:$F$259)*('Saving Account'!$M$4:$M$259=VND_rate!B$5)*('Saving Account'!$H$4:$H$259=VND_rate!$A8)),0)} -> 0 | D8: =SUMIFS(Table1218[[#All],[CLOSING BALANCE (VND)]],Table1218[[#All],[Term (months)]],VND_rate!$A8,Table1218[[#All],[NAME]],VND_rate!D$5) -> 750000000000 | E8: {=IFERROR(SUMPRODUCT(('Saving Account'!$F$4:$F$259)*('Saving Account'!$L$4:$L$259)*('Saving Account'!$M$4:$M$259=VND_rate!D$5)*('Saving Account'!$H$4:$H$259=VND_rate!$A8))/SUMPRODUCT(('Saving Account'!$F$4:$F$259)*('Saving Account'!$M$4:$M$259=VND_rate!D$5)*('Saving Account'!$H$4:$H$259=VND_rate!$A8)),0)} -> 0 | F8: =SUMIFS(Table1218[[#All],[CLOSING BALANCE (VND)]],Table1218[[#All],[Term (months)]],VND_rate!$A8,Table1218[[#All],[NAME]],VND_rate!F$5) -> 1134796213022 | G8: {=IFERROR(SUMPRODUCT(('Saving Account'!$F$4:$F$259)*('Saving Account'!$L$4:$L$259)*('Saving Account'!$M$4:$M$259=VND_rate!F$5)*('Saving Account'!$H$4:$H$259=VND_rate!$A8))/SUMPRODUCT(('Saving Account'!$F$4:$F$259)*('Saving Account'!$M$4:$M$259=VND_rate!F$5)*('Saving Account'!$H$4:$H$259=VND_rate!$A8)),0)} -> 0 | H8: =B8+D8+F8 -> 1920896213022 | I8: =IFERROR((B8*C8+D8*E8+F8*G8)/H8,0) -> 0
A9: 2 months | B9: =SUMIFS(Table1218[[#All],[CLOSING BALANCE (VND)]],Table1218[[#All],[Term (months)]],VND_rate!$A9,Table1218[[#All],[NAME]],VND_rate!B$5) -> 0 | C9: {=IFERROR(SUMPRODUCT(('Saving Account'!$F$4:$F$259)*('Saving Account'!$L$4:$L$259)*('Saving Account'!$M$4:$M$259=VND_rate!B$5)*('Saving Account'!$H$4:$H$259=VND_rate!$A9))/SUMPRODUCT(('Saving Account'!$F$4:$F$259)*('Saving Account'!$M$4:$M$259=VND_rate!B$5)*('Saving Account'!$H$4:$H$259=VND_rate!$A9)),0)} -> 0 | D9: =SUMIFS(Table1218[[#All],[CLOSING BALANCE (VND)]],Table1218[[#All],[Term (months)]],VND_rate!$A9,Table1218[[#All],[NAME]],VND_rate!D$5) -> 0 | E9: {=IFERROR(SUMPRODUCT(('Saving Account'!$F$4:$F$259)*('Saving Account'!$L$4:$L$259)*('Saving Account'!$M$4:$M$259=VND_rate!D$5)*('Saving Account'!$H$4:$H$259=VND_rate!$A9))/SUMPRODUCT(('Saving Account'!$F$4:$F$259)*('Saving Account'!$M$4:$M$259=VND_rate!D$5)*('Saving Account'!$H$4:$H$259=VND_rate!$A9)),0)} -> 0 | F9: =SUMIFS(Table1218[[#All],[CLOSING BALANCE (VND)]],Table1218[[#All],[Term (months)]],VND_rate!$A9,Table1218[[#All],[NAME]],VND_rate!F$5) -> 192715073357 | G9: {=IFERROR(SUMPRODUCT(('Saving Account'!$F$4:$F$259)*('Saving Account'!$L$4:$L$259)*('Saving Account'!$M$4:$M$259=VND_rate!F$5)*('Saving Account'!$H$4:$H$259=VND_rate!$A9))/SUMPRODUCT(('Saving Account'!$F$4:$F$259)*('Saving Account'!$M$4:$M$259=VND_rate!F$5)*('Saving Account'!$H$4:$H$259=VND_rate!$A9)),0)} -> 0 | H9: =B9+D9+F9 -> 192715073357 | I9: =IFERROR((B9*C9+D9*E9+F9*G9)/H9,0) -> 0
A10: 3 months | B10: =SUMIFS(Table1218[[#All],[CLOSING BALANCE (VND)]],Table1218[[#All],[Term (months)]],VND_rate!$A10,Table1218[[#All],[NAME]],VND_rate!B$5) -> 0 | C10: {=IFERROR(SUMPRODUCT(('Saving Account'!$F$4:$F$259)*('Saving Account'!$L$4:$L$259)*('Saving Account'!$M$4:$M$259=VND_rate!B$5)*('Saving Account'!$H$4:$H$259=VND_rate!$A10))/SUMPRODUCT(('Saving Account'!$F$4:$F$259)*('Saving Account'!$M$4:$M$259=VND_rate!B$5)*('Saving Account'!$H$4:$H$259=VND_rate!$A10)),0)} -> 0 | D10: =SUMIFS(Table1218[[#All],[CLOSING BALANCE (VND)]],Table1218[[#All],[Term (months)]],VND_rate!$A10,Table1218[[#All],[NAME]],VND_rate!D$5) -> 0 | E10: {=IFERROR(SUMPRODUCT(('Saving Account'!$F$4:$F$259)*('Saving Account'!$L$4:$L$259)*('Saving Account'!$M$4:$M$259=VND_rate!D$5)*('Saving Account'!$H$4:$H$259=VND_rate!$A10))/SUMPRODUCT(('Saving Account'!$F$4:$F$259)*('Saving Account'!$M$4:$M$259=VND_rate!D$5)*('Saving Account'!$H$4:$H$259=VND_rate!$A10)),0)} -> 0 | F10: =SUMIFS(Table1218[[#All],[CLOSING BALANCE (VND)]],Table1218[[#All],[Term (months)]],VND_rate!$A10,Table1218[[#All],[NAME]],VND_rate!F$5) -> 317524917760 | G10: {=IFERROR(SUMPRODUCT(('Saving Account'!$F$4:$F$259)*('Saving Account'!$L$4:$L$259)*('Saving Account'!$M$4:$M$259=VND_rate!F$5)*('Saving Account'!$H$4:$H$259=VND_rate!$A10))/SUMPRODUCT(('Saving Account'!$F$4:$F$259)*('Saving Account'!$M$4:$M$259=VND_rate!F$5)*('Saving Account'!$H$4:$H$259=VND_rate!$A10)),0)} -> 0 | H10: =B10+D10+F10 -> 317524917760 | I10: =IFERROR((B10*C10+D10*E10+F10*G10)/H10,0) -> 0
A11: 4 months | B11: =SUMIFS(Table1218[[#All],[CLOSING BALANCE (VND)]],Table1218[[#All],[Term (months)]],VND_rate!$A11,Table1218[[#All],[NAME]],VND_rate!B$5) -> 0 | C11: {=IFERROR(SUMPRODUCT(('Saving Account'!$F$4:$F$259)*('Saving Account'!$L$4:$L$259)*('Saving Account'!$M$4:$M$259=VND_rate!B$5)*('Saving Account'!$H$4:$H$259=VND_rate!$A11))/SUMPRODUCT(('Saving Account'!$F$4:$F$259)*('Saving Account'!$M$4:$M$259=VND_rate!B$5)*('Saving Account'!$H$4:$H$259=VND_rate!$A11)),0)} -> 0 | D11: =SUMIFS(Table1218[[#All],[CLOSING BALANCE (VND)]],Table1218[[#All],[Term (months)]],VND_rate!$A11,Table1218[[#All],[NAME]],VND_rate!D$5) -> 0 | E11: {=IFERROR(SUMPRODUCT(('Saving Account'!$F$4:$F$259)*('Saving Account'!$L$4:$L$259)*('Saving Account'!$M$4:$M$259=VND_rate!D$5)*('Saving Account'!$H$4:$H$259=VND_rate!$A11))/SUMPRODUCT(('Saving Account'!$F$4:$F$259)*('Saving Account'!$M$4:$M$259=VND_rate!D$5)*('Saving Account'!$H$4:$H$259=VND_rate!$A11)),0)} -> 0 | F11: =SUMIFS(Table1218[[#All],[CLOSING BALANCE (VND)]],Table1218[[#All],[Term (months)]],VND_rate!$A11,Table1218[[#All],[NAME]],VND_rate!F$5) -> 5000000000 | G11: {=IFERROR(SUMPRODUCT(('Saving Account'!$F$4:$F$259)*('Saving Account'!$L$4:$L$259)*('Saving Account'!$M$4:$M$259=VND_rate!F$5)*('Saving Account'!$H$4:$H$259=VND_rate!$A11))/SUMPRODUCT(('Saving Account'!$F$4:$F$259)*('Saving Account'!$M$4:$M$259=VND_rate!F$5)*('Saving Account'!$H$4:$H$259=VND_rate!$A11)),0)} -> 0 | H11: =B11+D11+F11 -> 5000000000 | I11: =IFERROR((B11*C11+D11*E11+F11*G11)/H11,0) -> 0
A12: 5 months | B12: =SUMIFS(Table1218[[#All],[CLOSING BALANCE (VND)]],Table1218[[#All],[Term (months)]],VND_rate!$A12,Table1218[[#All],[NAME]],VND_rate!B$5) -> 0 | C12: {=IFERROR(SUMPRODUCT(('Saving Account'!$F$4:$F$259)*('Saving Account'!$L$4:$L$259)*('Saving Account'!$M$4:$M$259=VND_rate!B$5)*('Saving Account'!$H$4:$H$259=VND_rate!$A12))/SUMPRODUCT(('Saving Account'!$F$4:$F$259)*('Saving Account'!$M$4:$M$259=VND_rate!B$5)*('Saving Account'!$H$4:$H$259=VND_rate!$A12)),0)} -> 0 | D12: =SUMIFS(Table1218[[#All],[CLOSING BALANCE (VND)]],Table1218[[#All],[Term (months)]],VND_rate!$A12,Table1218[[#All],[NAME]],VND_rate!D$5) -> 0 | E12: {=IFERROR(SUMPRODUCT(('Saving Account'!$F$4:$F$259)*('Saving Account'!$L$4:$L$259)*('Saving Account'!$M$4:$M$259=VND_rate!D$5)*('Saving Account'!$H$4:$H$259=VND_rate!$A12))/SUMPRODUCT(('Saving Account'!$F$4:$F$259)*('Saving Account'!$M$4:$M$259=VND_rate!D$5)*('Saving Account'!$H$4:$H$259=VND_rate!$A12)),0)} -> 0 | F12: =SUMIFS(Table1218[[#All],[CLOSING BALANCE (VND)]],Table1218[[#All],[Term (months)]],VND_rate!$A12,Table1218[[#All],[NAME]],VND_rate!F$5) -> 8000000000 | G12: {=IFERROR(SUMPRODUCT(('Saving Account'!$F$4:$F$259)*('Saving Account'!$L$4:$L$259)*('Saving Account'!$M$4:$M$259=VND_rate!F$5)*('Saving Account'!$H$4:$H$259=VND_rate!$A12))/SUMPRODUCT(('Saving Account'!$F$4:$F$259)*('Saving Account'!$M$4:$M$259=VND_rate!F$5)*('Saving Account'!$H$4:$H$259=VND_rate!$A12)),0)} -> 0 | H12: =B12+D12+F12 -> 8000000000 | I12: =IFERROR((B12*C12+D12*E12+F12*G12)/H12,0) -> 0
A13: 6 months | B13: =SUMIFS(Table1218[[#All],[CLOSING BALANCE (VND)]],Table1218[[#All],[Term (months)]],VND_rate!$A13,Table1218[[#All],[NAME]],VND_rate!B$5) -> 0 | C13: {=IFERROR(SUMPRODUCT(('Saving Account'!$F$4:$F$259)*('Saving Account'!$L$4:$L$259)*('Saving Account'!$M$4:$M$259=VND_rate!B$5)*('Saving Account'!$H$4:$H$259=VND_rate!$A13))/SUMPRODUCT(('Saving Account'!$F$4:$F$259)*('Saving Account'!$M$4:$M$259=VND_rate!B$5)*('Saving Account'!$H$4:$H$259=VND_rate!$A13)),0)} -> 0 | D13: =SUMIFS(Table1218[[#All],[CLOSING BALANCE (VND)]],Table1218[[#All],[Term (months)]],VND_rate!$A13,Table1218[[#All],[NAME]],VND_rate!D$5) -> 170000000000 | E13: {=IFERROR(SUMPRODUCT(('Saving Account'!$F$4:$F$259)*('Saving Account'!$L$4:$L$259)*('Saving Account'!$M$4:$M$259=VND_rate!D$5)*('Saving Account'!$H$4:$H$259=VND_rate!$A13))/SUMPRODUCT(('Saving Account'!$F$4:$F$259)*('Saving Account'!$M$4:$M$259=VND_rate!D$5)*('Saving Account'!$H$4:$H$259=VND_rate!$A13)),0)} -> 0 | F13: =SUMIFS(Table1218[[#All],[CLOSING BALANCE (VND)]],Table1218[[#All],[Term (months)]],VND_rate!$A13,Table1218[[#All],[NAME]],VND_rate!F$5) -> 49250000000 | G13: {=IFERROR(SUMPRODUCT(('Saving Account'!$F$4:$F$259)*('Saving Account'!$L$4:$L$259)*('Saving Account'!$M$4:$M$259=VND_rate!F$5)*('Saving Account'!$H$4:$H$259=VND_rate!$A13))/SUMPRODUCT(('Saving Account'!$F$4:$F$259)*('Saving Account'!$M$4:$M$259=VND_rate!F$5)*('Saving Account'!$H$4:$H$259=VND_rate!$A13)),0)} -> 0 | H13: =B13+D13+F13 -> 219250000000 | I13: =IFERROR((B13*C13+D13*E13+F13*G13)/H13,0) -> 0
A14: 7 months | B14: =SUMIFS(Table1218[[#All],[CLOSING BALANCE (VND)]],Table1218[[#All],[Term (months)]],VND_rate!$A14,Table1218[[#All],[NAME]],VND_rate!B$5) -> 0 | C14: {=IFERROR(SUMPRODUCT(('Saving Account'!$F$4:$F$259)*('Saving Account'!$L$4:$L$259)*('Saving Account'!$M$4:$M$259=VND_rate!B$5)*('Saving Account'!$H$4:$H$259=VND_rate!$A14))/SUMPRODUCT(('Saving Account'!$F$4:$F$259)*('Saving Account'!$M$4:$M$259=VND_rate!B$5)*('Saving Account'!$H$4:$H$259=VND_rate!$A14)),0)} -> 0 | D14: =SUMIFS(Table1218[[#All],[CLOSING BALANCE (VND)]],Table1218[[#All],[Term (months)]],VND_rate!$A14,Table1218[[#All],[NAME]],VND_rate!D$5) -> 0 | E14: {=IFERROR(SUMPRODUCT(('Saving Account'!$F$4:$F$259)*('Saving Account'!$L$4:$L$259)*('Saving Account'!$M$4:$M$259=VND_rate!D$5)*('Saving Account'!$H$4:$H$259=VND_rate!$A14))/SUMPRODUCT(('Saving Account'!$F$4:$F$259)*('Saving Account'!$M$4:$M$259=VND_rate!D$5)*('Saving Account'!$H$4:$H$259=VND_rate!$A14)),0)} -> 0 | F14: =SUMIFS(Table1218[[#All],[CLOSING BALANCE (VND)]],Table1218[[#All],[Term (months)]],VND_rate!$A14,Table1218[[#All],[NAME]],VND_rate!F$5) -> 0 | G14: {=IFERROR(SUMPRODUCT(('Saving Account'!$F$4:$F$259)*('Saving Account'!$L$4:$L$259)*('Saving Account'!$M$4:$M$259=VND_rate!F$5)*('Saving Account'!$H$4:$H$259=VND_rate!$A14))/SUMPRODUCT(('Saving Account'!$F$4:$F$259)*('Saving Account'!$M$4:$M$259=VND_rate!F$5)*('Saving Account'!$H$4:$H$259=VND_rate!$A14)),0)} -> 0 | H14: =B14+D14+F14 -> 0 | I14: =IFERROR((B14*C14+D14*E14+F14*G14)/H14,0) -> 0
A15: 8 months | B15: =SUMIFS(Table1218[[#All],[CLOSING BALANCE (VND)]],Table1218[[#All],[Term (months)]],VND_rate!$A15,Table1218[[#All],[NAME]],VND_rate!B$5) -> 0 | C15: {=IFERROR(SUMPRODUCT(('Saving Account'!$F$4:$F$259)*('Saving Account'!$L$4:$L$259)*('Saving Account'!$M$4:$M$259=VND_rate!B$5)*('Saving Account'!$H$4:$H$259=VND_rate!$A15))/SUMPRODUCT(('Saving Account'!$F$4:$F$259)*('Saving Account'!$M$4:$M$259=VND_rate!B$5)*('Saving Account'!$H$4:$H$259=VND_rate!$A15)),0)} -> 0 | D15: =SUMIFS(Table1218[[#All],[CLOSING BALANCE (VND)]],Table1218[[#All],[Term (months)]],VND_rate!$A15,Table1218[[#All],[NAME]],VND_rate!D$5) -> 0 | E15: {=IFERROR(SUMPRODUCT(('Saving Account'!$F$4:$F$259)*('Saving Account'!$L$4:$L$259)*('Saving Account'!$M$4:$M$259=VND_rate!D$5)*('Saving Account'!$H$4:$H$259=VND_rate!$A15))/SUMPRODUCT(('Saving Account'!$F$4:$F$259)*('Saving Account'!$M$4:$M$259=VND_rate!D$5)*('Saving Account'!$H$4:$H$259=VND_rate!$A15)),0)} -> 0 | F15: =SUMIFS(Table1218[[#All],[CLOSING BALANCE (VND)]],Table1218[[#All],[Term (months)]],VND_rate!$A15,Table1218[[#All],[NAME]],VND_rate!F$5) -> 0 | G15: {=IFERROR(SUMPRODUCT(('Saving Account'!$F$4:$F$259)*('Saving Account'!$L$4:$L$259)*('Saving Account'!$M$4:$M$259=VND_rate!F$5)*('Saving Account'!$H$4:$H$259=VND_rate!$A15))/SUMPRODUCT(('Saving Account'!$F$4:$F$259)*('Saving Account'!$M$4:$M$259=VND_rate!F$5)*('Saving Account'!$H$4:$H$259=VND_rate!$A15)),0)} -> 0 | H15: =B15+D15+F15 -> 0 | I15: =IFERROR((B15*C15+D15*E15+F15*G15)/H15,0) -> 0
A16: 9 months | B16: =SUMIFS(Table1218[[#All],[CLOSING BALANCE (VND)]],Table1218[[#All],[Term (months)]],VND_rate!$A16,Table1218[[#All],[NAME]],VND_rate!B$5) -> 0 | C16: {=IFERROR(SUMPRODUCT(('Saving Account'!$F$4:$F$259)*('Saving Account'!$L$4:$L$259)*('Saving Account'!$M$4:$M$259=VND_rate!B$5)*('Saving Account'!$H$4:$H$259=VND_rate!$A16))/SUMPRODUCT(('Saving Account'!$F$4:$F$259)*('Saving Account'!$M$4:$M$259=VND_rate!B$5)*('Saving Account'!$H$4:$H$259=VND_rate!$A16)),0)} -> 0 | D16: =SUMIFS(Table1218[[#All],[CLOSING BALANCE (VND)]],Table1218[[#All],[Term (months)]],VND_rate!$A16,Table1218[[#All],[NAME]],VND_rate!D$5) -> 0 | E16: {=IFERROR(SUMPRODUCT(('Saving Account'!$F$4:$F$259)*('Saving Account'!$L$4:$L$259)*('Saving Account'!$M$4:$M$259=VND_rate!D$5)*('Saving Account'!$H$4:$H$259=VND_rate!$A16))/SUMPRODUCT(('Saving Account'!$F$4:$F$259)*('Saving Account'!$M$4:$M$259=VND_rate!D$5)*('Saving Account'!$H$4:$H$259=VND_rate!$A16)),0)} -> 0 | F16: =SUMIFS(Table1218[[#All],[CLOSING BALANCE (VND)]],Table1218[[#All],[Term (months)]],VND_rate!$A16,Table1218[[#All],[NAME]],VND_rate!F$5) -> 0 | G16: {=IFERROR(SUMPRODUCT(('Saving Account'!$F$4:$F$259)*('Saving Account'!$L$4:$L$259)*('Saving Account'!$M$4:$M$259=VND_rate!F$5)*('Saving Account'!$H$4:$H$259=VND_rate!$A16))/SUMPRODUCT(('Saving Account'!$F$4:$F$259)*('Saving Account'!$M$4:$M$259=VND_rate!F$5)*('Saving Account'!$H$4:$H$259=VND_rate!$A16)),0)} -> 0 | H16: =B16+D16+F16 -> 0 | I16: =IFERROR((B16*C16+D16*E16+F16*G16)/H16,0) -> 0
A17: 12 months | B17: =SUMIFS(Table1218[[#All],[CLOSING BALANCE (VND)]],Table1218[[#All],[Term (months)]],VND_rate!$A17,Table1218[[#All],[NAME]],VND_rate!B$5) -> 100000000 | C17: {=IFERROR(SUMPRODUCT(('Saving Account'!$F$4:$F$259)*('Saving Account'!$L$4:$L$259)*('Saving Account'!$M$4:$M$259=VND_rate!B$5)*('Saving Account'!$H$4:$H$259=VND_rate!$A17))/SUMPRODUCT(('Saving Account'!$F$4:$F$259)*('Saving Account'!$M$4:$M$259=VND_rate!B$5)*('Saving Account'!$H$4:$H$259=VND_rate!$A17)),0)} -> 0 | D17: =SUMIFS(Table1218[[#All],[CLOSING BALANCE (VND)]],Table1218[[#All],[Term (months)]],VND_rate!$A17,Table1218[[#All],[NAME]],VND_rate!D$5) -> 0 | E17: {=IFERROR(SUMPRODUCT(('Saving Account'!$F$4:$F$259)*('Saving Account'!$L$4:$L$259)*('Saving Account'!$M$4:$M$259=VND_rate!D$5)*('Saving Account'!$H$4:$H$259=VND_rate!$A17))/SUMPRODUCT(('Saving Account'!$F$4:$F$259)*('Saving Account'!$M$4:$M$259=VND_rate!D$5)*('Saving Account'!$H$4:$H$259=VND_rate!$A17)),0)} -> 0 | F17: =SUMIFS(Table1218[[#All],[CLOSING BALANCE (VND)]],Table1218[[#All],[Term (months)]],VND_rate!$A17,Table1218[[#All],[NAME]],VND_rate!F$5) -> 17160452453 | G17: {=IFERROR(SUMPRODUCT(('Saving Account'!$F$4:$F$259)*('Saving Account'!$L$4:$L$259)*('Saving Account'!$M$4:$M$259=VND_rate!F$5)*('Saving Account'!$H$4:$H$259=VND_rate!$A17))/SUMPRODUCT(('Saving Account'!$F$4:$F$259)*('Saving Account'!$M$4:$M$259=VND_rate!F$5)*('Saving Account'!$H$4:$H$259=VND_rate!$A17)),0)} -> 0 | H17: =B17+D17+F17 -> 17260452453 | I17: =IFERROR((B17*C17+D17*E17+F17*G17)/H17,0) -> 0
A18: 13 months | B18: =SUMIFS(Table1218[[#All],[CLOSING BALANCE (VND)]],Table1218[[#All],[Term (months)]],VND_rate!$A18,Table1218[[#All],[NAME]],VND_rate!B$5) -> 0 | C18: {=IFERROR(SUMPRODUCT(('Saving Account'!$F$4:$F$259)*('Saving Account'!$L$4:$L$259)*('Saving Account'!$M$4:$M$259=VND_rate!B$5)*('Saving Account'!$H$4:$H$259=VND_rate!$A18))/SUMPRODUCT(('Saving Account'!$F$4:$F$259)*('Saving Account'!$M$4:$M$259=VND_rate!B$5)*('Saving Account'!$H$4:$H$259=VND_rate!$A18)),0)} -> 0 | D18: =SUMIFS(Table1218[[#All],[CLOSING BALANCE (VND)]],Table1218[[#All],[Term (months)]],VND_rate!$A18,Table1218[[#All],[NAME]],VND_rate!D$5) -> 0 | E18: {=IFERROR(SUMPRODUCT(('Saving Account'!$F$4:$F$259)*('Saving Account'!$L$4:$L$259)*('Saving Account'!$M$4:$M$259=VND_rate!D$5)*('Saving Account'!$H$4:$H$259=VND_rate!$A18))/SUMPRODUCT(('Saving Account'!$F$4:$F$259)*('Saving Account'!$M$4:$M$259=VND_rate!D$5)*('Saving Account'!$H$4:$H$259=VND_rate!$A18)),0)} -> 0 | F18: =SUMIFS(Table1218[[#All],[CLOSING BALANCE (VND)]],Table1218[[#All],[Term (months)]],VND_rate!$A18,Table1218[[#All],[NAME]],VND_rate!F$5) -> 15767097552 | G18: {=IFERROR(SUMPRODUCT(('Saving Account'!$F$4:$F$259)*('Saving Account'!$L$4:$L$259)*('Saving Account'!$M$4:$M$259=VND_rate!F$5)*('Saving Account'!$H$4:$H$259=VND_rate!$A18))/SUMPRODUCT(('Saving Account'!$F$4:$F$259)*('Saving Account'!$M$4:$M$259=VND_rate!F$5)*('Saving Account'!$H$4:$H$259=VND_rate!$A18)),0)} -> 0 | H18: =B18+D18+F18 -> 15767097552 | I18: =IFERROR((B18*C18+D18*E18+F18*G18)/H18,0) -> 0
A19: Term deposit | B19: =SUM(B7:B18) -> 36200000000 | C19: =SUMPRODUCT(B7:B18,C7:C18)/B19 -> 0 | D19: =SUM(D7:D18) -> 920000000000 | E19: =SUMPRODUCT(D7:D18,E7:E18)/D19 -> 0 | F19: =SUM(F7:F18) -> 1740213754144 | G19: =SUMPRODUCT(F7:F18,G7:G18)/F19 -> 0 | H19: =SUM(H7:H18) -> 2696413754144 | I19: =SUMPRODUCT(H7:H18,I7:I18)/H19 -> 0
A20: Total in VND | B20: =SUM(B6:B18) -> 38861564578 | C20: =SUMPRODUCT(B6:B18,C6:C18)/B20 -> 0.00023325813 | D20: =SUM(D6:D18) -> 1275152665621 | E20: =SUMPRODUCT(D6:D18,E6:E18)/D20 -> 0.0013312812 | F20: =SUM(F6:F18) -> 2328443126281 | G20: =SUMPRODUCT(F6:F18,G6:G18)/F20 -> 0.0011761441 | H20: =SUM(H6:H18) -> 3642457356480 | I20: =SUMPRODUCT(H6:H18,I6:I18)/H20 -> 0.0012210378
A21: Total VND deposit in USD equivalent | B21: =B19/Fx_rate -> 1382999 | D21: =D19/Fx_rate -> 35148042 | F21: =F19/Fx_rate -> 66483811 | H21: =H19/Fx_rate -> 1.0301485e+08
A22: Total VND cash in USD equivalent | B22: =B20/Fx_rate -> 1484682.5 | D22: =D20/Fx_rate -> 48716434 | F22: =F20/Fx_rate -> 88956757 | H22: =H20/Fx -> 1.3915787e+08
A23: % | B23: =B22/$H$22 -> 0.010669051 | D23: =D22/$H$22 -> 0.35008033 | F23: =F22/$H$22 -> 0.63925062 | H23: =H22/$H$22 -> 1
H25: =VND_rate!H20=Summary!B18*1000000*Fx_rate -> FALSE
A41: DETAIL CASH DEPOSIT
A44: NAME | B44: BWID JSC
A46: Sum of CLOSING BALANCE (VND) | B46: Column Labels
A47: Row Labels | B47: 1 month | C47: 12 months | D47: 3 months | E47: Grand Total | AC47: 1 month | AD47: 3 months | AE47: 6 months | AF47: 12 months | AG47: Grand Total
A48: VCB | B48: 100000000 | C48: 100000000 | E48: 200000000 | AC48: {=IFERROR(SUM(AC49:AC51)/INDEX($B48:$E48,,MATCH(AC$47,$B$47:$E$47,0)),0)} -> 0 | AD48: {=IFERROR(SUM(AD49:AD51)/INDEX($B48:$E48,,MATCH(AD$47,$B$47:$E$47,0)),0)} -> 0 | AE48: {=IFERROR(SUM(AE49:AE51)/INDEX($B48:$E48,,MATCH(AE$47,$B$47:$E$47,0)),0)} -> 0 | AF48: {=IFERROR(SUM(AF49:AF51)/INDEX($B48:$E48,,MATCH(AF$47,$B$47:$E$47,0)),0)} -> 0
A49: 0.041 | C49: 100000000 | E49: 100000000 | AC49: {=$A49*IFERROR(INDEX($B49:$E49,,MATCH(AC$47,$B$47:$E$47,0)),0)} -> 0 | AD49: {=$A49*IFERROR(INDEX($B49:$E49,,MATCH(AD$47,$B$47:$E$47,0)),0)} -> 0 | AE49: {=$A49*IFERROR(INDEX($B49:$E49,,MATCH(AE$47,$B$47:$E$47,0)),0)} -> 0 | AF49: {=$A49*IFERROR(INDEX($B49:$E49,,MATCH(AF$47,$B$47:$E$47,0)),0)} -> 4100000
A50: 0.015 | B50: 100000000 | E50: 100000000 | AC50: {=$A50*IFERROR(INDEX($B50:$E50,,MATCH(AC$47,$B$47:$E$47,0)),0)} -> 1500000 | AD50: {=$A50*IFERROR(INDEX($B50:$E50,,MATCH(AD$47,$B$47:$E$47,0)),0)} -> 0 | AE50: {=$A50*IFERROR(INDEX($B50:$E50,,MATCH(AE$47,$B$47:$E$47,0)),0)} -> 0 | AF50: {=$A50*IFERROR(INDEX($B50:$E50,,MATCH(AF$47,$B$47:$E$47,0)),0)} -> 0
A51: SNP | D51: 30000000000 | E51: 30000000000 | AC51: {=$A51*IFERROR(INDEX($B51:$E51,,MATCH(AC$47,$B$47:$E$47,0)),0)} -> #VALUE! | AD51: {=$A51*IFERROR(INDEX($B51:$E51,,MATCH(AD$47,$B$47:$E$47,0)),0)} -> #VALUE! | AE51: {=$A51*IFERROR(INDEX($B51:$E51,,MATCH(AE$47,$B$47:$E$47,0)),0)} -> #VALUE! | AF51: {=$A51*IFERROR(INDEX($B51:$E51,,MATCH(AF$47,$B$47:$E$47,0)),0)} -> #VALUE!
A52: 0.045 | D52: 30000000000 | E52: 30000000000 | AC52: {=IFERROR(SUM(AC53:AC53)/INDEX($B52:$E52,,MATCH(AC$47,$B$47:$E$47,0)),0)} -> 0 | AD52: {=IFERROR(SUM(AD53:AD53)/INDEX($B52:$E52,,MATCH(AD$47,$B$47:$E$47,0)),0)} -> 0 | AE52: {=IFERROR(SUM(AE53:AE53)/INDEX($B52:$E52,,MATCH(AE$47,$B$47:$E$47,0)),0)} -> 0 | AF52: {=IFERROR(SUM(AF53:AF53)/INDEX($B52:$E52,,MATCH(AF$47,$B$47:$E$47,0)),0)} -> 0
A53: Grand Total | B53: 100000000 | C53: 100000000 | D53: 30000000000 | E53: 30200000000 | AC53: {=$A53*IFERROR(INDEX($B53:$E53,,MATCH(AC$47,$B$47:$E$47,0)),0)} -> #VALUE! | AD53: {=$A53*IFERROR(INDEX($B53:$E53,,MATCH(AD$47,$B$47:$E$47,0)),0)} -> #VALUE! | AE53: {=$A53*IFERROR(INDEX($B53:$E53,,MATCH(AE$47,$B$47:$E$47,0)),0)} -> #VALUE! | AF53: {=$A53*IFERROR(INDEX($B53:$E53,,MATCH(AF$47,$B$47:$E$47,0)),0)} -> #VALUE!
AC54: =IFERROR((AC48*B48+AC52*B52)/B54,0) -> 0 | AD54: =IFERROR((AD48*C48+AD52*C52)/C54,0) -> 0 | AE54: =IFERROR((AE48*D48+AE52*D52)/D54,0) -> 0 | AF54: =IFERROR((AF48*D48+AF52*D52)/D54,0) -> 0 | AG54: =IFERROR((AG48*F48+AG52*F52)/F55,0) -> 0
A99: NAME | B99: VC3
A101: Sum of CLOSING BALANCE (VND) | B101: Column Labels
A102: Row Labels | B102: 1 month | C102: 6 months | D102: Grand Total
A103: BIDV | B103: 50000000000 | D103: 50000000000
A104: 0.043 | B104: 50000000000 | D104: 50000000000 | AC104: {=$A107*IFERROR(INDEX($D104:$E104,,MATCH(AC$47,#REF!,0)),0)} -> #VALUE! | AD104: {=$A107*IFERROR(INDEX($D104:$E104,,MATCH(AD$47,#REF!,0)),0)} -> #VALUE! | AE104: {=$A107*IFERROR(INDEX($D104:$E104,,MATCH(AE$47,#REF!,0)),0)} -> #VALUE! | AF104: {=$A107*IFERROR(INDEX($D104:$E104,,MATCH(AF$47,#REF!,0)),0)} -> #VALUE!
A105: VCB | B105: 950000000000 | D105: 950000000000 | AC105: {=IFERROR(SUM(#REF!)/INDEX($D106:$E106,,MATCH(AC$47,$B$47:$E$47,0)),0)} -> 0 | AD105: {=IFERROR(SUM(#REF!)/INDEX($D106:$E106,,MATCH(AD$47,$B$47:$E$47,0)),0)} -> 0 | AE105: {=IFERROR(SUM(#REF!)/INDEX($D106:$E106,,MATCH(AE$47,$B$47:$E$47,0)),0)} -> 0 | AF105: {=IFERROR(SUM(#REF!)/INDEX($D106:$E106,,MATCH(AF$47,$B$47:$E$47,0)),0)} -> 0
A106: 0.043 | B106: 950000000000 | D106: 950000000000 | AC106: =(#REF!*#REF!+#REF!*#REF!+#REF!*#REF!)/B108 -> #REF!
A107: VTB | B107: 182000000000 | D107: 182000000000
A108: 0.045 | B108: 182000000000 | D108: 182000000000
A109: SNP | B109: 50000000000 | D109: 50000000000
A110: 0.043 | B110: 50000000000 | D110: 50000000000
A111: VIB | C111: 170000000000 | D111: 170000000000
A112: 0.062 | C112: 170000000000 | D112: 170000000000
A113: TCB | B113: 50000000000 | D113: 50000000000
A114: 0.0475 | B114: 50000000000 | D114: 50000000000
A115: Grand Total | B115: 1282000000000 | C115: 170000000000 | D115: 1452000000000
A128: NAME | B128: Subsidiaries
A130: Sum of CLOSING BALANCE (VND) | B130: Column Labels
A131: Row Labels | B131: 1 month | C131: 12 months | D131: 13 months | E131: 2 months | F131: 3 months | G131: 4 months | H131: 5 months | I131: 6 months | J131: 7 months | K131: Grand Total | AC131: 1 month | AD131: 3 months | AE131: 6 months | AF131: 12 months | AG131: Grand Total
A132: BIDV | B132: 148900000000 | C132: 2878000000 | E132: 7000000000 | F132: 155215000000 | G132: 9700000000 | I132: 35000000000 | J132: 10000000000 | K132: 368693000000 | AC132: {=IFERROR(SUM(AC133:AC136)/INDEX($B132:$E132,,MATCH(AC$131,$B$131:$E$131,0)),0)} -> 0.043758899 | AD132: {=IFERROR(SUM(AD133:AD136)/INDEX($B132:$E132,,MATCH(AD$131,$B$131:$E$131,0)),0)} -> 0 | AE132: {=IFERROR(SUM(AE133:AE136)/INDEX($B132:$E132,,MATCH(AE$131,$B$131:$E$131,0)),0)} -> 0 | AF132: {=IFERROR(SUM(AF133:AF136)/INDEX($B132:$E132,,MATCH(AF$131,$B$131:$E$131,0)),0)} -> 0.02637943
A133: 0.046 | I133: 19000000000 | J133: 8000000000 | K133: 27000000000 | AC133: {=$A133*IFERROR(INDEX($B133:$E133,,MATCH(AC$47,$B$131:$E$131,0)),0)} -> 0 | AD133: {=$A133*IFERROR(INDEX($B133:$E133,,MATCH(AD$47,$B$131:$E$131,0)),0)} -> 0 | AE133: {=$A133*IFERROR(INDEX($B133:$E133,,MATCH(AE$47,$B$131:$E$131,0)),0)} -> 0 | AF133: {=$A133*IFERROR(INDEX($B133:$E133,,MATCH(AF$47,$B$131:$E$131,0)),0)} -> 0
A134: 0.052 | C134: 1460000000 | K134: 1460000000 | AC134: {=$A134*IFERROR(INDEX($B134:$E134,,MATCH(AC$47,$B$131:$E$131,0)),0)} -> 0 | AD134: {=$A134*IFERROR(INDEX($B134:$E134,,MATCH(AD$47,$B$131:$E$131,0)),0)} -> 0 | AE134: {=$A134*IFERROR(INDEX($B134:$E134,,MATCH(AE$47,$B$131:$E$131,0)),0)} -> 0 | AF134: {=$A134*IFERROR(INDEX($B134:$E134,,MATCH(AF$47,$B$131:$E$131,0)),0)} -> 75920000
A135: 0.043 | B135: 92400000000 | E135: 7000000000 | K135: 99400000000 | AC135: {=$A135*IFERROR(INDEX($B135:$E135,,MATCH(AC$47,$B$131:$E$131,0)),0)} -> 3.9732e+09 | AD135: {=$A135*IFERROR(INDEX($B135:$E135,,MATCH(AD$47,$B$131:$E$131,0)),0)} -> 0 | AE135: {=$A135*IFERROR(INDEX($B135:$E135,,MATCH(AE$47,$B$131:$E$131,0)),0)} -> 0 | AF135: {=$A135*IFERROR(INDEX($B135:$E135,,MATCH(AF$47,$B$131:$E$131,0)),0)} -> 0
A136: 0.045 | B136: 56500000000 | F136: 125215000000 | G136: 9700000000 | I136: 6400000000 | J136: 2000000000 | K136: 199815000000 | AC136: {=$A136*IFERROR(INDEX($B136:$E136,,MATCH(AC$47,$B$131:$E$131,0)),0)} -> 2542500000 | AD136: {=$A136*IFERROR(INDEX($B136:$E136,,MATCH(AD$47,$B$131:$E$131,0)),0)} -> 0 | AE136: {=$A136*IFERROR(INDEX($B136:$E136,,MATCH(AE$47,$B$131:$E$131,0)),0)} -> 0 | AF136: {=$A136*IFERROR(INDEX($B136:$E136,,MATCH(AF$47,$B$131:$E$131,0)),0)} -> 0
A137: 0.048 | I137: 2500000000 | K137: 2500000000 | AC137: {=IFERROR(SUM(AC138)/INDEX($B138:$E138,,MATCH(AC$131,$B$131:$E$131,0)),0)} -> 0 | AD137: {=IFERROR(SUM(AD138)/INDEX($B138:$E138,,MATCH(AD$131,$B$131:$E$131,0)),0)} -> 0 | AE137: {=IFERROR(SUM(AE138)/INDEX($B138:$E138,,MATCH(AE$131,$B$131:$E$131,0)),0)} -> 0 | AF137: {=IFERROR(SUM(AF138)/INDEX($B138:$E138,,MATCH(AF$131,$B$131:$E$131,0)),0)} -> 0
A138: 0.029 | I138: 2700000000 | K138: 2700000000 | AC138: {=$A138*IFERROR(INDEX($B138:$E138,,MATCH(AC$47,$B$131:$E$131,0)),0)} -> 0 | AD138: {=$A138*IFERROR(INDEX($B138:$E138,,MATCH(AD$47,$B$131:$E$131,0)),0)} -> 0 | AE138: {=$A138*IFERROR(INDEX($B138:$E138,,MATCH(AE$47,$B$131:$E$131,0)),0)} -> 0 | AF138: {=$A138*IFERROR(INDEX($B138:$E138,,MATCH(AF$47,$B$131:$E$131,0)),0)} -> 0
A139: 0.042 | C139: 1418000000 | I139: 4400000000 | K139: 5818000000 | AC139: {=IFERROR(SUM(AC140:AC141)/INDEX($B139:$E139,,MATCH(AC$131,$B$131:$E$131,0)),0)} -> 0 | AD139: {=IFERROR(SUM(AD140:AD141)/INDEX($B139:$E139,,MATCH(AD$131,$B$131:$E$131,0)),0)} -> 0 | AE139: {=IFERROR(SUM(AE140:AE141)/INDEX($B139:$E139,,MATCH(AE$131,$B$131:$E$131,0)),0)} -> 0 | AF139: {=IFERROR(SUM(AF140:AF141)/INDEX($B139:$E139,,MATCH(AF$131,$B$131:$E$131,0)),0)} -> 0
A140: 0.044 | F140: 30000000000 | K140: 30000000000 | AC140: {=$A140*IFERROR(INDEX($B140:$E140,,MATCH(AC$47,$B$131:$E$131,0)),0)} -> 0 | AD140: {=$A140*IFERROR(INDEX($B140:$E140,,MATCH(AD$47,$B$131:$E$131,0)),0)} -> 0 | AE140: {=$A140*IFERROR(INDEX($B140:$E140,,MATCH(AE$47,$B$131:$E$131,0)),0)} -> 0 | AF140: {=$A140*IFERROR(INDEX($B140:$E140,,MATCH(AF$47,$B$131:$E$131,0)),0)} -> 0
A141: VCB | B141: 47800000000 | C141: 1128000000 | E141: 17500000000 | F141: 66500000000 | G141: 4000000000 | H141: 6000000000 | I141: 11000000000 | K141: 153928000000 | AC141: {=$A141*IFERROR(INDEX($B141:$E141,,MATCH(AC$47,$B$131:$E$131,0)),0)} -> #VALUE! | AD141: {=$A141*IFERROR(INDEX($B141:$E141,,MATCH(AD$47,$B$131:$E$131,0)),0)} -> #VALUE! | AE141: {=$A141*IFERROR(INDEX($B141:$E141,,MATCH(AE$47,$B$131:$E$131,0)),0)} -> #VALUE! | AF141: {=$A141*IFERROR(INDEX($B141:$E141,,MATCH(AF$47,$B$131:$E$131,0)),0)} -> #VALUE!
A142: 0.043 | B142: 7000000000 | E142: 3000000000 | K142: 10000000000 | AC142: {=IFERROR(SUM(AC143:AC148)/INDEX($B142:$E142,,MATCH(AC$131,$B$131:$E$131,0)),0)} -> 0 | AD142: {=IFERROR(SUM(AD143:AD148)/INDEX($B142:$E142,,MATCH(AD$131,$B$131:$E$131,0)),0)} -> 0 | AE142: {=IFERROR(SUM(AE143:AE148)/INDEX($B142:$E142,,MATCH(AE$131,$B$131:$E$131,0)),0)} -> 0 | AF142: {=IFERROR(SUM(AF143:AF148)/INDEX($B142:$E142,,MATCH(AF$131,$B$131:$E$131,0)),0)} -> 0
A143: 0.041 | C143: 1128000000 | K143: 1128000000 | AC143: {=$A143*IFERROR(INDEX($B143:$E143,,MATCH(AC$47,$B$131:$E$131,0)),0)} -> 0 | AD143: {=$A143*IFERROR(INDEX($B143:$E143,,MATCH(AD$47,$B$131:$E$131,0)),0)} -> 0 | AE143: {=$A143*IFERROR(INDEX($B143:$E143,,MATCH(AE$47,$B$131:$E$131,0)),0)} -> 0 | AF143: {=$A143*IFERROR(INDEX($B143:$E143,,MATCH(AF$47,$B$131:$E$131,0)),0)} -> 46248000
A144: 0.045 | B144: 40800000000 | E144: 14500000000 | F144: 66500000000 | G144: 4000000000 | H144: 6000000000 | K144: 131800000000 | AC144: {=$A144*IFERROR(INDEX($B144:$E144,,MATCH(AC$47,$B$131:$E$131,0)),0)} -> 1836000000 | AD144: {=$A144*IFERROR(INDEX($B144:$E144,,MATCH(AD$47,$B$131:$E$131,0)),0)} -> 0 | AE144: {=$A144*IFERROR(INDEX($B144:$E144,,MATCH(AE$47,$B$131:$E$131,0)),0)} -> 0 | AF144: {=$A144*IFERROR(INDEX($B144:$E144,,MATCH(AF$47,$B$131:$E$131,0)),0)} -> 0
A145: 0.048 | I145: 11000000000 | K145: 11000000000 | AC145: {=$A145*IFERROR(INDEX($B145:$E145,,MATCH(AC$47,$B$131:$E$131,0)),0)} -> 0 | AD145: {=$A145*IFERROR(INDEX($B145:$E145,,MATCH(AD$47,$B$131:$E$131,0)),0)} -> 0 | AE145: {=$A145*IFERROR(INDEX($B145:$E145,,MATCH(AE$47,$B$131:$E$131,0)),0)} -> 0 | AF145: {=$A145*IFERROR(INDEX($B145:$E145,,MATCH(AF$47,$B$131:$E$131,0)),0)} -> 0
A146: VTB | B146: 449551182467 | C146: 7521354342 | D146: 5925568608 | E146: 100996854000 | F146: 100400000000 | G146: 6000000000 | H146: 9000000000 | I146: 32950000000 | K146: 712344959417 | AC146: {=$A146*IFERROR(INDEX($B146:$E146,,MATCH(AC$47,$B$131:$E$131,0)),0)} -> #VALUE! | AD146: {=$A146*IFERROR(INDEX($B146:$E146,,MATCH(AD$47,$B$131:$E$131,0)),0)} -> #VALUE! | AE146: {=$A146*IFERROR(INDEX($B146:$E146,,MATCH(AE$47,$B$131:$E$131,0)),0)} -> #VALUE! | AF146: {=$A146*IFERROR(INDEX($B146:$E146,,MATCH(AF$47,$B$131:$E$131,0)),0)} -> #VALUE!
A147: 0.047 | D147: 5925568608 | K147: 5925568608 | AC147: {=$A147*IFERROR(INDEX($B147:$E147,,MATCH(AC$47,$B$131:$E$131,0)),0)} -> 0 | AD147: {=$A147*IFERROR(INDEX($B147:$E147,,MATCH(AD$47,$B$131:$E$131,0)),0)} -> 0 | AE147: {=$A147*IFERROR(INDEX($B147:$E147,,MATCH(AE$47,$B$131:$E$131,0)),0)} -> 0 | AF147: {=$A147*IFERROR(INDEX($B147:$E147,,MATCH(AF$47,$B$131:$E$131,0)),0)} -> 0
A148: 0.043 | B148: 382550000000 | E148: 100996854000 | F148: 34000000000 | K148: 517546854000 | AC148: {=$A148*IFERROR(INDEX($B148:$E148,,MATCH(AC$47,$B$131:$E$131,0)),0)} -> 1.644965e+10 | AD148: {=$A148*IFERROR(INDEX($B148:$E148,,MATCH(AD$47,$B$131:$E$131,0)),0)} -> 0 | AE148: {=$A148*IFERROR(INDEX($B148:$E148,,MATCH(AE$47,$B$131:$E$131,0)),0)} -> 0 | AF148: {=$A148*IFERROR(INDEX($B148:$E148,,MATCH(AF$47,$B$131:$E$131,0)),0)} -> 0
A149: 0.045 | B149: 67001182467 | F149: 66400000000 | G149: 6000000000 | I149: 21050000000 | K149: 160451182467 | AC149: {=IFERROR(SUM(AC150)/INDEX($B149:$E149,,MATCH(AC$131,$B$131:$E$131,0)),0)} -> 0 | AD149: {=IFERROR(SUM(AD150)/INDEX($B149:$E149,,MATCH(AD$131,$B$131:$E$131,0)),0)} -> 0 | AE149: {=IFERROR(SUM(AE150)/INDEX($B149:$E149,,MATCH(AE$131,$B$131:$E$131,0)),0)} -> 0 | AF149: {=IFERROR(SUM(AF150)/INDEX($B149:$E149,,MATCH(AF$131,$B$131:$E$131,0)),0)} -> 0
A150: 0.029 | I150: 900000000 | K150: 900000000 | AC150: {=$A150*IFERROR(INDEX($B150:$E150,,MATCH(AC$47,$B$131:$E$131,0)),0)} -> 0 | AD150: {=$A150*IFERROR(INDEX($B150:$E150,,MATCH(AD$47,$B$131:$E$131,0)),0)} -> 0 | AE150: {=$A150*IFERROR(INDEX($B150:$E150,,MATCH(AE$47,$B$131:$E$131,0)),0)} -> 0 | AF150: {=$A150*IFERROR(INDEX($B150:$E150,,MATCH(AF$47,$B$131:$E$131,0)),0)} -> 0
A151: 0.042 | C151: 7521354342 | H151: 9000000000 | K151: 16521354342 | AC151: =(AC132*B132+AC139*B137++AC142*B142+AC149*B149)/B151 -> #DIV/0! | AD151: =(AD132*C132+AD139*C137++AD142*C142+AD149*C149)/C151 -> 0 | AE151: =(AE132*D132+AE139*D137++AE142*D142+AE149*D149)/D151 -> #DIV/0! | AF151: =(AF132*E132+AF139*E137++AF142*E142+AF149*E149)/E151 -> #DIV/0!
A152: 0.044 | I152: 11000000000 | K152: 11000000000
A153: SNP | B153: 16500000000 | C153: 5633098111 | F153: 40000000000 | K153: 62133098111
A154: 0.041 | F154: 20000000000 | K154: 20000000000
A155: 0.045 | F155: 20000000000 | K155: 20000000000
A156: 0.03 | C156: 5633098111 | K156: 5633098111
A157: 0.037 | B157: 16500000000 | K157: 16500000000
A158: VIB | I158: 2600000000 | K158: 2600000000
A159: 0.055 | I159: 2600000000 | K159: 2600000000
A160: KBANK | F160: 13700000000 | K160: 13700000000
A161: 0.046 | F161: 13700000000 | K161: 13700000000
A162: KEB Hana | B162: 4000000000 | K162: 4000000000
A163: 0.0475 | B163: 4000000000 | K163: 4000000000
A164: Woori Bank | B164: 17000000000 | K164: 17000000000
A165: 0.041 | B165: 17000000000 | K165: 17000000000
A166: Grand Total | B166: 683751182467 | C166: 17160452453 | D166: 5925568608 | E166: 125496854000 | F166: 375815000000 | G166: 19700000000 | H166: 15000000000 | I166: 81550000000 | J166: 10000000000 | K166: 1334399057528
A171: NAME | B171: (All)
A173: Sum of CLOSING BALANCE (VND) | B173: Column Labels
A174: Row Labels | B174: 1 month | C174: 3 months | D174: 6 months | E174: 12 months | F174: 2 months | G174: 4 months | H174: 7 months | I174: 5 months | J174: 13 months | K174: Grand Total | AC174: 1 month | AD174: 3 months | AE174: 6 months | AF174: 12 months | AG174: Grand Total
A175: BIDV | B175: 198900000000 | C175: 155215000000 | D175: 35000000000 | E175: 2878000000 | F175: 7000000000 | G175: 9700000000 | H175: 10000000000 | K175: 418693000000 | AB175: =A175 -> BIDV | AC175: {=IFERROR(SUM(AC176:AC179)/INDEX($B175:$E175,,MATCH(AC$174,$B$174:$E$174,0)),0)} -> 0.043568125 | AD175: {=IFERROR(SUM(AD176:AD179)/INDEX($B175:$E175,,MATCH(AD$174,$B$174:$E$174,0)),0)} -> 0.036302387 | AE175: {=IFERROR(SUM(AE176:AE179)/INDEX($B175:$E175,,MATCH(AE$174,$B$174:$E$174,0)),0)} -> 0.0332 | AF175: {=IFERROR(SUM(AF176:AF179)/INDEX($B175:$E175,,MATCH(AF$174,$B$174:$E$174,0)),0)} -> 0.02637943 | AG175: =(B175*AC175+C175*AD175+D175*AE175+E175*AF175)/F175 -> 2.2197564
A176: 0.046 | D176: 19000000000 | H176: 8000000000 | K176: 27000000000 | AC176: {=$A176*IFERROR(INDEX($B176:$E176,,MATCH(AC$47,$B$174:$E$174,0)),0)} -> 0 | AD176: {=$A176*IFERROR(INDEX($B176:$E176,,MATCH(AD$47,$B$174:$E$174,0)),0)} -> 0 | AE176: {=$A176*IFERROR(INDEX($B176:$E176,,MATCH(AE$47,$B$174:$E$174,0)),0)} -> 874000000 | AF176: {=$A176*IFERROR(INDEX($B176:$E176,,MATCH(AF$47,$B$174:$E$174,0)),0)} -> 0
A177: 0.052 | E177: 1460000000 | K177: 1460000000 | AC177: {=$A177*IFERROR(INDEX($B177:$E177,,MATCH(AC$47,$B$174:$E$174,0)),0)} -> 0 | AD177: {=$A177*IFERROR(INDEX($B177:$E177,,MATCH(AD$47,$B$174:$E$174,0)),0)} -> 0 | AE177: {=$A177*IFERROR(INDEX($B177:$E177,,MATCH(AE$47,$B$174:$E$174,0)),0)} -> 0 | AF177: {=$A177*IFERROR(INDEX($B177:$E177,,MATCH(AF$47,$B$174:$E$174,0)),0)} -> 75920000
A178: 0.043 | B178: 142400000000 | F178: 7000000000 | K178: 149400000000 | AC178: {=$A178*IFERROR(INDEX($B178:$E178,,MATCH(AC$47,$B$174:$E$174,0)),0)} -> 6.1232e+09 | AD178: {=$A178*IFERROR(INDEX($B178:$E178,,MATCH(AD$47,$B$174:$E$174,0)),0)} -> 0 | AE178: {=$A178*IFERROR(INDEX($B178:$E178,,MATCH(AE$47,$B$174:$E$174,0)),0)} -> 0 | AF178: {=$A178*IFERROR(INDEX($B178:$E178,,MATCH(AF$47,$B$174:$E$174,0)),0)} -> 0
A179: 0.045 | B179: 56500000000 | C179: 125215000000 | D179: 6400000000 | G179: 9700000000 | H179: 2000000000 | K179: 199815000000 | AC179: {=$A179*IFERROR(INDEX($B179:$E179,,MATCH(AC$47,$B$174:$E$174,0)),0)} -> 2542500000 | AD179: {=$A179*IFERROR(INDEX($B179:$E179,,MATCH(AD$47,$B$174:$E$174,0)),0)} -> 5634675000 | AE179: {=$A179*IFERROR(INDEX($B179:$E179,,MATCH(AE$47,$B$174:$E$174,0)),0)} -> 288000000 | AF179: {=$A179*IFERROR(INDEX($B179:$E179,,MATCH(AF$47,$B$174:$E$174,0)),0)} -> 0
A180: 0.048 | D180: 2500000000 | K180: 2500000000 | AB180: =A180 -> 0.048 | AC180: {=IFERROR(SUM(AC181)/INDEX($B180:$E180,,MATCH(AC$174,$B$174:$E$174,0)),0)} -> 0 | AD180: {=IFERROR(SUM(AD181)/INDEX($B182:$E182,,MATCH(AD$174,$B$174:$E$174,0)),0)} -> 0 | AE180: {=IFERROR(SUM(AE181)/INDEX($B182:$E182,,MATCH(AE$174,$B$174:$E$174,0)),0)} -> 0.017795455 | AF180: {=IFERROR(SUM(AF181)/INDEX($B182:$E182,,MATCH(AF$174,$B$174:$E$174,0)),0)} -> 0 | AG180: =(B180*AC180+C180*AD180+D180*AE180+E180*AF180)/F180 -> #DIV/0!
A181: 0.029 | D181: 2700000000 | K181: 2700000000 | AC181: {=$A181*IFERROR(INDEX($B181:$E181,,MATCH(AC$47,$B$174:$E$174,0)),0)} -> 0 | AD181: {=$A181*IFERROR(INDEX($B181:$E181,,MATCH(AD$47,$B$174:$E$174,0)),0)} -> 0 | AE181: {=$A181*IFERROR(INDEX($B181:$E181,,MATCH(AE$47,$B$174:$E$174,0)),0)} -> 78300000 | AF181: {=$A181*IFERROR(INDEX($B181:$E181,,MATCH(AF$47,$B$174:$E$174,0)),0)} -> 0
A182: 0.042 | D182: 4400000000 | E182: 1418000000 | K182: 5818000000 | AB182: =A182 -> 0.042 | AC182: {=IFERROR(SUM(AC183:AC185)/INDEX($B182:$E182,,MATCH(AC$174,$B$174:$E$174,0)),0)} -> 0 | AD182: {=IFERROR(SUM(AD183:AD185)/INDEX($B182:$E182,,MATCH(AD$174,$B$174:$E$174,0)),0)} -> 0 | AE182: {=IFERROR(SUM(AE183:AE185)/INDEX($B182:$E182,,MATCH(AE$174,$B$174:$E$174,0)),0)} -> 0 | AF182: {=IFERROR(SUM(AF183:AF185)/INDEX($B182:$E182,,MATCH(AF$174,$B$174:$E$174,0)),0)} -> 0 | AG182: =(B182*AC182+C182*AD182+D182*AE182+E182*AF182)/F182 -> #DIV/0!
A183: 0.044 | C183: 30000000000 | K183: 30000000000 | AC183: {=$A183*IFERROR(INDEX($B183:$E183,,MATCH(AC$47,$B$174:$E$174,0)),0)} -> 0 | AD183: {=$A183*IFERROR(INDEX($B183:$E183,,MATCH(AD$47,$B$174:$E$174,0)),0)} -> 1320000000 | AE183: {=$A183*IFERROR(INDEX($B183:$E183,,MATCH(AE$47,$B$174:$E$174,0)),0)} -> 0 | AF183: {=$A183*IFERROR(INDEX($B183:$E183,,MATCH(AF$47,$B$174:$E$174,0)),0)} -> 0
A184: VCB | B184: 997900000000 | C184: 66500000000 | D184: 11000000000 | E184: 1228000000 | F184: 17500000000 | G184: 4000000000 | I184: 6000000000 | K184: 1104128000000 | AC184: {=$A184*IFERROR(INDEX($B184:$E184,,MATCH(AC$47,$B$174:$E$174,0)),0)} -> #VALUE! | AD184: {=$A184*IFERROR(INDEX($B184:$E184,,MATCH(AD$47,$B$174:$E$174,0)),0)} -> #VALUE! | AE184: {=$A184*IFERROR(INDEX($B184:$E184,,MATCH(AE$47,$B$174:$E$174,0)),0)} -> #VALUE! | AF184: {=$A184*IFERROR(INDEX($B184:$E184,,MATCH(AF$47,$B$174:$E$174,0)),0)} -> #VALUE!
...

Sheet USD_yield
A2: ="Total USD of BWID Group as at "&TEXT(Summary!B6,"dd mmm yyyy")&" is USD"&TEXT(H33/1000000,"$#,###.00")&"mn, gaining an average yield of 1-2% p.a" -> Total USD of BWID Group as at 15 Jan 2026 is USD$,06567mn, gaining an average yield of 1-2% p.a
A3: Due to SBV regulations, the Banks onlt offer BW 0% on USD deposit. To improve the yield of USD given the depreciation of VND against USD:
A4: (i) Keep USD balance at existing lender and convert to VND equal to cash shortage of next 3 months
A5: (ii) Offet with the lending VND interest rate from 1% - 1.5% p.a subject to volume and timeline commitment
H6: =H33-Summary!C18*1000000 -> 0
A7: Original Currency: USD | B7: BWID JSC | C7: Yield | D7: VC3 | E7: Yield | F7: Subsidiaries | G7: Yield | H7: Total (USD) | I7: Weighted average deposit rate | J7: Remark
A8: No yield USD deposit | B8: =SUM(B9:B20) -> 19468.47 | C8: =SUMPRODUCT(B9:B20,C9:C20)/B8 -> 0 | D8: =SUM(D9:D20) -> 9629.06 | E8: =SUMPRODUCT(D9:D20,E9:E20)/D8 -> 0 | F8: =SUM(F9:F20) -> 36570.06 | G8: =SUMPRODUCT(F9:F20,G9:G20)/F8 -> 0 | H8: =SUM(B8,D8,F8) -> 65667.59 | I8: =IFERROR((B8*C8+D8*E8+F8*G8)/H8,0) -> 0
A9: VTB | B9: =SUMIFS('Cash Balance'!$T$4:$T$920,'Cash Balance'!$X$4:$X$920,USD_yield!$A9,'Cash Balance'!$W$4:$W$920,USD_yield!B$7)-B22 -> 3421.25 | C9: 0 | D9: =SUMIFS('Cash Balance'!$T$4:$T$920,'Cash Balance'!$X$4:$X$920,USD_yield!$A9,'Cash Balance'!$W$4:$W$920,USD_yield!D$7)-D22 -> 2792.51 | E9: 0 | F9: =SUMIFS('Cash Balance'!$T$4:$T$920,'Cash Balance'!$X$4:$X$920,USD_yield!$A9,'Cash Balance'!$W$4:$W$920,USD_yield!F$7)-F22 -> 30673.31 | G9: 0 | H9: =SUM(B9,D9,F9) -> 36887.07 | I9: =IFERROR((B9*C9+D9*E9+F9*G9)/H9,0) -> 0 | J9: Demand cash at VC3 and Booking fee/deposits of tenants
A10: VCB | B10: =SUMIFS('Cash Balance'!$T$4:$T$920,'Cash Balance'!$X$4:$X$920,USD_yield!$A10,'Cash Balance'!$W$4:$W$920,USD_yield!B$7)-B23 -> 1711.05 | C10: 0 | D10: =SUMIFS('Cash Balance'!$T$4:$T$920,'Cash Balance'!$X$4:$X$920,USD_yield!$A10,'Cash Balance'!$W$4:$W$920,USD_yield!D$7)-D23 -> 698.7 | E10: 0 | F10: =SUMIFS('Cash Balance'!$T$4:$T$920,'Cash Balance'!$X$4:$X$920,USD_yield!$A10,'Cash Balance'!$W$4:$W$920,USD_yield!F$7)-F23 -> 5589.32 | G10: 0 | H10: =SUM(B10,D10,F10) -> 7999.07 | I10: =IFERROR((B10*C10+D10*E10+F10*G10)/H10,0) -> 0 | J10: Booking fee/deposits of tenants
A11: BIDV | B11: =SUMIFS('Cash Balance'!$T$4:$T$920,'Cash Balance'!$X$4:$X$920,USD_yield!$A11,'Cash Balance'!$W$4:$W$920,USD_yield!B$7)-B24 -> 64.8 | C11: 0 | D11: =SUMIFS('Cash Balance'!$T$4:$T$920,'Cash Balance'!$X$4:$X$920,USD_yield!$A11,'Cash Balance'!$W$4:$W$920,USD_yield!D$7)-D24 -> 211.61 | E11: 0 | F11: =SUMIFS('Cash Balance'!$T$4:$T$920,'Cash Balance'!$X$4:$X$920,USD_yield!$A11,'Cash Balance'!$W$4:$W$920,USD_yield!F$7)-F24 -> 302.69 | G11: 0 | H11: =SUM(B11,D11,F11) -> 579.1 | I11: =IFERROR((B11*C11+D11*E11+F11*G11)/H11,0) -> 0 | J11: Booking fee/deposits of tenants
A12: VIB | B12: =SUMIFS('Cash Balance'!$T$4:$T$920,'Cash Balance'!$X$4:$X$920,USD_yield!$A12,'Cash Balance'!$W$4:$W$920,USD_yield!B$7)-B25 -> 51.6 | C12: 0 | D12: =SUMIFS('Cash Balance'!$T$4:$T$920,'Cash Balance'!$X$4:$X$920,USD_yield!$A12,'Cash Balance'!$W$4:$W$920,USD_yield!D$7)-D25 -> 100 | E12: 0 | F12: =SUMIFS('Cash Balance'!$T$4:$T$920,'Cash Balance'!$X$4:$X$920,USD_yield!$A12,'Cash Balance'!$W$4:$W$920,USD_yield!F$7)-F25 -> 0 | G12: 0 | H12: =SUM(B12,D12,F12) -> 151.6 | I12: =IFERROR((B12*C12+D12*E12+F12*G12)/H12,0) -> 0
A13: OCB | B13: =SUMIFS('Cash Balance'!$T$4:$T$920,'Cash Balance'!$X$4:$X$920,USD_yield!$A13,'Cash Balance'!$W$4:$W$920,USD_yield!B$7)-B26 -> 150 | C13: 0 | D13: =SUMIFS('Cash Balance'!$T$4:$T$920,'Cash Balance'!$X$4:$X$920,USD_yield!$A13,'Cash Balance'!$W$4:$W$920,USD_yield!D$7)-D26 -> 100 | E13: 0 | F13: =SUMIFS('Cash Balance'!$T$4:$T$920,'Cash Balance'!$X$4:$X$920,USD_yield!$A13,'Cash Balance'!$W$4:$W$920,USD_yield!F$7)-F26 -> 0 | G13: 0 | H13: =SUM(B13,D13,F13) -> 250 | I13: =IFERROR((B13*C13+D13*E13+F13*G13)/H13,0) -> 0
A14: MBB | B14: =SUMIFS('Cash Balance'!$T$4:$T$920,'Cash Balance'!$X$4:$X$920,USD_yield!$A14,'Cash Balance'!$W$4:$W$920,USD_yield!B$7)-B27 -> 0 | C14: 0 | D14: =SUMIFS('Cash Balance'!$T$4:$T$920,'Cash Balance'!$X$4:$X$920,USD_yield!$A14,'Cash Balance'!$W$4:$W$920,USD_yield!D$7)-D27 -> 90 | E14: 0 | F14: =SUMIFS('Cash Balance'!$T$4:$T$920,'Cash Balance'!$X$4:$X$920,USD_yield!$A14,'Cash Balance'!$W$4:$W$920,USD_yield!F$7)-F27 -> 0 | G14: 0 | H14: =SUM(B14,D14,F14) -> 90 | I14: =IFERROR((B14*C14+D14*E14+F14*G14)/H14,0) -> 0
A15: DB - Singapore | B15: =SUMIFS('Cash Balance'!$T$4:$T$920,'Cash Balance'!$X$4:$X$920,USD_yield!$A15,'Cash Balance'!$W$4:$W$920,USD_yield!B$7)-B28 -> 0 | C15: 0 | E15: 0 | F15: =SUMIFS('Cash Balance'!$T$4:$T$920,'Cash Balance'!$X$4:$X$920,USD_yield!$A15,'Cash Balance'!$W$4:$W$920,USD_yield!F$7)-F28 -> 0 | G15: 0 | H15: =SUM(B15,D15,F15) -> 0 | I15: =IFERROR((B15*C15+D15*E15+F15*G15)/H15,0) -> 0
A16: SNP | B16: =SUMIFS('Cash Balance'!$T$4:$T$920,'Cash Balance'!$X$4:$X$920,USD_yield!$A16,'Cash Balance'!$W$4:$W$920,USD_yield!B$7)-B29 -> 13119.74 | C16: 0 | D16: =SUMIFS('Cash Balance'!$T$4:$T$920,'Cash Balance'!$X$4:$X$920,USD_yield!$A16,'Cash Balance'!$W$4:$W$920,USD_yield!D$7)-D29 -> 0 | E16: 0 | F16: =SUMIFS('Cash Balance'!$T$4:$T$920,'Cash Balance'!$X$4:$X$920,USD_yield!$A16,'Cash Balance'!$W$4:$W$920,USD_yield!F$7)-F29 -> 0 | G16: 0 | H16: =SUM(B16,D16,F16) -> 13119.74 | I16: =IFERROR((B16*C16+D16*E16+F16*G16)/H16,0) -> 0 | J16: for commitment
A17: Keb Hana | B17: =SUMIFS('Cash Balance'!$T$4:$T$920,'Cash Balance'!$X$4:$X$920,USD_yield!$A17,'Cash Balance'!$W$4:$W$920,USD_yield!B$7)-B30 -> 0 | C17: 0 | D17: =SUMIFS('Cash Balance'!$T$4:$T$920,'Cash Balance'!$X$4:$X$920,USD_yield!$A17,'Cash Balance'!$W$4:$W$920,USD_yield!D$7)-D30 -> 0 | E17: 0 | F17: =SUMIFS('Cash Balance'!$T$4:$T$920,'Cash Balance'!$X$4:$X$920,USD_yield!$A17,'Cash Balance'!$W$4:$W$920,USD_yield!F$7)-F30 -> 0 | G17: 0 | H17: =SUM(B17,D17,F17) -> 0 | I17: =IFERROR((B17*C17+D17*E17+F17*G17)/H17,0) -> 0
A18: UOB | B18: =SUMIFS('Cash Balance'!$T$4:$T$920,'Cash Balance'!$X$4:$X$920,USD_yield!$A18,'Cash Balance'!$W$4:$W$920,USD_yield!B$7)-B31 -> 950 | C18: 0 | D18: =SUMIFS('Cash Balance'!$T$4:$T$920,'Cash Balance'!$X$4:$X$920,USD_yield!$A18,'Cash Balance'!$W$4:$W$920,USD_yield!D$7)-D31 -> 5636.24 | E18: 0 | F18: =SUMIFS('Cash Balance'!$T$4:$T$920,'Cash Balance'!$X$4:$X$920,USD_yield!$A18,'Cash Balance'!$W$4:$W$920,USD_yield!F$7)-F31 -> 0 | G18: 0 | H18: =SUM(B18,D18,F18) -> 6586.24 | I18: =IFERROR((B18*C18+D18*E18+F18*G18)/H18,0) -> 0 | J18: Sao Hoa's ISRA of Corporate Loan
A19: Standard Chartered | B19: =SUMIFS('Cash Balance'!$T$4:$T$920,'Cash Balance'!$X$4:$X$920,USD_yield!$A19,'Cash Balance'!$W$4:$W$920,USD_yield!B$7)-B32 -> 0 | C19: 0 | D19: =SUMIFS('Cash Balance'!$T$4:$T$920,'Cash Balance'!$X$4:$X$920,USD_yield!$A19,'Cash Balance'!$W$4:$W$920,USD_yield!D$7)-D32 -> 0 | E19: 0 | F19: =SUMIFS('Cash Balance'!$T$4:$T$920,'Cash Balance'!$X$4:$X$920,USD_yield!$A19,'Cash Balance'!$W$4:$W$920,USD_yield!F$7)-F32 -> 4.74 | G19: 0 | H19: =SUM(B19,D19,F19) -> 4.74 | I19: =IFERROR((B19*C19+D19*E19+F19*G19)/H19,0) -> 0
A20: Others | B20: =SUMIFS('Cash Balance'!$T$4:$T$920,'Cash Balance'!$X$4:$X$920,USD_yield!$A20,'Cash Balance'!$W$4:$W$920,USD_yield!B$7)-B32 -> 0.03 | C20: 0 | D20: =SUMIFS('Cash Balance'!$T$4:$T$920,'Cash Balance'!$X$4:$X$920,USD_yield!$A20,'Cash Balance'!$W$4:$W$920,USD_yield!D$7)-D32-D15-D28 -> 0 | E20: 0 | F20: =SUMIFS('Cash Balance'!$T$4:$T$920,'Cash Balance'!$X$4:$X$920,USD_yield!$A20,'Cash Balance'!$W$4:$W$920,USD_yield!F$7)-F32 -> 0 | G20: 0 | H20: =SUM(B20,D20,F20) -> 0.03 | I20: =IFERROR((B20*C20+D20*E20+F20*G20)/H20,0) -> 0
A21: Yield USD deposit | B21: =SUM(B22:B32) -> 0 | C21: =IFERROR(SUMPRODUCT(B22:B32,C22:C32)/B21,0) -> 0 | D21: =SUM(D22:D32) -> 0 | E21: =IFERROR(SUMPRODUCT(D22:D32,E22:E32)/D21,0) -> 0 | F21: =SUM(F22:F32) -> 0 | G21: =IFERROR(SUMPRODUCT(F22:F32,G22:G32)/F21,0) -> 0 | H21: =SUM(B21,D21,F21) -> 0 | I21: =IFERROR((B21*C21+D21*E21+F21*G21)/H21,0) -> 0
A22: VTB | C22: 0.011 | E22: 0.011 | G22: 0.011 | H22: =SUM(B22,D22,F22) -> 0 | I22: =IFERROR((B22*C22+D22*E22+F22*G22)/H22,0) -> 0
A23: VCB | C23: 0.011 | H23: =SUM(B23,D23,F23) -> 0 | I23: =IFERROR((B23*C23+D23*E23+F23*G23)/H23,0) -> 0
A24: BIDV | C24: 0.011 | E24: 0.011 | H24: =SUM(B24,D24,F24) -> 0 | I24: =IFERROR((B24*C24+D24*E24+F24*G24)/H24,0) -> 0
A25: VIB | H25: =SUM(B25,D25,F25) -> 0 | I25: =IFERROR((B25*C25+D25*E25+F25*G25)/H25,0) -> 0
A26: OCB | H26: =SUM(B26,D26,F26) -> 0 | I26: =IFERROR((B26*C26+D26*E26+F26*G26)/H26,0) -> 0
A27: MBB | H27: =SUM(B27,D27,F27) -> 0 | I27: =IFERROR((B27*C27+D27*E27+F27*G27)/H27,0) -> 0
A28: DB - Singapore | D28: =SUMIFS('Cash Balance'!$T$4:$T$920,'Cash Balance'!$B$4:$B$920,USD_yield!$A28,'Cash Balance'!$W$4:$W$920,USD_yield!D$7) -> 0 | E28: 0.0275 | H28: =SUM(B28,D28,F28) -> 0 | I28: =IFERROR((B28*C28+D28*E28+F28*G28)/H28,0) -> 0 | J28: DSRA for Corporate Loan
A29: SNP | H29: =SUM(B29,D29,F29) -> 0 | I29: =IFERROR((B29*C29+D29*E29+F29*G29)/H29,0) -> 0
A30: Keb Hana | H30: =SUM(B30,D30,F30) -> 0 | I30: =IFERROR((B30*C30+D30*E30+F30*G30)/H30,0) -> 0
A31: UOB | D31: =SUMIFS('Cash Balance'!$T$4:$T$920,'Cash Balance'!$B$4:$B$920,USD_yield!$A31,'Cash Balance'!$W$4:$W$920,USD_yield!D$7) -> 0 | H31: =SUM(B31,D31,F31) -> 0 | I31: =IFERROR((B31*C31+D31*E31+F31*G31)/H31,0) -> 0
A32: Others | H32: =SUM(B32,D32,F32) -> 0 | I32: =IFERROR((B32*C32+D32*E32+F32*G32)/H32,0) -> 0
A33: Total | B33: =SUM(B8,B21) -> 19468.47 | C33: =(B8*C8+B21*C21)/B33 -> 0 | D33: =SUM(D8,D21) -> 9629.06 | E33: =(D8*E8+D21*E21)/D33 -> 0 | F33: =SUM(F8,F21) -> 36570.06 | G33: =(F8*G8+F21*G21)/F33 -> 0 | H33: =SUM(H8,H21) -> 65667.59 | I33: =IFERROR((B33*C33+D33*E33+F33*G33)/H33,0) -> 0
A34: % | B34: =B33/H33 -> 0.29646999 | D34: =D33/$H$33 -> 0.14663337 | F34: =F33/H33 -> 0.55689664 | H34: =H33/H33 -> 1
B35: =B33=Summary!C15*1000000 -> TRUE | D35: =D33=Summary!C16*1000000 -> TRUE | F35: =F33-Summary!C17*1000000 -> 0 | H35: =H33-Summary!C18*1000000 -> 0
A37: DETAIL USD CASH
A39: ACCOUNT TYPE | B39: (Multiple Items)
A41: Sum of CLOSING BALANCE (USD) | B41: Column Labels
A42: Row Labels | B42: BWID JSC | C42: VC3 | D42: Subsidiaries | E42: Grand Total
A43: BIDV | B43: 73.6 | C43: 220.41 | D43: 29839.5 | E43: 30133.51
A44: MBB | C44: 90 | E44: 90
A45: OCB | B45: 150 | C45: 100 | D45: 0 | E45: 250
A46: Others | B46: 0 | C46: 0 | D46: 0 | E46: 0
A47: VCB | B47: 1717.4 | C47: 705.3 | D47: 5645.87 | E47: 8068.57
A48: VIB | B48: 58.2 | C48: 100 | D48: 0 | E48: 158.2
A49: VTB | B49: 3421 | C49: 2792.51 | D49: 1162.84 | E49: 7376.35
A50: SNP | B50: 13120 | C50: 0 | D50: 0 | E50: 13120
A51: Standard Chartered | D51: 4.74 | E51: 4.74
A52: TCB | B52: 0 | C52: 0 | D52: 0 | E52: 0
A53: ACB | B53: 0 | C53: 0 | D53: 0 | E53: 0
A54: UOB | B54: 950 | C54: 6419.67 | D54: 0 | E54: 7369.67
A55: KEB Hana | B55: 0 | D55: 0 | E55: 0
A56: Grand Total | B56: 19490.2 | C56: 10427.89 | D56: 36652.95 | E56: 66571.04
A81: Sum of CLOSING BALANCE (USD) | B81: Column Labels
A82: Row Labels | B82: BWID JSC | C82: VC3 | D82: Subsidiaries | E82: Grand Total
A83: BIDV | B83: 73.6 | C83: 220.41 | D83: 29839.5 | E83: 30133.51
A84: Capital Account | D84: 0 | E84: 0
A85: Current Account | B85: 73.6 | C85: 220.41 | D85: 29839.5 | E85: 30133.51
A86: Foreign Loan | C86: 0 | D86: 0 | E86: 0
A87: Saving Account | B87: 0 | C87: 0 | D87: 0 | E87: 0
A88: MBB | C88: 90 | E88: 90
A89: Current Account | C89: 90 | E89: 90
A90: OCB | B90: 150 | C90: 100 | D90: 0 | E90: 250
A91: Current Account | B91: 150 | C91: 100 | D91: 0 | E91: 250
A92: Saving Account | D92: 0 | E92: 0
A93: Others | B93: 0 | C93: 0 | D93: 0 | E93: 0
A94: Current Account | B94: 0 | C94: 0 | D94: 0 | E94: 0
A95: Saving Account | D95: 0 | E95: 0
A96: VCB | B96: 1717.4 | C96: 705.3 | D96: 5645.87 | E96: 8068.57
A97: Capital Account | B97: 749 | E97: 749
A98: Current Account | B98: 968.4 | C98: 705.3 | D98: 5645.87 | E98: 7319.57
A99: Saving Account | B99: 0 | C99: 0 | D99: 0 | E99: 0
A100: VIB | B100: 58.2 | C100: 100 | D100: 0 | E100: 158.2
A101: Current Account | B101: 58.2 | C101: 100 | D101: 0 | E101: 158.2
A102: Saving Account | C102: 0 | D102: 0 | E102: 0
A103: VTB | B103: 3421 | C103: 2792.51 | D103: 1162.84 | E103: 7376.35
A104: Capital Account | D104: 0 | E104: 0
A105: Current Account | B105: 3421 | C105: 2792.51 | D105: 1162.84 | E105: 7376.35
A106: Foreign Loan | C106: 0 | E106: 0
A107: Saving Account | B107: 0 | C107: 0 | D107: 0 | E107: 0
A108: SNP | B108: 13120 | C108: 0 | D108: 0 | E108: 13120
A109: Current Account | B109: 13120 | C109: 0 | D109: 0 | E109: 13120
A110: Foreign Loan | D110: 0 | E110: 0
A111: Reserve Account | D111: 0 | E111: 0
A112: Saving Account | B112: 0 | C112: 0 | D112: 0 | E112: 0
A113: Standard Chartered | D113: 4.74 | E113: 4.74
A114: Capital Account | D114: 4.74 | E114: 4.74
A115: Current Account | D115: 0 | E115: 0
A116: TCB | B116: 0 | C116: 0 | D116: 0 | E116: 0
A117: Current Account | B117: 0 | C117: 0 | D117: 0 | E117: 0
A118: Saving Account | C118: 0 | E118: 0
A119: ACB | B119: 0 | C119: 0 | D119: 0 | E119: 0
A120: Current Account | B120: 0 | C120: 0 | D120: 0 | E120: 0
A121: UOB | B121: 950 | C121: 6419.67 | D121: 0 | E121: 7369.67
A122: Capital Account | D122: 0 | E122: 0
A123: Current Account | B123: 950 | C123: 0 | D123: 0 | E123: 950
A124: Foreign Loan | C124: 2118.73 | D124: 0 | E124: 2118.73
A125: Reserve Account | C125: 4300.94 | E125: 4300.94
A126: KEB Hana | B126: 0 | D126: 0 | E126: 0
A127: Current Account | B127: 0 | D127: 0 | E127: 0
A128: Saving Account | D128: 0 | E128: 0
...

Sheet Detail1
A1: Details for Sum of CLOSING BALANCE (USD) - ACCOUNT TYPE: Current Account, Bank: BIDV - LONG BIEN, NAME: Subsidiaries
A3: ENTITY | B3: BRANCH | C3: ACCOUNT NUMBER | D3: ACCOUNT TYPE | E3: CURRENCY | F3: OB_BS (VND) | G3: Dif | H3: OPENING BALANCE (VND) | I3: CASH IN - CREDIT (VND) | J3: CASH OUT - DEBIT (VND) | K3: NET AMOUNT (VND) | L3: CLOSING BALANCE (VND)2 | M3: CB_BS (VND) | N3: Dif2 | O3: OB_BS (USD) | P3: Dif3 | Q3: OPENING BALANCE (USD) | R3: CASH IN - CREDIT (USD) | S3: CASH OUT - DEBIT (USD) | T3: CLOSING BALANCE (USD) | U3: CB_BS (USD) | V3: Dif4 | W3: NAME | X3: Bank_1 | Y3: Bank
A4: BW NAM DINH VU | B4: BIDV - LONG BIEN | C4: 1500871050 | D4: Current Account | E4: VND | F4: #N/A | G4: #N/A | H4: 3932701297 | I4: 19282275292 | J4: 23033163273 | K4: -3750887981 | L4: 181813316 | M4: #N/A | N4: #N/A | O4: 0 | P4: 0 | Q4: 0 | R4: 0 | S4: 0 | T4: 0 | V4: 0 | W4: Subsidiaries | X4: BIDV | Y4: BIDV - LONG BIEN
A5: BW NAM DINH VU | B5: BIDV - LONG BIEN | C5: 1500019128 | D5: Current Account | E5: USD | H5: 0 | I5: 0 | J5: 0 | K5: 0 | L5: 0 | N5: 0 | O5: #N/A | P5: #N/A | Q5: 29669.21 | R5: 0 | S5: 0 | T5: 29669.21 | U5: #N/A | V5: #N/A | W5: Subsidiaries | X5: BIDV | Y5: BIDV - LONG BIEN

Sheet Total Cash
A1: ACCOUNT TYPE | B1: (All)
A3: Sum of CLOSING BALANCE (USD) | B3: Column Labels
A4: Row Labels | B4: BWID JSC | C4: VC3 | D4: Subsidiaries | E4: Grand Total
A5: VIETINBANK - TIEN SON | B5: 200 | C5: 438.53 | D5: 1162.84 | E5: 1801.37
A6: VIETINBANK - BINH DUONG + QM | B6: 1704 | C6: 1812.22 | D6: 0 | E6: 3516.22
A7: VIETINBANK - DONG SAI GON | B7: 769 | C7: 0 | D7: 0 | E7: 769
A8: VIETINBANK - CN1 | B8: 748 | C8: 541.76 | D8: 0 | E8: 1289.76
A9: VIETCOMBANK - HCM | B9: 1071.7 | C9: 95.8 | D9: 5645.87 | E9: 6813.37
A10: VIETCOMBANK - BA DINH | B10: 645.7 | C10: 609.5 | D10: 0 | E10: 1255.2
A11: BIDV - LONG BIEN | D11: 29660.41 | E11: 29660.41
A12: BIDV - NAM SAI GON | D12: 0 | E12: 0
A13: BIDV - THANH XUAN | B13: 73.6 | C13: 220.41 | D13: 179.09 | E13: 473.1
A14: OCB - BINH DUONG | B14: 150 | C14: 100 | D14: 0 | E14: 250
A15: MB - BAC SAI GON | C15: 90 | E15: 90
A16: VIB - HOI SO | B16: 58.2 | C16: 100 | D16: 0 | E16: 158.2
A17: SINOPAC | B17: 13120 | C17: 0 | D17: 0 | E17: 13120
A18: OTHERS | B18: 0 | C18: 0 | D18: 0 | E18: 0
A19: STANDARD CHARTERED | D19: 4.74 | E19: 4.74
A20: TECHCOMBANK | B20: 0 | C20: 0 | D20: 0 | E20: 0
A21: ACB - HCM | B21: 0 | C21: 0 | E21: 0
A22: ACB - SAI GON | D22: 0 | E22: 0
A23: UOB | B23: 950 | C23: 6419.67 | D23: 0 | E23: 7369.67
A24: KEB Hana - HCM | B24: 0 | D24: 0 | E24: 0
A25: VIETINBANK - TPHCM | C25: 0 | D25: 0 | E25: 0
A26: BIDV - GIA DINH | D26: 0 | E26: 0
A27: VIETCOMBANK - NAM BINH DUONG | D27: 0 | E27: 0
A28: VIETCOMBANK - BINH TAY | D28: 0 | E28: 0
A29: Grand Total | B29: 19490.2 | C29: 10427.89 | D29: 36652.95 | E29: 66571.04
A61: Sum of CLOSING BALANCE (USD) | B61: Column Labels
A62: Row Labels | B62: BWID JSC | C62: VC3 | D62: Subsidiaries | E62: Grand Total
A63: VIETINBANK - TIEN SON | B63: 200 | C63: 438.53 | D63: 1162.84 | E63: 1801.37
A64: Capital Account | D64: 0 | E64: 0
A65: Current Account | B65: 200 | C65: 438.53 | D65: 1162.84 | E65: 1801.37
A66: Escrow account | D66: 0 | E66: 0
A67: Saving Account | C67: 0 | D67: 0 | E67: 0
A68: VIETINBANK - BINH DUONG + QM | B68: 1704 | C68: 1812.22 | D68: 0 | E68: 3516.22
A69: Current Account | B69: 1704 | C69: 1812.22 | D69: 0 | E69: 3516.22
A70: Saving Account | B70: 0 | C70: 0 | D70: 0 | E70: 0
A71: VIETINBANK - DONG SAI GON | B71: 769 | C71: 0 | D71: 0 | E71: 769
A72: Current Account | B72: 769 | C72: 0 | D72: 0 | E72: 769
A73: Saving Account | D73: 0 | E73: 0
A74: VIETINBANK - CN1 | B74: 748 | C74: 541.76 | D74: 0 | E74: 1289.76
A75: Current Account | B75: 748 | C75: 541.76 | D75: 0 | E75: 1289.76
A76: Foreign Loan | C76: 0 | E76: 0
A77: Saving Account | C77: 0 | D77: 0 | E77: 0
A78: VIETCOMBANK - HCM | B78: 1071.7 | C78: 95.8 | D78: 5645.87 | E78: 6813.37
A79: Capital Account | B79: 749 | E79: 749
A80: Current Account | B80: 322.7 | C80: 95.8 | D80: 5645.87 | E80: 6064.37
A81: Saving Account | B81: 0 | C81: 0 | D81: 0 | E81: 0
A82: VIETCOMBANK - BA DINH | B82: 645.7 | C82: 609.5 | D82: 0 | E82: 1255.2
A83: Current Account | B83: 645.7 | C83: 609.5 | D83: 0 | E83: 1255.2
A84: Saving Account | C84: 0 | D84: 0 | E84: 0
A85: BIDV - LONG BIEN | D85: 29660.41 | E85: 29660.41
A86: Current Account | D86: 29660.41 | E86: 29660.41
A87: Saving Account | D87: 0 | E87: 0
A88: BIDV - NAM SAI GON | D88: 0 | E88: 0
A89: Current Account | D89: 0 | E89: 0
A90: Saving Account | D90: 0 | E90: 0
A91: BIDV - THANH XUAN | B91: 73.6 | C91: 220.41 | D91: 179.09 | E91: 473.1
A92: Capital Account | D92: 0 | E92: 0
A93: Current Account | B93: 73.6 | C93: 220.41 | D93: 179.09 | E93: 473.1
A94: Foreign Loan | C94: 0 | D94: 0 | E94: 0
A95: Saving Account | B95: 0 | C95: 0 | D95: 0 | E95: 0
A96: OCB - BINH DUONG | B96: 150 | C96: 100 | D96: 0 | E96: 250
A97: Current Account | B97: 150 | C97: 100 | D97: 0 | E97: 250
A98: Saving Account | D98: 0 | E98: 0
A99: MB - BAC SAI GON | C99: 90 | E99: 90
A100: Current Account | C100: 90 | E100: 90
A101: VIB - HOI SO | B101: 58.2 | C101: 100 | D101: 0 | E101: 158.2
A102: Current Account | B102: 58.2 | C102: 100 | D102: 0 | E102: 158.2
A103: Saving Account | C103: 0 | D103: 0 | E103: 0
A104: SINOPAC | B104: 13120 | C104: 0 | D104: 0 | E104: 13120
A105: Current Account | B105: 13120 | C105: 0 | D105: 0 | E105: 13120
A106: Foreign Loan | D106: 0 | E106: 0
A107: Reserve Account | D107: 0 | E107: 0
A108: Saving Account | B108: 0 | C108: 0 | D108: 0 | E108: 0
A109: OTHERS | B109: 0 | C109: 0 | D109: 0 | E109: 0
A110: Current Account | B110: 0 | C110: 0 | D110: 0 | E110: 0
A111: Saving Account | D111: 0 | E111: 0
A112: STANDARD CHARTERED | D112: 4.74 | E112: 4.74
A113: Capital Account | D113: 4.74 | E113: 4.74
A114: Current Account | D114: 0 | E114: 0
A115: Escrow account | D115: 0 | E115: 0
A116: TECHCOMBANK | B116: 0 | C116: 0 | D116: 0 | E116: 0
A117: Current Account | B117: 0 | C117: 0 | D117: 0 | E117: 0
A118: Saving Account | C118: 0 | E118: 0
A119: ACB - HCM | B119: 0 | C119: 0 | E119: 0
A120: Current Account | B120: 0 | C120: 0 | E120: 0
A121: ACB - SAI GON | D121: 0 | E121: 0
A122: Current Account | D122: 0 | E122: 0
A123: UOB | B123: 950 | C123: 6419.67 | D123: 0 | E123: 7369.67
A124: Capital Account | D124: 0 | E124: 0
A125: Current Account | B125: 950 | C125: 0 | D125: 0 | E125: 950
A126: Foreign Loan | C126: 2118.73 | D126: 0 | E126: 2118.73
A127: Reserve Account | C127: 4300.94 | E127: 4300.94
A128: KEB Hana - HCM | B128: 0 | D128: 0 | E128: 0
A129: Current Account | B129: 0 | D129: 0 | E129: 0
A130: Saving Account | D130: 0 | E130: 0
A131: VIETINBANK - TPHCM | C131: 0 | D131: 0 | E131: 0
A132: Current Account | C132: 0 | D132: 0 | E132: 0
...

Sheet Cash Planning
A1: CASH OUT | W1: CASH IN
C2: (1) | F2: (2) | H2: (3) = (1) + (2) | Y2: (4) | AB2: (5) | AD2: (6) = (4) + (5)
B3: VND | C3: Total Demand (in orginal VND) | E3: USD | F3: Total Demand (in orginal USD) | H3: Total Demand (USD equivalent) | X3: VND | Y3: Planned Cash-in (in orginal VND) | AA3: USD | AB3: Planned Cash-in (in orginal USD) | AD3: Total Planned Cash-in (USD equivalent)
B4: SHL | C4: =SUMIFS($C$15:$C$139,$K$15:$K$139,$B4,$J$15:$J$139,"PLANNED",$D$15:$D$139,$B$3) -> 243856187675 | E4: SHL | F4: =SUMIFS($C$15:$C$139,$K$15:$K$139,$B4,$J$15:$J$139,"PLANNED",$D$15:$D$139,$E$3,$G$15:$G$139,"W*") -> 0 | H4: =C4/Fx_rate+F4 -> 9316377.8 | X4: BWID JSC | Y4: =SUMIFS($Y$15:$Y$199,$AG$15:$AG$199,$X4&"*",$AF$15:$AF$199,"PLANNED",$Z$15:$Z$199,$X$3) -> 25024065387 | AA4: BWID JSC | AB4: =SUMIFS($Y$15:$Y$199,$AG$15:$AG$199,$X4&"*",$AF$15:$AF$199,"PLANNED",$Z$15:$Z$199,$AA$3,$AC$15:$AC$199,"W*") -> 0 | AD4: =Y4/Fx_rate+AB4 -> 956029.24
B5: Equity | C5: =SUMIFS($C$15:$C$139,$K$15:$K$139,$B5,$J$15:$J$139,"PLANNED",$D$15:$D$139,$B$3) -> 134864432522 | E5: Equity | F5: =SUMIFS($C$15:$C$139,$K$15:$K$139,$B5,$J$15:$J$139,"PLANNED",$D$15:$D$139,$E$3,$G$15:$G$139,"W*") -> 2996506.7 | H5: =C5/Fx_rate+F5 -> 8148920.5 | X5: VC3 | Y5: =SUMIFS($Y$15:$Y$199,$AG$15:$AG$199,$X5&"*",$AF$15:$AF$199,"PLANNED",$Z$15:$Z$199,$X$3) -> 1024275000000 | AA5: VC3 | AB5: =SUMIFS($Y$15:$Y$199,$AG$15:$AG$199,$X5&"*",$AF$15:$AF$199,"PLANNED",$Z$15:$Z$199,$AA$3,$AC$15:$AC$199,"W*") -> 0 | AD5: =Y5/Fx_rate+AB5 -> 39131805
B6: Bank Loan | C6: =SUMIFS($C$15:$C$139,$K$15:$K$139,$B6,$J$15:$J$139,"PLANNED",$D$15:$D$139,$B$3) -> 431132389718 | E6: Bank Loan | F6: =SUMIFS($C$15:$C$139,$K$15:$K$139,$B6,$J$15:$J$139,"PLANNED",$D$15:$D$139,$E$3,$G$15:$G$139,"W*") -> 0 | H6: =C6/Fx_rate+F6 -> 16471151 | X6: Subsidiaries | Y6: =SUMIFS($Y$15:$Y$199,$AG$15:$AG$199,$X6&"*",$AF$15:$AF$199,"PLANNED",$Z$15:$Z$199,$X$3) -> 351320924150 | AA6: Subsidiaries | AB6: =SUMIFS($Y$15:$Y$199,$AG$15:$AG$199,$X6&"*",$AF$15:$AF$199,"PLANNED",$Z$15:$Z$199,$AA$3,$AC$15:$AC$199,"W*") -> 0 | AD6: =Y6/Fx_rate+AB6 -> 13422003
B7: Contribution | C7: =SUMIFS($C$15:$C$139,$K$15:$K$139,$B7,$J$15:$J$139,"PLANNED",$D$15:$D$139,$B$3) -> 0 | E7: Contribution | F7: =SUMIFS($C$15:$C$139,$K$15:$K$139,$B7,$J$15:$J$139,"PLANNED",$D$15:$D$139,$E$3,$G$15:$G$139,"W*") -> 0 | H7: =C7/Fx_rate+F7 -> 0 | AD7: =Y7/Fx_rate+AB7 -> 0
B8: Total | C8: =SUM(C4:C7) -> 809853009915 | E8: Total | F8: =SUM(F4:F7) -> 2996506.7 | H8: =SUM(H4:H7) -> 33936450 | I8: Total | X8: Total | Y8: =SUM(Y4:Y6) -> 1400619989537 | AA8: Total | AB8: =SUM(AB4:AB6) -> 0 | AD8: =Y8/Fx_rate+AB8 -> 53509837
H9: =H8-H6 -> 17465298 | I9: Total excluded Bank loan (external source)
H10: =H9-H7 -> 17465298 | I10: Total excluded Bank loan & Internal contribution (NO cash outflow)
AK12: Internal transfer
E13: =SUBTOTAL(9,Table9[VND equivalent]) -> 8.8828657e+11 | F13: =E13/Fx -> 33936450 | AN13: =SUBTOTAL(9,AN15:AN26) -> 0 | AP13: =SUBTOTAL(9,AP15:AP26) -> 0 | AQ13: =AP13/Fx -> 0
A14: No.1 | B14: Entity | C14: Billed Amount | D14: Denoted Currency | E14: VND equivalent | F14: Description | G14: Expected date of payment | H14: Sub_type | I14: Type | J14: Status | K14: Source | L14: Transfer from | M14: Urgent | N14: Transfer Account | O14: Transfer Entity | P14: Transfer Branch | Q14: Receiving Account | R14: Receiving Entity | S14: Receiving Branch | W14: No.1 | X14: Entity | Y14: Billed Amount | Z14: Denoted Currency | AA14: VND equivalent | AB14: Description | AC14: Expected date of receipt | AD14: Sub_Type | AE14: Type | AF14: Status | AG14: Transfer to | AK14: No.1 | AL14: Entity | AM14: Transfer from2 | AN14: Billed Amount | AO14: Denoted Currency | AP14: VND equivalent | AQ14: Description | AR14: Expected date of transfer | AS14: Sub_Type | AT14: Type | AU14: Status | AV14: Transfer to
